Workbook
Name ac: '[1]ac code'!$B$2:$C$664
Name acc: '[2]Acc code'!$B$6:$C$774
Name accnt: '[3]ac code'!$B$3:$C$747
Name Account: [4]ACs!$B$4:$C$659
Name Account.: '[3]ac code'!$B$5:$C$757
Name Account1: #REF!
Name Account1: #REF!
Name Account1: #REF!
Name ACCOUNTCODE: '[5]Acc code'!$B$7:$C$971
Name Accounts: '[6]Acc code'!$B$5:$C$758
Name Accounts.: [7]ACs!$B$5:$C$758
Name AJ_AccCode: '[8]Adjusting Journal'!$H$8:$H$3507
Name AJ_Credit: '[8]Adjusting Journal'!$K$8:$K$3507
Name AJ_Date: '[8]Adjusting Journal'!$D$8:$D$3507
Name AJ_Debit: '[8]Adjusting Journal'!$J$8:$J$3507
Name Beg_Bal: #REF!
Name Beg_Bal: #REF!
Name Beg_Bal: #REF!
Name ChartofAccounts: '[8]Chart of Accounts'!$D$5:$D$163
Name ChartofAccountsTable: '[8]Chart of Accounts'!$D$5:$E$163
Name Chequeregistermay2025: #REF!
Name CJ_AccCode: '[8]Cash Journal'!$H$8:$H$3507
Name CJ_Credit: '[8]Cash Journal'!$K$8:$K$3507
Name CJ_Cust_Supplier: '[8]Cash Journal'!$F$8:$F$3507
Name CJ_Date: '[8]Cash Journal'!$D$8:$D$3507
Name CJ_Debit: '[8]Cash Journal'!$J$8:$J$3507
Name CJ_maxdate: '[8]Cash Journal'!$F$4
Name COD: '[9]Ac Code'!$B$1:$C$726
Name CODE: '[9]Ac Code'!$B$1:$C$726
Name Code..: '[5]Acc code'!$B$4:$C$770
Name codes: [10]Sheet2!$B$4:$C$758
Name Codess: '[11]acc code'!$B$6:$C$760
Name Cum_Int: #REF!
Name Cum_Int: #REF!
Name Cum_Int: #REF!
Name CustomerCode: [8]Customer!$F$8:$F$107
Name darc: [12]Utilization!#REF!
Name darc: [12]Utilization!#REF!
Name darc: [12]Utilization!#REF!
Name Data: #REF!
Name Data: #REF!
Name Data: #REF!
Name DEPARTMENT: '[13]dept code'!$B$3:$C$13
Name dept: [14]Dept!$B$3:$C$10
Name dept1: [14]Dept!$B$3:$C$10
Name DEPT2: [9]Dept!$A$3:$B$11
Name Deptment1: '[15]dept code'!$B$3:$C$18
Name DPRT: [16]Dept!$B$3:$C$11
Name dptmnt: '[17]dpt code'!$A$2:$B$10
Name DS: [18]Dept!$B$4:$C$85
Name DummyBukuBesar: '[8]Dummy GL'!$C$3:$L$17502
Name EmployeeID: [8]Employee!$E$9:$E$108
Name End_Bal: #REF!
Name End_Bal: #REF!
Name End_Bal: #REF!
Name Excel_BuiltIn_Print_Area_11: #REF!
Name Excel_BuiltIn_Print_Area_11: #REF!
Name Excel_BuiltIn_Print_Area_11: #REF!
Name Excel_BuiltIn_Print_Area_12: #REF!
Name Excel_BuiltIn_Print_Area_12: #REF!

Sheet Company Code
A1: CODE | B1: NAME OF THE COMPANY | C1: TYPE
A2: MGL001 | B2: Mbogo Mining and General Supply Limited | C2: MINING
A3: NCL001 | B3: Nile Complex Plaza Limited | C3: FUEL
A4: NFL001 | B4: Nyashishi Finance Limited | C4: FINANCE
A5: NIL001 | B5: Nibengo Insurance Limited | C5: INSUARANCE
A6: BAN001 | B6: Barnabas Athanas Nibengo | C6: PROPRIETOR
A7: NHL001 | B7: NILE Holding Limited | C7: HOLDING

Sheet Business Code
A1: CODE | B1: NAME OF COMPANY | C1: CODE | D1: NAME OF BUSINESS UNITS | E1: TYPE
A2: MGL001 | B2: Mbogo Mining and General Supply Limited | C2: MGL0011 | D2: MANUFACTUREING OF COMMERCIAL EXPLOSIVES | E2: MANUFACTURING
C3: MGL0012 | D3: TRADING OF COMERCIAL EXPLOSIVES | E3: TRADING
C4: MGL0013 | D4: BLASTING AND DRILLING SERVICES | E4: SERVICE
C5: MGL0014 | D5: GENERAL SUPPLY | E5: TRADING
A6: NCL001 | B6: Nile Complex Plaza Limited | C6: NCL0011 | D6: NILE OIL: TRADING OF PETROLEUM PRODUCTS
C7: NCL0012 | D7: NILE PUB: TRADING OF FOODS AND DRINKS
C8: NCL0013 | D8: NILE GARAGE: SPARE PARTS, CAR WASH MANTENANCE AND REPAIR SERVICES
C9: NCL0014 | D9: NILE FINANCIAL HUB: CASH POINT SERVICES
A10: NFL001 | B10: Nyashishi Finance Limited | C10: NFL0011 | D10: SMALL AND MEDIUM ENTERPRISES LOAN
C11: NFL0012 | D11: SALARIED WORKERS LOAN
C12: NFL0013 | D12: ASSET LOAN
A13: NIL001 | B13: Nibengo Insurance Limited | C13: NIL0011 | D13: MOTOR VEHICLE INSURANCE
C14: NIL0012 | D14: MOTOR CYCLE INSURANCE
C15: NIL0013 | D15: FIRE INSURANCE
C16: NIL0014 | D16: LIFE INSURANCE
A17: BAN001 | B17: Barnabas Athanas Nibengo | C17: BAN0011 | D17: MAKOROBOI SHOP BEAUTY PRODUCTIS
C18: BAN0012 | D18: NILE SATO SANGALA SHOP
C19: BAN0013 | D19: NILE FRESH SPRINGS WATER

Sheet Location Code Code
A1: CODE | B1: NAME OF COMPANY | C1: CODE | D1: NAME OF BUSINESS UNITS | E1: CODE | F1: NAME OF SALES POINT
A2: MGL001 | B2: Mbogo Mining and General Supply Limited | C2: MGL0011 | D2: MANUFACTURING OF COMMERCIAL EXPLOSIVES | E2: MGL00111 | F2: IHAYABUYAGA MAGU MWANZA
C3: MGL0012 | D3: TRADING OF COMERCIAL EXPLOSIVES | E3: MGL00121 | F3: HEAD OFFICE NYASHISHI MWANZA
E4: MGL00122 | F4: MERERANI MERERANI MANYARA
E5: MGL00123 | F5: MBEZI LUISI UBUNGO DAR ES SALAAM
E6: MGL00124 | F6: RUANDA MBINGA RUVUMA
C7: MGL0013 | D7: BLASTING AND DRILLING SERVICES | E7: MGL00131 | F7: HEAD OFFICE NYASHISHI MWANZA
C8: MGL0014 | D8: GENERAL SUPPLY | E8: MGL00141 | F8: HEAD OFFICE NYASHISHI MWANZA
A9: NCL001 | B9: Nile Complex Plaza Limited | C9: NCL0011 | D9: NILE OIL: TRADING OF PETROLEUM PRODUCTS | E9: NCL00111 | F9: HEAD OFFICE NYASHISHI MWANZA
C10: NCL0012 | D10: NILE PUB: TRADING OF FOODS AND DRINKS | E10: NCL00112 | F10: HEAD OFFICE NYASHISHI MWANZA
C11: NCL0013 | D11: NILE GARAGE: SPARE PARTS, CAR WASH AND SERVICES | E11: NCL00113 | F11: HEAD OFFICE NYASHISHI MWANZA
C12: NCL0014 | D12: NILE FINANCIAL HUB: CASH POINT | E12: NCL00114 | F12: HEAD OFFICE NYASHISHI MWANZA
A13: NFL001 | B13: Nyashishi Finance Limited | C13: NFL0011 | D13: SMALL AND MEDIUM ENTERPRISES LOAN | E13: NFL00111 | F13: HEAD OFFICE NYASHISHI MWANZA
C14: NFL0012 | D14: SALARIED WORKERS LOAN | E14: NFL00112 | F14: HEAD OFFICE NYASHISHI MWANZA
C15: NFL0013 | D15: ASSET LOAN | E15: NFL00113 | F15: HEAD OFFICE NYASHISHI MWANZA
A16: NIL001 | B16: Nibengo Insurance Limited | C16: NIL0011 | D16: MOTOR VEHICLE INSURANCE | E16: NIL00111 | F16: HEAD OFFICE NYASHISHI MWANZA
C17: NIL0012 | D17: MOTOR CYCLE INSURANCE | E17: NIL00112 | F17: HEAD OFFICE NYASHISHI MWANZA
C18: NIL0013 | D18: FIRE INSURANCE | E18: NIL00113 | F18: HEAD OFFICE NYASHISHI MWANZA
C19: NIL0014 | D19: LIFE INSURANCE | E19: NIL00114 | F19: HEAD OFFICE NYASHISHI MWANZA
A20: BAN001 | B20: Barnabas Athanas Nibengo | C20: BAN0011 | D20: NILE FRESH SPRINGS WATER | E20: BAN00131 | F20: RUANDA MBINGA RUVUMA
C21: BAN0012 | D21: NILE SATO SANGALA | E21: BAN00121 | F21: MBEZI LUISI UBUNGO DAR ES SALAAM
E22: BAN00122 | F22: USAGARA MISUNGWI MWANZA

Sheet Department  Codes
A1: CODE | B1: NAME OF DEPARTMENT
A2: FAD001 | B2: Finance and Administration Department
A3: PRD001 | B3: Production Department
A4: BDD001 | B4: Business Development Department
D203: =VLOOKUP(#REF!,'Department Codes'!A2:B4,2,FALSE) -> #REF!

Sheet Section Code
A1: Department Code | B1: Section Code | C1: Name of Section
A2: ='Department Codes'!A2 -> FAD001 | B2: FAD00101 | C2: General Administration Section
A3: ='Department Codes'!B2 -> Finance and Administration Department | B3: FAD00102 | C3: Finance Section
B4: FAD00103 | C4: Microfinance Section
B5: FAD00104 | C5: Insurance Section
B6: FAD00105 | C6: Information Communication Technology Department
B7: FAD00106 | C7: Internal Audit and Control Section
A9: ='Department Codes'!A3 -> PRD001 | B9: PRD00101 | C9: Manufacturing of Commercial Explosive Section
A10: ='Department Codes'!B3 -> Production Department | B10: PRD00102 | C10: Drilling and Blasting Section
B11: PRD00103 | C11: Water Supply Section
B12: PRD00104 | C12: Construction section
B13: PRD00105 | C13: Technology Transfer Research and Innovation section
A15: ='Department Codes'!A4 -> BDD001 | B15: BDD00101 | C15: General Supply Section
A16: ='Department Codes'!B4 -> Business Development Department | B16: BDD00102 | C16: Sales and Marketing Section
B17: BDD00103 | C17: Logistic and freight Management Section
B18: BDD00104 | C18: Store Management Section

Sheet Improved Accounting codes
A3: ENGLISH | B3: ENGLISH | C3: ENGLISH
A4: LIST | B4: LIST OF ACCOUNTS OF THE REVISED CH OF ACCOUNTS | C4: LIST
A5: Codes | B5: Name | C5: Sub Acc Code | D5: Name
A6: 1 | B6: CLASS 1 – EQUITY AND NON-CURRENT LIABILITIES
A7: 10 | B7: Capital and similar
A8: 101 | B8: Share capital
A9: 101101 | B9: Share capital | C9: 10110100 | D9: Subscribed Share Capital
C10: 10110101 | D10: Paid Share Share Capital
C11: 10110102 | D11: pay As You Earn (PAYE)
A12: 102 | B12: Bonuses linked to share capital
A13: 102101 | B13: Bonuses linked to share capital | C13: 10210100 | D13: Bonuses linked to share capital
A14: 103 | B14: Personal capital .
A15: 103101 | B15: Personal capital . | C15: 10310100 | D15: Personal capital .
A16: 104 | B16: Blocked accounts of institutions and branches
A17: 104101 | B17: Blocked accounts of institutions and branches | C17: 10410100 | D17: Blocked accounts of institutions and branches
A18: 105 | B18: Endowment Fund .
A19: 105101 | B19: Endowment Fund . | C19: 10510100 | D19: Endowment Fund .
A20: 108 | B20: Operator's account
A21: 108101 | B21: Operator's account | C21: 10810100 | D21: Operator's account
A22: 109 | B22: Partners, unpaid subscribed capital
A23: 109101 | B23: Partners, unpaid subscribed capital | C23: 10910100 | D23: Partners, unpaid subscribed capital
A24: 11 | B24: Reserves
A25: 111 | B25: Regulatory reserves .
A26: 111101 | B26: Regulatory reserves . | C26: 11110100 | D26: Regulatory reserves .
A27: 112 | B27: Optional reserves
A28: 112101 | B28: Optional reserves | C28: 11210100 | D28: Optional reserves
A29: 116 | B29: Consolidated reserves .
A30: 116101 | B30: Consolidated reserves . | C30: 11610100 | D30: Consolidated reserves .
A31: 117 | B31: Equivalence discrepancies
A32: 117101 | B32: Equivalence discrepancies | C32: 11710100 | D32: Equivalence discrepancies
A33: 12 | B33: Result and carry-over again
A34: 120 | B34: Postponement
A35: 120101 | B35: Postponement | C35: 12010100 | D35: Postponement
A36: 125 | B36: Net profit or loss for the year
A37: 125101 | B37: Net profit or loss for the year | C37: 12510100 | D37: Net profit or loss for the year
A38: 13 | B38: Other equity
A39: 131 | B39: Conversion discrepancies .
A40: 131101 | B40: Conversion discrepancies . | C40: 13110100 | D40: Conversion discrepancies .
A41: 132 | B41: Revaluation deviations
A42: 132101 | B42: Revaluation deviations | C42: 13210100 | D42: Revaluation deviations
A43: 133 | B43: Evaluation discrepancies
A44: 133101 | B44: Evaluation discrepancies | C44: 13310100 | D44: Evaluation discrepancies
A45: 138 | B45: Other gains and losses not recognised in profit or loss
A46: 138101 | B46: Other gains and losses not recognised in profit or loss | C46: 13810100 | D46: Other gains and losses not recognised in profit or loss
A47: 14 | B47: Non-current liabilities: deferred income and expenses .
A48: 141 | B48: Equipment subsidies
A49: 141101 | B49: Equipment subsidies | C49: 14110100 | D49: Equipment subsidies
A50: 142 | B50: Other investment grants
A51: 142101 | B51: Other investment grants | C51: 14210100 | D51: Other investment grants
A52: 143 | B52: Deferred assets
A53: 143101 | B53: Deffered Tax Liabilities | C53: 143101
C54: 14310100 | D54: Corporate In- come Tax (CIT)
C55: 14310101 | D55: Individual / Per- sonal Income Tax
C56: 14310102 | D56: Capital Gains Tax (CGT)
C57: 14310103 | D57: Withholding Taxes (WHT)
C58: 14310104 | D58: Pay As You Earn (PAYE)
C59: 14310105 | D59: Digital Services Tax (DST)
C60: 14310106 | D60: Skills Development Levy (SDL)
C61: 14310107 | D61: Value Added Tax (VAT) on Domestic
C62: 14310108 | D62: Excise Duty
C63: 14310109 | D63: Stamp Duty
C64: 14310110 | D64: Gaming Taxes
C65: 14310111 | D65: Airport Service Charge
... C70: 14310116 | D70: Value Added Tax on Import
A71: 148 | B71: Other deferred income and expenses .
A72: 148101 | B72: Other deferred income and expenses . | C72: 14810100 | D72: Prepayment
C73: 14810101 | D73: Advances
C74: 14810102 | D74: Loans
A75: 15 | B75: Liaison accounts between institutions and joint ventures
A76: 151 | B76: Establishment liaison account
A77: 151101 | B77: Establishment liaison account | C77: 15110100 | D77: Establishment liaison account
A78: 152 | B78: Goods and services traded between establishments (charges)
A79: 152101 | B79: Goods and services traded between establishments (charges) | C79: 15210100 | D79: Goods and services traded between establishments (charges)
A80: 157 | B80: Goods and services traded between establishments (products) .
A81: 157101 | B81: Goods and services traded between establishments (products) . | C81: 15710100 | D81: Goods and services traded between establishments (products) .
A82: 158 | B82: Liaison accounts of joint ventures .
A83: 158101 | B83: Liaison accounts of joint ventures . | C83: 15810100 | D83: Liaison accounts of joint ventures .
A84: 16 | B84: Bonds
A85: 161 | B85: Government bonds
A86: 161101 | B86: Government bonds | C86: 16110100 | D86: Government bonds
A87: 162 | B87: Loans issued to the public
A88: 162101 | B88: Loans issued to the public
A89: 163 | B89: Bank loans or similar loans
A90: 163101 | B90: Bank loans or similar loans
A91: 169 | B91: Other bond issues
A92: 169101 | B92: Other bond issues
A93: 17 | B93: Other borrowings and assimilated liabilities as non-current liabilities
A94: 171 | B94: Deposits and bonds received more than one year
A95: 171101 | B95: Deposits and bonds received more than one year
A96: 172 | B96: Suppliers more than one year old
A97: 172101 | B97: Suppliers more than one year old
A98: 173 | B98: Advances received or accounts blocked for more than one year .
... A102: 175 | B102: Long- and medium-term borrowings .
A103: 175101 | B103: Long term loan | C103: 17510100 | D103: DTB Bank
C104: 17510101 | D104: HABIB Bank
C105: 17510102 | D105: CRDB Bank Plc
C106: 17510103 | D106: NMB Bank Plc
A107: 175102 | B107: Short term loan | C107: 17510104 | D107: DTB Bank
C108: 17510105 | D108: HABIB Bank
C109: 17510106 | D109: CRDB Bank Plc
...

Sheet General ledger 2025
A1: Account Bank Statement
A2: MBOGO MINING AND GENERAL KISEKE P.O.BOX 6369
A3: Account: 0150481116500 Available Balance: 15,921,784.45 TZS Period: 1 Year Total Value for Credit: 2,615,814,992.61 TZS Total Value for Debit: 2,597,702,089.91 TZS Summary of Book Balance as at 19/12/2025 : 15,921,784.45 TZS Summary of Cleared Balance as at 19/12/2025 : 15,921,784.45 TZS 19/12/2025 11:47:36
A7: Posting Date | B7: P.V.NO. | C7: CHQ N0. | D7: PAYEE | E7: Sub Account Code | F7: Sub Account Description | G7: Account Code | H7: Account Description | I7: Section Code | J7: Section description | K7: Department Code | L7: Department Description | M7: Location code | N7: Location Description | O7: Busines Code | P7: Business Description | Q7: Company Code | R7: Company Description | S7: USD | T7: EXCHANGE RATE | U7: Details | V7: Debit | W7: Credit
A8: 02.01.2025 | D8: CRDB BANK PLC | E8: 56150700 | F8: =VLOOKUP(E8,'Improved Accounting codes'!C89:D2429,2,FALSE) -> CRDB TZS:0150481116500 | G8: 561507 | H8: =VLOOKUP(G8,'Improved Accounting codes'!A61:B2401,2,FALSE) -> Agency Float Account | I8: FAD00102 | J8: =VLOOKUP(I8,'Section Code'!$B$1:$C$17,2,FALSE) -> Finance Section | K8: FAD001 | L8: =VLOOKUP(K8,'Department Codes'!$A$1:$B$4,2,FALSE) -> Finance and Administration Department | M8: MGL00121 | N8: =VLOOKUP(M8,'Location Code Code'!$E$2:$F$22,2,FALSE) -> HEAD OFFICE NYASHISHI MWANZA | O8: MGL0012 | P8: =VLOOKUP(O8,'Business Code'!$C$1:$D$19,2,FALSE) -> TRADING OF COMERCIAL EXPLOSIVES | Q8: MGL001 | R8: =VLOOKUP(Q8,'Company Code'!$A$1:$B$7,2,FALSE) -> Mbogo Mining and General Supply Limited | U8: REF:19426ee2ed61dab3 AGENCY FT AB17358199306989206479:Flavian:K N/A | V8: 3000000 | X8: =IF(V8="", W8, V8) -> 3000000 | Y8: =IF(V8<>"","DR","CR") -> DR
A9: 02.01.2025 | D9: CRDB BANK PLC | E9: 56150600 | F9: =VLOOKUP(E9,'Improved Accounting codes'!C90:D2430,2,FALSE) -> CRDB TZS:0150481116500 | G9: 561506 | H9: =VLOOKUP(G9,'Improved Accounting codes'!A62:B2402,2,FALSE) -> CRDB BANK PLC | I9: FAD00102 | J9: =VLOOKUP(I9,'Section Code'!$B$1:$C$17,2,FALSE) -> Finance Section | K9: FAD001 | L9: =VLOOKUP(K9,'Department Codes'!$A$1:$B$4,2,FALSE) -> Finance and Administration Department | M9: MGL00121 | N9: =VLOOKUP(M9,'Location Code Code'!$E$2:$F$22,2,FALSE) -> HEAD OFFICE NYASHISHI MWANZA | O9: MGL0012 | P9: =VLOOKUP(O9,'Business Code'!$C$1:$D$19,2,FALSE) -> TRADING OF COMERCIAL EXPLOSIVES | Q9: MGL001 | R9: =VLOOKUP(Q9,'Company Code'!$A$1:$B$7,2,FALSE) -> Mbogo Mining and General Supply Limited | U9: REF:19426ee2ed61dab3 AGENCY FT AB17358199306989206479:Flavian:K N/A | W9: 3000000 | X9: =IF(V9="", W9, V9) -> 3000000 | Y9: =IF(V9<>"","DR","CR") -> CR
A10: 02.01.2025 | B10: RV01-02012025 | D10: NEEMA RAPHAEL 0744979075 M -PESA | E10: 60160204 | F10: =VLOOKUP(E10,'Improved Accounting codes'!C91:D2431,2,FALSE) -> Service Cost: Labour Charges | G10: 601602 | H10: =VLOOKUP(G10,'Improved Accounting codes'!A63:B2403,2,FALSE) -> Cost of Services | I10: BDD00102 | J10: =VLOOKUP(I10,'Section Code'!$B$1:$C$17,2,FALSE) -> Sales and Marketing Section | K10: BDD001 | L10: =VLOOKUP(K10,'Department Codes'!$A$1:$B$4,2,FALSE) -> Business Development Department | M10: MGL00121 | N10: =VLOOKUP(M10,'Location Code Code'!$E$2:$F$22,2,FALSE) -> HEAD OFFICE NYASHISHI MWANZA | O10: MGL0012 | P10: =VLOOKUP(O10,'Business Code'!$C$1:$D$19,2,FALSE) -> TRADING OF COMERCIAL EXPLOSIVES | Q10: MGL001 | R10: =VLOOKUP(Q10,'Company Code'!$A$1:$B$7,2,FALSE) -> Mbogo Mining and General Supply Limited | U10: .Being payment for Casual labour 3 people@8000/= for six days | V10: 144000 | X10: =IF(V10="", W10, V10) -> 144000 | Y10: =IF(V10<>"","DR","CR") -> DR
A11: 02.01.2025 | B11: RV01-02012025 | D11: NEEMA RAPHAEL 0744979075 M -PESA | E11: 57250100 | F11: =VLOOKUP(E11,'Improved Accounting codes'!C92:D2432,2,FALSE) -> Cash for office use Mbogo Mining and General Supply Limited | G11: 572501 | H11: =VLOOKUP(G11,'Improved Accounting codes'!A64:B2404,2,FALSE) -> Cash for Office Use | I11: BDD00102 | J11: =VLOOKUP(I11,'Section Code'!$B$1:$C$17,2,FALSE) -> Sales and Marketing Section | K11: BDD001 | L11: =VLOOKUP(K11,'Department Codes'!$A$1:$B$4,2,FALSE) -> Business Development Department | M11: MGL00121 | N11: =VLOOKUP(M11,'Location Code Code'!$E$2:$F$22,2,FALSE) -> HEAD OFFICE NYASHISHI MWANZA | O11: MGL0012 | P11: =VLOOKUP(O11,'Business Code'!$C$1:$D$19,2,FALSE) -> TRADING OF COMERCIAL EXPLOSIVES | Q11: MGL001 | R11: =VLOOKUP(Q11,'Company Code'!$A$1:$B$7,2,FALSE) -> Mbogo Mining and General Supply Limited | U11: .Being payment for Casual labour 3 people@8000/= for six days | W11: 144000 | X11: =IF(V11="", W11, V11) -> 144000 | Y11: =IF(V11<>"","DR","CR") -> CR
A12: 02.01.2025 | B12: RV01-02012025 | D12: NEEMA RAPHAEL 0744979075 M -PESA | E12: 40240100 | F12: =VLOOKUP(E12,'Improved Accounting codes'!C93:D2433,2,FALSE) -> Fixed Asset Suppliers | G12: 402401 | H12: =VLOOKUP(G12,'Improved Accounting codes'!A65:B2405,2,FALSE) -> Fixed Asset Suppliers | I12: BDD00102 | J12: =VLOOKUP(I12,'Section Code'!$B$1:$C$17,2,FALSE) -> Sales and Marketing Section | K12: BDD001 | L12: =VLOOKUP(K12,'Department Codes'!$A$1:$B$4,2,FALSE) -> Business Development Department | M12: MGL00121 | N12: =VLOOKUP(M12,'Location Code Code'!$E$2:$F$22,2,FALSE) -> HEAD OFFICE NYASHISHI MWANZA | O12: MGL0012 | P12: =VLOOKUP(O12,'Business Code'!$C$1:$D$19,2,FALSE) -> TRADING OF COMERCIAL EXPLOSIVES | Q12: MGL001 | R12: =VLOOKUP(Q12,'Company Code'!$A$1:$B$7,2,FALSE) -> Mbogo Mining and General Supply Limited | U12: Being purchase of purchase of sharpening throw 4pcs@4000 | V12: 16000 | X12: =IF(V12="", W12, V12) -> 16000 | Y12: =IF(V12<>"","DR","CR") -> DR
A13: 02.01.2025 | B13: RV01-02012025 | D13: NEEMA RAPHAEL 0744979075 M -PESA | E13: 57250100 | F13: =VLOOKUP(E13,'Improved Accounting codes'!C94:D2434,2,FALSE) -> Cash for office use Mbogo Mining and General Supply Limited | G13: 572501 | H13: =VLOOKUP(G13,'Improved Accounting codes'!A66:B2406,2,FALSE) -> Cash for Office Use | I13: BDD00102 | J13: =VLOOKUP(I13,'Section Code'!$B$1:$C$17,2,FALSE) -> Sales and Marketing Section | K13: BDD001 | L13: =VLOOKUP(K13,'Department Codes'!$A$1:$B$4,2,FALSE) -> Business Development Department | M13: MGL00121 | N13: =VLOOKUP(M13,'Location Code Code'!$E$2:$F$22,2,FALSE) -> HEAD OFFICE NYASHISHI MWANZA | O13: MGL0012 | P13: =VLOOKUP(O13,'Business Code'!$C$1:$D$19,2,FALSE) -> TRADING OF COMERCIAL EXPLOSIVES | Q13: MGL001 | R13: =VLOOKUP(Q13,'Company Code'!$A$1:$B$7,2,FALSE) -> Mbogo Mining and General Supply Limited | U13: Being purchase of purchase of sharpening throw 4pcs@4000 | W13: 16000 | X13: =IF(V13="", W13, V13) -> 16000 | Y13: =IF(V13<>"","DR","CR") -> CR
A14: 02.01.2025 | B14: RV01-02012025 | D14: NEEMA RAPHAEL 0744979075 M -PESA | E14: 40240100 | F14: =VLOOKUP(E14,'Improved Accounting codes'!C95:D2435,2,FALSE) -> Fixed Asset Suppliers | G14: 402401 | H14: =VLOOKUP(G14,'Improved Accounting codes'!A67:B2407,2,FALSE) -> Fixed Asset Suppliers | I14: BDD00102 | J14: =VLOOKUP(I14,'Section Code'!$B$1:$C$17,2,FALSE) -> Sales and Marketing Section | K14: BDD001 | L14: =VLOOKUP(K14,'Department Codes'!$A$1:$B$4,2,FALSE) -> Business Development Department | M14: MGL00121 | N14: =VLOOKUP(M14,'Location Code Code'!$E$2:$F$22,2,FALSE) -> HEAD OFFICE NYASHISHI MWANZA | O14: MGL0012 | P14: =VLOOKUP(O14,'Business Code'!$C$1:$D$19,2,FALSE) -> TRADING OF COMERCIAL EXPLOSIVES | Q14: MGL001 | R14: =VLOOKUP(Q14,'Company Code'!$A$1:$B$7,2,FALSE) -> Mbogo Mining and General Supply Limited | U14: Being payment for purchase of wood chiper 10 pcs@2000 | V14: 20000 | X14: =IF(V14="", W14, V14) -> 20000 | Y14: =IF(V14<>"","DR","CR") -> DR
A15: 02.01.2025 | B15: RV01-02012025 | D15: NEEMA RAPHAEL 0744979075 M -PESA | E15: 57250100 | F15: =VLOOKUP(E15,'Improved Accounting codes'!C96:D2436,2,FALSE) -> Cash for office use Mbogo Mining and General Supply Limited | G15: 572501 | H15: =VLOOKUP(G15,'Improved Accounting codes'!A68:B2408,2,FALSE) -> Cash for Office Use | I15: BDD00102 | J15: =VLOOKUP(I15,'Section Code'!$B$1:$C$17,2,FALSE) -> Sales and Marketing Section | K15: BDD001 | L15: =VLOOKUP(K15,'Department Codes'!$A$1:$B$4,2,FALSE) -> Business Development Department | M15: MGL00121 | N15: =VLOOKUP(M15,'Location Code Code'!$E$2:$F$22,2,FALSE) -> HEAD OFFICE NYASHISHI MWANZA | O15: MGL0012 | P15: =VLOOKUP(O15,'Business Code'!$C$1:$D$19,2,FALSE) -> TRADING OF COMERCIAL EXPLOSIVES | Q15: MGL001 | R15: =VLOOKUP(Q15,'Company Code'!$A$1:$B$7,2,FALSE) -> Mbogo Mining and General Supply Limited | U15: Being payment for purchase of wood chiper 10 pcs@2000 | W15: 20000 | X15: =IF(V15="", W15, V15) -> 20000 | Y15: =IF(V15<>"","DR","CR") -> CR
A16: 02.01.2025 | B16: RV01-02012025 | D16: NEEMA RAPHAEL 0744979075 M -PESA | E16: 40240100 | F16: =VLOOKUP(E16,'Improved Accounting codes'!C97:D2437,2,FALSE) -> Fixed Asset Suppliers | G16: 572501 | H16: =VLOOKUP(G16,'Improved Accounting codes'!A69:B2409,2,FALSE) -> Cash for Office Use | I16: BDD00102 | J16: =VLOOKUP(I16,'Section Code'!$B$1:$C$17,2,FALSE) -> Sales and Marketing Section | K16: BDD001 | L16: =VLOOKUP(K16,'Department Codes'!$A$1:$B$4,2,FALSE) -> Business Development Department | M16: MGL00121 | N16: =VLOOKUP(M16,'Location Code Code'!$E$2:$F$22,2,FALSE) -> HEAD OFFICE NYASHISHI MWANZA | O16: MGL0012 | P16: =VLOOKUP(O16,'Business Code'!$C$1:$D$19,2,FALSE) -> TRADING OF COMERCIAL EXPLOSIVES | Q16: MGL001 | R16: =VLOOKUP(Q16,'Company Code'!$A$1:$B$7,2,FALSE) -> Mbogo Mining and General Supply Limited | U16: Being payment forpurchase of knife 2 pcs@7000 | V16: 14000 | X16: =IF(V16="", W16, V16) -> 14000 | Y16: =IF(V16<>"","DR","CR") -> DR
A17: 02.01.2025 | B17: RV01-02012025 | D17: NEEMA RAPHAEL 0744979075 M -PESA | E17: 57250100 | F17: =VLOOKUP(E17,'Improved Accounting codes'!C98:D2438,2,FALSE) -> Cash for office use Mbogo Mining and General Supply Limited | G17: 572501 | H17: =VLOOKUP(G17,'Improved Accounting codes'!A70:B2410,2,FALSE) -> Cash for Office Use | I17: BDD00102 | J17: =VLOOKUP(I17,'Section Code'!$B$1:$C$17,2,FALSE) -> Sales and Marketing Section | K17: BDD001 | L17: =VLOOKUP(K17,'Department Codes'!$A$1:$B$4,2,FALSE) -> Business Development Department | M17: MGL00121 | N17: =VLOOKUP(M17,'Location Code Code'!$E$2:$F$22,2,FALSE) -> HEAD OFFICE NYASHISHI MWANZA | O17: MGL0012 | P17: =VLOOKUP(O17,'Business Code'!$C$1:$D$19,2,FALSE) -> TRADING OF COMERCIAL EXPLOSIVES | Q17: MGL001 | R17: =VLOOKUP(Q17,'Company Code'!$A$1:$B$7,2,FALSE) -> Mbogo Mining and General Supply Limited | U17: Being payment forpurchase of knife 2 pcs@7000 | W17: 14000 | X17: =IF(V17="", W17, V17) -> 14000 | Y17: =IF(V17<>"","DR","CR") -> CR
A18: 02.01.2025 | B18: RV01-02012025 | D18: CRDB BANK PLC | E18: 63860710 | F18: =VLOOKUP(E18,'Improved Accounting codes'!C99:D2439,2,FALSE) -> CRDB TZS:0150481116500 | G18: 638607 | H18: =VLOOKUP(G18,'Improved Accounting codes'!A71:B2411,2,FALSE) -> Bank Charges | I18: FAD00102 | J18: =VLOOKUP(I18,'Section Code'!$B$1:$C$17,2,FALSE) -> Finance Section | K18: FAD001 | L18: =VLOOKUP(K18,'Department Codes'!$A$1:$B$4,2,FALSE) -> Finance and Administration Department | M18: MGL00121 | N18: =VLOOKUP(M18,'Location Code Code'!$E$2:$F$22,2,FALSE) -> HEAD OFFICE NYASHISHI MWANZA | O18: MGL0012 | P18: =VLOOKUP(O18,'Business Code'!$C$1:$D$19,2,FALSE) -> TRADING OF COMERCIAL EXPLOSIVES | Q18: MGL001 | R18: =VLOOKUP(Q18,'Company Code'!$A$1:$B$7,2,FALSE) -> Mbogo Mining and General Supply Limited | U18: Transaction cost.Tsh 3,700 | V18: 3700 | X18: =IF(V18="", W18, V18) -> 3700 | Y18: =IF(V18<>"","DR","CR") -> DR
A19: 02.01.2025 | B19: RV01-02012025 | D19: CRDB BANK PLC | E19: 56150600 | F19: =VLOOKUP(E19,'Improved Accounting codes'!C100:D2440,2,FALSE) -> CRDB TZS:0150481116500 | G19: 561506 | H19: =VLOOKUP(G19,'Improved Accounting codes'!A72:B2412,2,FALSE) -> CRDB BANK PLC | I19: FAD00102 | J19: =VLOOKUP(I19,'Section Code'!$B$1:$C$17,2,FALSE) -> Finance Section | K19: FAD001 | L19: =VLOOKUP(K19,'Department Codes'!$A$1:$B$4,2,FALSE) -> Finance and Administration Department | M19: MGL00121 | N19: =VLOOKUP(M19,'Location Code Code'!$E$2:$F$22,2,FALSE) -> HEAD OFFICE NYASHISHI MWANZA | O19: MGL0012 | P19: =VLOOKUP(O19,'Business Code'!$C$1:$D$19,2,FALSE) -> TRADING OF COMERCIAL EXPLOSIVES | Q19: MGL001 | R19: =VLOOKUP(Q19,'Company Code'!$A$1:$B$7,2,FALSE) -> Mbogo Mining and General Supply Limited | U19: Transaction cost.Tsh 3,700 | W19: 3700 | X19: =IF(V19="", W19, V19) -> 3700 | Y19: =IF(V19<>"","DR","CR") -> CR
A20: 02.01.2025 | B20: RV01-02012025 | D20: SHABANI MERERE MPESA | E20: 62360104 | F20: =VLOOKUP(E20,'Improved Accounting codes'!C101:D2441,2,FALSE) -> Accomodation, Transport and meals expense | G20: 623601 | H20: =VLOOKUP(G20,'Improved Accounting codes'!A73:B2413,2,FALSE) -> Staff transport | I20: BDD00102 | J20: =VLOOKUP(I20,'Section Code'!$B$1:$C$17,2,FALSE) -> Sales and Marketing Section | K20: BDD001 | L20: =VLOOKUP(K20,'Department Codes'!$A$1:$B$4,2,FALSE) -> Business Development Department | M20: MGL00121 | N20: =VLOOKUP(M20,'Location Code Code'!$E$2:$F$22,2,FALSE) -> HEAD OFFICE NYASHISHI MWANZA | O20: MGL0012 | P20: =VLOOKUP(O20,'Business Code'!$C$1:$D$19,2,FALSE) -> TRADING OF COMERCIAL EXPLOSIVES | Q20: MGL001 | R20: =VLOOKUP(Q20,'Company Code'!$A$1:$B$7,2,FALSE) -> Mbogo Mining and General Supply Limited | U20: Being payment for meals and accomodation | V20: 400000 | X20: =IF(V20="", W20, V20) -> 400000 | Y20: =IF(V20<>"","DR","CR") -> DR
A21: 02.01.2025 | B21: RV01-02012025 | D21: SHABANI MERERE MPESA | E21: 57250100 | F21: =VLOOKUP(E21,'Improved Accounting codes'!C102:D2442,2,FALSE) -> Cash for office use Mbogo Mining and General Supply Limited | G21: 572501 | H21: =VLOOKUP(G21,'Improved Accounting codes'!A74:B2414,2,FALSE) -> Cash for Office Use | I21: BDD00102 | J21: =VLOOKUP(I21,'Section Code'!$B$1:$C$17,2,FALSE) -> Sales and Marketing Section | K21: BDD001 | L21: =VLOOKUP(K21,'Department Codes'!$A$1:$B$4,2,FALSE) -> Business Development Department | M21: MGL00121 | N21: =VLOOKUP(M21,'Location Code Code'!$E$2:$F$22,2,FALSE) -> HEAD OFFICE NYASHISHI MWANZA | O21: MGL0012 | P21: =VLOOKUP(O21,'Business Code'!$C$1:$D$19,2,FALSE) -> TRADING OF COMERCIAL EXPLOSIVES | Q21: MGL001 | R21: =VLOOKUP(Q21,'Company Code'!$A$1:$B$7,2,FALSE) -> Mbogo Mining and General Supply Limited | U21: Being payment for meals and accomodation | W21: 400000 | X21: =IF(V21="", W21, V21) -> 400000 | Y21: =IF(V21<>"","DR","CR") -> CR
A22: 02.01.2025 | B22: RV01-02012025 | D22: ZAWADI MWASONGWE 43010002631-NMB | E22: 6386051 | F22: =VLOOKUP(E22,'Improved Accounting codes'!C103:D2443,2,FALSE) -> #N/A | G22: 638605 | H22: =VLOOKUP(G22,'Improved Accounting codes'!A75:B2415,2,FALSE) -> Security Charges | I22: BDD00102 | J22: =VLOOKUP(I22,'Section Code'!$B$1:$C$17,2,FALSE) -> Sales and Marketing Section | K22: BDD001 | L22: =VLOOKUP(K22,'Department Codes'!$A$1:$B$4,2,FALSE) -> Business Development Department | M22: MGL00121 | N22: =VLOOKUP(M22,'Location Code Code'!$E$2:$F$22,2,FALSE) -> HEAD OFFICE NYASHISHI MWANZA | O22: MGL0012 | P22: =VLOOKUP(O22,'Business Code'!$C$1:$D$19,2,FALSE) -> TRADING OF COMERCIAL EXPLOSIVES | Q22: MGL001 | R22: =VLOOKUP(Q22,'Company Code'!$A$1:$B$7,2,FALSE) -> Mbogo Mining and General Supply Limited | U22: Being payment for security the month of November 2024. | V22: 300000 | X22: =IF(V22="", W22, V22) -> 300000 | Y22: =IF(V22<>"","DR","CR") -> DR
A23: 02.01.2025 | B23: RV01-02012025 | D23: ZAWADI MWASONGWE 43010002631-NMB | E23: 57250100 | F23: =VLOOKUP(E23,'Improved Accounting codes'!C104:D2444,2,FALSE) -> Cash for office use Mbogo Mining and General Supply Limited | G23: 572501 | H23: =VLOOKUP(G23,'Improved Accounting codes'!A76:B2416,2,FALSE) -> Cash for Office Use | I23: BDD00102 | J23: =VLOOKUP(I23,'Section Code'!$B$1:$C$17,2,FALSE) -> Sales and Marketing Section | K23: BDD001 | L23: =VLOOKUP(K23,'Department Codes'!$A$1:$B$4,2,FALSE) -> Business Development Department | M23: MGL00121 | N23: =VLOOKUP(M23,'Location Code Code'!$E$2:$F$22,2,FALSE) -> HEAD OFFICE NYASHISHI MWANZA | O23: MGL0012 | P23: =VLOOKUP(O23,'Business Code'!$C$1:$D$19,2,FALSE) -> TRADING OF COMERCIAL EXPLOSIVES | Q23: MGL001 | R23: =VLOOKUP(Q23,'Company Code'!$A$1:$B$7,2,FALSE) -> Mbogo Mining and General Supply Limited | U23: Being payment for security the month of November 2024. | W23: 30000 | X23: =IF(V23="", W23, V23) -> 30000 | Y23: =IF(V23<>"","DR","CR") -> CR
A24: 02.01.2025 | B24: RV01-02012025 | D24: EPIFANIA ODANCE | E24: 63860102 | F24: =VLOOKUP(E24,'Improved Accounting codes'!C105:D2445,2,FALSE) -> Charging Battery | G24: 638601 | H24: =VLOOKUP(G24,'Improved Accounting codes'!A77:B2417,2,FALSE) -> Utilities | I24: FAD00102 | J24: =VLOOKUP(I24,'Section Code'!$B$1:$C$17,2,FALSE) -> Finance Section | K24: FAD001 | L24: =VLOOKUP(K24,'Department Codes'!$A$1:$B$4,2,FALSE) -> Finance and Administration Department | M24: MGL00121 | N24: =VLOOKUP(M24,'Location Code Code'!$E$2:$F$22,2,FALSE) -> HEAD OFFICE NYASHISHI MWANZA | O24: MGL0012 | P24: =VLOOKUP(O24,'Business Code'!$C$1:$D$19,2,FALSE) -> TRADING OF COMERCIAL EXPLOSIVES | Q24: MGL001 | R24: =VLOOKUP(Q24,'Company Code'!$A$1:$B$7,2,FALSE) -> Mbogo Mining and General Supply Limited | U24: Being payment for chargng batery | V24: 3000 | X24: =IF(V24="", W24, V24) -> 3000 | Y24: =IF(V24<>"","DR","CR") -> DR
A25: 02.01.2025 | B25: RV01-02012025 | D25: EPIFANIA ODANCE | E25: 57250100 | F25: =VLOOKUP(E25,'Improved Accounting codes'!C106:D2446,2,FALSE) -> Cash for office use Mbogo Mining and General Supply Limited | G25: 572501 | H25: =VLOOKUP(G25,'Improved Accounting codes'!A78:B2418,2,FALSE) -> Cash for Office Use | I25: FAD00102 | J25: =VLOOKUP(I25,'Section Code'!$B$1:$C$17,2,FALSE) -> Finance Section | K25: FAD001 | L25: =VLOOKUP(K25,'Department Codes'!$A$1:$B$4,2,FALSE) -> Finance and Administration Department | M25: MGL00121 | N25: =VLOOKUP(M25,'Location Code Code'!$E$2:$F$22,2,FALSE) -> HEAD OFFICE NYASHISHI MWANZA | O25: MGL0012 | P25: =VLOOKUP(O25,'Business Code'!$C$1:$D$19,2,FALSE) -> TRADING OF COMERCIAL EXPLOSIVES | Q25: MGL001 | R25: =VLOOKUP(Q25,'Company Code'!$A$1:$B$7,2,FALSE) -> Mbogo Mining and General Supply Limited | U25: Being payment for chargng batery | W25: 3000 | X25: =IF(V25="", W25, V25) -> 3000 | Y25: =IF(V25<>"","DR","CR") -> CR
A26: 02.01.2025 | B26: RV01-02012025 | D26: BBELINDA FREEMAN MIX BY YA YAS 0676302325 | E26: 62360104 | F26: =VLOOKUP(E26,'Improved Accounting codes'!C107:D2447,2,FALSE) -> Accomodation, Transport and meals expense | G26: 623601 | H26: =VLOOKUP(G26,'Improved Accounting codes'!A79:B2419,2,FALSE) -> Staff transport | I26: FAD00102 | J26: =VLOOKUP(I26,'Section Code'!$B$1:$C$17,2,FALSE) -> Finance Section | K26: FAD001 | L26: =VLOOKUP(K26,'Department Codes'!$A$1:$B$4,2,FALSE) -> Finance and Administration Department | M26: MGL00121 | N26: =VLOOKUP(M26,'Location Code Code'!$E$2:$F$22,2,FALSE) -> HEAD OFFICE NYASHISHI MWANZA | O26: MGL0012 | P26: =VLOOKUP(O26,'Business Code'!$C$1:$D$19,2,FALSE) -> TRADING OF COMERCIAL EXPLOSIVES | Q26: MGL001 | R26: =VLOOKUP(Q26,'Company Code'!$A$1:$B$7,2,FALSE) -> Mbogo Mining and General Supply Limited | U26: Being payment for Transport fare to Ihayabuyaga site | V26: 20000 | X26: =IF(V26="", W26, V26) -> 20000 | Y26: =IF(V26<>"","DR","CR") -> DR
A27: 02.01.2025 | B27: RV01-02012025 | D27: BBELINDA FREEMAN MIX BY YA YAS 0676302325 | E27: 57250100 | F27: =VLOOKUP(E27,'Improved Accounting codes'!C108:D2448,2,FALSE) -> Cash for office use Mbogo Mining and General Supply Limited | G27: 572501 | H27: =VLOOKUP(G27,'Improved Accounting codes'!A80:B2420,2,FALSE) -> Cash for Office Use | I27: FAD00102 | J27: =VLOOKUP(I27,'Section Code'!$B$1:$C$17,2,FALSE) -> Finance Section | K27: FAD001 | L27: =VLOOKUP(K27,'Department Codes'!$A$1:$B$4,2,FALSE) -> Finance and Administration Department | M27: MGL00121 | N27: =VLOOKUP(M27,'Location Code Code'!$E$2:$F$22,2,FALSE) -> HEAD OFFICE NYASHISHI MWANZA | O27: MGL0012 | P27: =VLOOKUP(O27,'Business Code'!$C$1:$D$19,2,FALSE) -> TRADING OF COMERCIAL EXPLOSIVES | Q27: MGL001 | R27: =VLOOKUP(Q27,'Company Code'!$A$1:$B$7,2,FALSE) -> Mbogo Mining and General Supply Limited | U27: Being payment for Transport fare to Ihayabuyaga site | W27: 20000 | X27: =IF(V27="", W27, V27) -> 20000 | Y27: =IF(V27<>"","DR","CR") -> CR
A28: 02.01.2025 | B28: RV01-02012025 | D28: GASPER LEONARD MPESA 076542761 | E28: 62760101 | F28: =VLOOKUP(E28,'Improved Accounting codes'!C109:D2449,2,FALSE) -> Spare parts | G28: 627601 | H28: =VLOOKUP(G28,'Improved Accounting codes'!A81:B2421,2,FALSE) -> Spare parts, Repair,Acetone and Maintenance | I28: FAD00102 | J28: =VLOOKUP(I28,'Section Code'!$B$1:$C$17,2,FALSE) -> Finance Section | K28: FAD001 | L28: =VLOOKUP(K28,'Department Codes'!$A$1:$B$4,2,FALSE) -> Finance and Administration Department | M28: MGL00121 | N28: =VLOOKUP(M28,'Location Code Code'!$E$2:$F$22,2,FALSE) -> HEAD OFFICE NYASHISHI MWANZA | O28: MGL0012 | P28: =VLOOKUP(O28,'Business Code'!$C$1:$D$19,2,FALSE) -> TRADING OF COMERCIAL EXPLOSIVES | Q28: MGL001 | R28: =VLOOKUP(Q28,'Company Code'!$A$1:$B$7,2,FALSE) -> Mbogo Mining and General Supply Limited | U28: Being payment for spare parts | V28: 2000000 | X28: =IF(V28="", W28, V28) -> 2000000 | Y28: =IF(V28<>"","DR","CR") -> DR
A29: 02.01.2025 | B29: RV01-02012025 | D29: GASPER LEONARD MPESA 076542761 | E29: 57250100 | F29: =VLOOKUP(E29,'Improved Accounting codes'!C110:D2450,2,FALSE) -> Cash for office use Mbogo Mining and General Supply Limited | G29: 572501 | H29: =VLOOKUP(G29,'Improved Accounting codes'!A82:B2422,2,FALSE) -> Cash for Office Use | I29: BDD00102 | J29: =VLOOKUP(I29,'Section Code'!$B$1:$C$17,2,FALSE) -> Sales and Marketing Section | K29: BDD001 | L29: =VLOOKUP(K29,'Department Codes'!$A$1:$B$4,2,FALSE) -> Business Development Department | M29: MGL00121 | N29: =VLOOKUP(M29,'Location Code Code'!$E$2:$F$22,2,FALSE) -> HEAD OFFICE NYASHISHI MWANZA | O29: MGL0012 | P29: =VLOOKUP(O29,'Business Code'!$C$1:$D$19,2,FALSE) -> TRADING OF COMERCIAL EXPLOSIVES | Q29: MGL001 | R29: =VLOOKUP(Q29,'Company Code'!$A$1:$B$7,2,FALSE) -> Mbogo Mining and General Supply Limited | U29: Being payment for spare parts | W29: 2000000 | X29: =IF(V29="", W29, V29) -> 2000000 | Y29: =IF(V29<>"","DR","CR") -> CR
A30: 02.01.2025 | B30: RV01-02012025 | D30: BENJAMINI SABUNI MIX BY YAS 0655184402 | E30: 60160205 | F30: =VLOOKUP(E30,'Improved Accounting codes'!C111:D2451,2,FALSE) -> Service cost: Processing Charges | G30: 601602 | H30: =VLOOKUP(G30,'Improved Accounting codes'!A83:B2423,2,FALSE) -> Cost of Services | I30: BDD00102 | J30: =VLOOKUP(I30,'Section Code'!$B$1:$C$17,2,FALSE) -> Sales and Marketing Section | K30: BDD001 | L30: =VLOOKUP(K30,'Department Codes'!$A$1:$B$4,2,FALSE) -> Business Development Department | M30: MGL00121 | N30: =VLOOKUP(M30,'Location Code Code'!$E$2:$F$22,2,FALSE) -> HEAD OFFICE NYASHISHI MWANZA | O30: MGL0012 | P30: =VLOOKUP(O30,'Business Code'!$C$1:$D$19,2,FALSE) -> TRADING OF COMERCIAL EXPLOSIVES | Q30: MGL001 | R30: =VLOOKUP(Q30,'Company Code'!$A$1:$B$7,2,FALSE) -> Mbogo Mining and General Supply Limited | U30: Being payment for production of ANFO | V30: 1050750 | X30: =IF(V30="", W30, V30) -> 1050750 | Y30: =IF(V30<>"","DR","CR") -> DR
A31: 02.01.2025 | B31: RV01-02012025 | D31: BENJAMINI SABUNI MIX BY YAS 0655184402 | E31: 57250100 | F31: =VLOOKUP(E31,'Improved Accounting codes'!C112:D2452,2,FALSE) -> Cash for office use Mbogo Mining and General Supply Limited | G31: 572501 | H31: =VLOOKUP(G31,'Improved Accounting codes'!A84:B2424,2,FALSE) -> Cash for Office Use | I31: BDD00102 | J31: =VLOOKUP(I31,'Section Code'!$B$1:$C$17,2,FALSE) -> Sales and Marketing Section | K31: BDD001 | L31: =VLOOKUP(K31,'Department Codes'!$A$1:$B$4,2,FALSE) -> Business Development Department | M31: MGL00121 | N31: =VLOOKUP(M31,'Location Code Code'!$E$2:$F$22,2,FALSE) -> HEAD OFFICE NYASHISHI MWANZA | O31: MGL0012 | P31: =VLOOKUP(O31,'Business Code'!$C$1:$D$19,2,FALSE) -> TRADING OF COMERCIAL EXPLOSIVES | Q31: MGL001 | R31: =VLOOKUP(Q31,'Company Code'!$A$1:$B$7,2,FALSE) -> Mbogo Mining and General Supply Limited | U31: Being payment for production of ANFO | W31: 1050750 | X31: =IF(V31="", W31, V31) -> 1050750 | Y31: =IF(V31<>"","DR","CR") -> CR
A32: 02.01.2025 | B32: RV01-02012025 | D32: BBELINDA FREEMAN MIX BY YA YAS 0676302325 | E32: 62560200 | F32: =VLOOKUP(E32,'Improved Accounting codes'!C113:D2453,2,FALSE) -> TRA Penalties | G32: 625602 | H32: =VLOOKUP(G32,'Improved Accounting codes'!A85:B2425,2,FALSE) -> Penalties Fines and Interests | I32: FAD00102 | J32: =VLOOKUP(I32,'Section Code'!$B$1:$C$17,2,FALSE) -> Finance Section | K32: FAD001 | L32: =VLOOKUP(K32,'Department Codes'!$A$1:$B$4,2,FALSE) -> Finance and Administration Department | M32: MGL00121 | N32: =VLOOKUP(M32,'Location Code Code'!$E$2:$F$22,2,FALSE) -> HEAD OFFICE NYASHISHI MWANZA | O32: MGL0012 | P32: =VLOOKUP(O32,'Business Code'!$C$1:$D$19,2,FALSE) -> TRADING OF COMERCIAL EXPLOSIVES | Q32: MGL001 | R32: =VLOOKUP(Q32,'Company Code'!$A$1:$B$7,2,FALSE) -> Mbogo Mining and General Supply Limited | U32: Being payment for fine for RATRA | V32: 250000 | X32: =IF(V32="", W32, V32) -> 250000 | Y32: =IF(V32<>"","DR","CR") -> DR
A33: 02.01.2025 | B33: RV01-02012025 | D33: BBELINDA FREEMAN MIX BY YA YAS 0676302325 | E33: 57250100 | F33: =VLOOKUP(E33,'Improved Accounting codes'!C114:D2454,2,FALSE) -> Cash for office use Mbogo Mining and General Supply Limited | G33: 572501 | H33: =VLOOKUP(G33,'Improved Accounting codes'!A86:B2426,2,FALSE) -> Cash for Office Use | I33: FAD00102 | J33: =VLOOKUP(I33,'Section Code'!$B$1:$C$17,2,FALSE) -> Finance Section | K33: FAD001 | L33: =VLOOKUP(K33,'Department Codes'!$A$1:$B$4,2,FALSE) -> Finance and Administration Department | M33: MGL00121 | N33: =VLOOKUP(M33,'Location Code Code'!$E$2:$F$22,2,FALSE) -> HEAD OFFICE NYASHISHI MWANZA | O33: MGL0012 | P33: =VLOOKUP(O33,'Business Code'!$C$1:$D$19,2,FALSE) -> TRADING OF COMERCIAL EXPLOSIVES | Q33: MGL001 | R33: =VLOOKUP(Q33,'Company Code'!$A$1:$B$7,2,FALSE) -> Mbogo Mining and General Supply Limited | U33: Being payment for fine for RATRA | W33: 250000 | X33: =IF(V33="", W33, V33) -> 250000 | Y33: =IF(V33<>"","DR","CR") -> CR
A34: 02.01.2025 | B34: RV01-02012025 | D34: BARNABAS NIBENGO MPESA 0765427622 | E34: 62360104 | F34: =VLOOKUP(E34,'Improved Accounting codes'!C115:D2455,2,FALSE) -> Accomodation, Transport and meals expense | G34: 623601 | H34: =VLOOKUP(G34,'Improved Accounting codes'!A87:B2427,2,FALSE) -> Staff transport | I34: BDD00102 | J34: =VLOOKUP(I34,'Section Code'!$B$1:$C$17,2,FALSE) -> Sales and Marketing Section | K34: BDD001 | L34: =VLOOKUP(K34,'Department Codes'!$A$1:$B$4,2,FALSE) -> Business Development Department | M34: MGL00121 | N34: =VLOOKUP(M34,'Location Code Code'!$E$2:$F$22,2,FALSE) -> HEAD OFFICE NYASHISHI MWANZA | O34: MGL0012 | P34: =VLOOKUP(O34,'Business Code'!$C$1:$D$19,2,FALSE) -> TRADING OF COMERCIAL EXPLOSIVES | Q34: MGL001 | R34: =VLOOKUP(Q34,'Company Code'!$A$1:$B$7,2,FALSE) -> Mbogo Mining and General Supply Limited | U34: .Being payment for Meals and Accomodation | V34: 2550000 | X34: =IF(V34="", W34, V34) -> 2550000 | Y34: =IF(V34<>"","DR","CR") -> DR
A35: 02.01.2025 | B35: RV01-02012025 | D35: BARNABAS NIBENGO MPESA 0765427622 | E35: 57250100 | F35: =VLOOKUP(E35,'Improved Accounting codes'!C116:D2456,2,FALSE) -> Cash for office use Mbogo Mining and General Supply Limited | G35: 572501 | H35: =VLOOKUP(G35,'Improved Accounting codes'!A88:B2428,2,FALSE) -> Cash for Office Use | I35: BDD00102 | J35: =VLOOKUP(I35,'Section Code'!$B$1:$C$17,2,FALSE) -> Sales and Marketing Section | K35: BDD001 | L35: =VLOOKUP(K35,'Department Codes'!$A$1:$B$4,2,FALSE) -> Business Development Department | M35: MGL00121 | N35: =VLOOKUP(M35,'Location Code Code'!$E$2:$F$22,2,FALSE) -> HEAD OFFICE NYASHISHI MWANZA | O35: MGL0012 | P35: =VLOOKUP(O35,'Business Code'!$C$1:$D$19,2,FALSE) -> TRADING OF COMERCIAL EXPLOSIVES | Q35: MGL001 | R35: =VLOOKUP(Q35,'Company Code'!$A$1:$B$7,2,FALSE) -> Mbogo Mining and General Supply Limited | U35: .Being payment for Meals and Accomodation | W35: 2550000 | X35: =IF(V35="", W35, V35) -> 2550000 | Y35: =IF(V35<>"","DR","CR") -> CR
A36: 02.01.2025 | B36: RV01-02012025 | D36: ANISET MABULA | E36: 6386051 | F36: =VLOOKUP(E36,'Improved Accounting codes'!C117:D2457,2,FALSE) -> #N/A | G36: 638605 | H36: =VLOOKUP(G36,'Improved Accounting codes'!A89:B2429,2,FALSE) -> Security Charges | I36: BDD00102 | J36: =VLOOKUP(I36,'Section Code'!$B$1:$C$17,2,FALSE) -> Sales and Marketing Section | K36: BDD001 | L36: =VLOOKUP(K36,'Department Codes'!$A$1:$B$4,2,FALSE) -> Business Development Department | M36: MGL00121 | N36: =VLOOKUP(M36,'Location Code Code'!$E$2:$F$22,2,FALSE) -> HEAD OFFICE NYASHISHI MWANZA | O36: MGL0012 | P36: =VLOOKUP(O36,'Business Code'!$C$1:$D$19,2,FALSE) -> TRADING OF COMERCIAL EXPLOSIVES | Q36: MGL001 | R36: =VLOOKUP(Q36,'Company Code'!$A$1:$B$7,2,FALSE) -> Mbogo Mining and General Supply Limited | U36: Being payment for security payment for the month of November 2024 | V36: 750000 | X36: =IF(V36="", W36, V36) -> 750000 | Y36: =IF(V36<>"","DR","CR") -> DR
A37: 02.01.2025 | B37: RV01-02012025 | D37: ANISET MABULA | E37: 57250100 | F37: =VLOOKUP(E37,'Improved Accounting codes'!C118:D2458,2,FALSE) -> Cash for office use Mbogo Mining and General Supply Limited | G37: 572501 | H37: =VLOOKUP(G37,'Improved Accounting codes'!A90:B2430,2,FALSE) -> Cash for Office Use | I37: BDD00102 | J37: =VLOOKUP(I37,'Section Code'!$B$1:$C$17,2,FALSE) -> Sales and Marketing Section | K37: BDD001 | L37: =VLOOKUP(K37,'Department Codes'!$A$1:$B$4,2,FALSE) -> Business Development Department | M37: MGL00121 | N37: =VLOOKUP(M37,'Location Code Code'!$E$2:$F$22,2,FALSE) -> HEAD OFFICE NYASHISHI MWANZA | O37: MGL0012 | P37: =VLOOKUP(O37,'Business Code'!$C$1:$D$19,2,FALSE) -> TRADING OF COMERCIAL EXPLOSIVES | Q37: MGL001 | R37: =VLOOKUP(Q37,'Company Code'!$A$1:$B$7,2,FALSE) -> Mbogo Mining and General Supply Limited | U37: Being payment for security payment for the month of November 2024 | W37: 750000 | X37: =IF(V37="", W37, V37) -> 750000 | Y37: =IF(V37<>"","DR","CR") -> CR
A38: 02.01.2025 | B38: RV01-02012025 | D38: ONESMO NIBENGO NMB 61810095948 | E38: 40240100 | F38: =VLOOKUP(E38,'Improved Accounting codes'!C119:D2459,2,FALSE) -> Fixed Asset Suppliers | G38: 402401 | H38: =VLOOKUP(G38,'Improved Accounting codes'!A91:B2431,2,FALSE) -> Fixed Asset Suppliers | I38: BDD00102 | J38: =VLOOKUP(I38,'Section Code'!$B$1:$C$17,2,FALSE) -> Sales and Marketing Section | K38: BDD001 | L38: =VLOOKUP(K38,'Department Codes'!$A$1:$B$4,2,FALSE) -> Business Development Department | M38: MGL00121 | N38: =VLOOKUP(M38,'Location Code Code'!$E$2:$F$22,2,FALSE) -> HEAD OFFICE NYASHISHI MWANZA | O38: MGL0012 | P38: =VLOOKUP(O38,'Business Code'!$C$1:$D$19,2,FALSE) -> TRADING OF COMERCIAL EXPLOSIVES | Q38: MGL001 | R38: =VLOOKUP(Q38,'Company Code'!$A$1:$B$7,2,FALSE) -> Mbogo Mining and General Supply Limited | U38: Being payment for purchase of iron steel 3m 11 pcs@21,000 | V38: 231000 | X38: =IF(V38="", W38, V38) -> 231000 | Y38: =IF(V38<>"","DR","CR") -> DR
A39: 02.01.2025 | B39: RV01-02012025 | D39: ONESMO NIBENGO NMB 61810095948 | E39: 57250100 | F39: =VLOOKUP(E39,'Improved Accounting codes'!C120:D2460,2,FALSE) -> Cash for office use Mbogo Mining and General Supply Limited | G39: 572501 | H39: =VLOOKUP(G39,'Improved Accounting codes'!A92:B2432,2,FALSE) -> Cash for Office Use | I39: BDD00102 | J39: =VLOOKUP(I39,'Section Code'!$B$1:$C$17,2,FALSE) -> Sales and Marketing Section | K39: BDD001 | L39: =VLOOKUP(K39,'Department Codes'!$A$1:$B$4,2,FALSE) -> Business Development Department | M39: MGL00121 | N39: =VLOOKUP(M39,'Location Code Code'!$E$2:$F$22,2,FALSE) -> HEAD OFFICE NYASHISHI MWANZA | O39: MGL0012 | P39: =VLOOKUP(O39,'Business Code'!$C$1:$D$19,2,FALSE) -> TRADING OF COMERCIAL EXPLOSIVES | Q39: MGL001 | R39: =VLOOKUP(Q39,'Company Code'!$A$1:$B$7,2,FALSE) -> Mbogo Mining and General Supply Limited | U39: Being payment for purchase of iron steel 3m 11 pcs@21,000 | W39: 231000 | X39: =IF(V39="", W39, V39) -> 231000 | Y39: =IF(V39<>"","DR","CR") -> CR
A40: 02.01.2025 | B40: RV01-02012025 | D40: ONESMO NIBENGO NMB 61810095948 | E40: 40240100 | F40: =VLOOKUP(E40,'Improved Accounting codes'!C121:D2461,2,FALSE) -> Fixed Asset Suppliers | G40: 402401 | H40: =VLOOKUP(G40,'Improved Accounting codes'!A93:B2433,2,FALSE) -> Fixed Asset Suppliers | I40: BDD00102 | J40: =VLOOKUP(I40,'Section Code'!$B$1:$C$17,2,FALSE) -> Sales and Marketing Section | K40: BDD001 | L40: =VLOOKUP(K40,'Department Codes'!$A$1:$B$4,2,FALSE) -> Business Development Department | M40: MGL00121 | N40: =VLOOKUP(M40,'Location Code Code'!$E$2:$F$22,2,FALSE) -> HEAD OFFICE NYASHISHI MWANZA | O40: MGL0012 | P40: =VLOOKUP(O40,'Business Code'!$C$1:$D$19,2,FALSE) -> TRADING OF COMERCIAL EXPLOSIVES | Q40: MGL001 | R40: =VLOOKUP(Q40,'Company Code'!$A$1:$B$7,2,FALSE) -> Mbogo Mining and General Supply Limited | U40: Being payment for purchase of iron steel 2m 12@15000 | V40: 180000 | X40: =IF(V40="", W40, V40) -> 180000 | Y40: =IF(V40<>"","DR","CR") -> DR
A41: 02.01.2025 | B41: RV01-02012025 | D41: ONESMO NIBENGO NMB 61810095948 | E41: 57250100 | F41: =VLOOKUP(E41,'Improved Accounting codes'!C122:D2462,2,FALSE) -> Cash for office use Mbogo Mining and General Supply Limited | G41: 572501 | H41: =VLOOKUP(G41,'Improved Accounting codes'!A94:B2434,2,FALSE) -> Cash for Office Use | I41: BDD00102 | J41: =VLOOKUP(I41,'Section Code'!$B$1:$C$17,2,FALSE) -> Sales and Marketing Section | K41: BDD001 | L41: =VLOOKUP(K41,'Department Codes'!$A$1:$B$4,2,FALSE) -> Business Development Department | M41: MGL00121 | N41: =VLOOKUP(M41,'Location Code Code'!$E$2:$F$22,2,FALSE) -> HEAD OFFICE NYASHISHI MWANZA | O41: MGL0012 | P41: =VLOOKUP(O41,'Business Code'!$C$1:$D$19,2,FALSE) -> TRADING OF COMERCIAL EXPLOSIVES | Q41: MGL001 | R41: =VLOOKUP(Q41,'Company Code'!$A$1:$B$7,2,FALSE) -> Mbogo Mining and General Supply Limited | U41: Being payment for purchase of iron steel 2m 12@15000 | W41: 180000 | X41: =IF(V41="", W41, V41) -> 180000 | Y41: =IF(V41<>"","DR","CR") -> CR
A42: 02.01.2025 | B42: RV01-02012025 | D42: ONESMO NIBENGO NMB 61810095948 | E42: 62760100 | F42: =VLOOKUP(E42,'Improved Accounting codes'!C123:D2463,2,FALSE) -> Tools | G42: 627601 | H42: =VLOOKUP(G42,'Improved Accounting codes'!A95:B2435,2,FALSE) -> Spare parts, Repair,Acetone and Maintenance | I42: BDD00102 | J42: =VLOOKUP(I42,'Section Code'!$B$1:$C$17,2,FALSE) -> Sales and Marketing Section | K42: BDD001 | L42: =VLOOKUP(K42,'Department Codes'!$A$1:$B$4,2,FALSE) -> Business Development Department | M42: MGL00121 | N42: =VLOOKUP(M42,'Location Code Code'!$E$2:$F$22,2,FALSE) -> HEAD OFFICE NYASHISHI MWANZA | O42: MGL0012 | P42: =VLOOKUP(O42,'Business Code'!$C$1:$D$19,2,FALSE) -> TRADING OF COMERCIAL EXPLOSIVES | Q42: MGL001 | R42: =VLOOKUP(Q42,'Company Code'!$A$1:$B$7,2,FALSE) -> Mbogo Mining and General Supply Limited | U42: Being payment for purchase of Nails 2 kg @6000 | V42: 12000 | X42: =IF(V42="", W42, V42) -> 12000 | Y42: =IF(V42<>"","DR","CR") -> DR
A43: 02.01.2025 | B43: RV01-02012025 | D43: ONESMO NIBENGO NMB 61810095948 | E43: 57250100 | F43: =VLOOKUP(E43,'Improved Accounting codes'!C124:D2464,2,FALSE) -> Cash for office use Mbogo Mining and General Supply Limited | G43: 572501 | H43: =VLOOKUP(G43,'Improved Accounting codes'!A96:B2436,2,FALSE) -> Cash for Office Use | I43: BDD00102 | J43: =VLOOKUP(I43,'Section Code'!$B$1:$C$17,2,FALSE) -> Sales and Marketing Section | K43: BDD001 | L43: =VLOOKUP(K43,'Department Codes'!$A$1:$B$4,2,FALSE) -> Business Development Department | M43: MGL00121 | N43: =VLOOKUP(M43,'Location Code Code'!$E$2:$F$22,2,FALSE) -> HEAD OFFICE NYASHISHI MWANZA | O43: MGL0012 | P43: =VLOOKUP(O43,'Business Code'!$C$1:$D$19,2,FALSE) -> TRADING OF COMERCIAL EXPLOSIVES | Q43: MGL001 | R43: =VLOOKUP(Q43,'Company Code'!$A$1:$B$7,2,FALSE) -> Mbogo Mining and General Supply Limited | U43: Being payment for purchase of Nails 2 kg @6000 | W43: 12000 | X43: =IF(V43="", W43, V43) -> 12000 | Y43: =IF(V43<>"","DR","CR") -> CR
A44: 02.01.2025 | B44: RV01-02012025 | D44: ONESMO NIBENGO NMB 61810095948 | E44: 62760100 | F44: =VLOOKUP(E44,'Improved Accounting codes'!C125:D2465,2,FALSE) -> Tools | G44: 627601 | H44: =VLOOKUP(G44,'Improved Accounting codes'!A97:B2437,2,FALSE) -> Spare parts, Repair,Acetone and Maintenance | I44: BDD00102 | J44: =VLOOKUP(I44,'Section Code'!$B$1:$C$17,2,FALSE) -> Sales and Marketing Section | K44: BDD001 | L44: =VLOOKUP(K44,'Department Codes'!$A$1:$B$4,2,FALSE) -> Business Development Department | M44: MGL00121 | N44: =VLOOKUP(M44,'Location Code Code'!$E$2:$F$22,2,FALSE) -> HEAD OFFICE NYASHISHI MWANZA | O44: MGL0012 | P44: =VLOOKUP(O44,'Business Code'!$C$1:$D$19,2,FALSE) -> TRADING OF COMERCIAL EXPLOSIVES | Q44: MGL001 | R44: =VLOOKUP(Q44,'Company Code'!$A$1:$B$7,2,FALSE) -> Mbogo Mining and General Supply Limited | U44: Being payment for purchase of Nails 2 kg @4000 | V44: 8000 | X44: =IF(V44="", W44, V44) -> 8000 | Y44: =IF(V44<>"","DR","CR") -> DR
A45: 02.01.2025 | B45: RV01-02012025 | D45: ONESMO NIBENGO NMB 61810095948 | E45: 57250100 | F45: =VLOOKUP(E45,'Improved Accounting codes'!C126:D2466,2,FALSE) -> Cash for office use Mbogo Mining and General Supply Limited | G45: 572501 | H45: =VLOOKUP(G45,'Improved Accounting codes'!A98:B2438,2,FALSE) -> Cash for Office Use | I45: BDD00102 | J45: =VLOOKUP(I45,'Section Code'!$B$1:$C$17,2,FALSE) -> Sales and Marketing Section | K45: BDD001 | L45: =VLOOKUP(K45,'Department Codes'!$A$1:$B$4,2,FALSE) -> Business Development Department | M45: MGL00121 | N45: =VLOOKUP(M45,'Location Code Code'!$E$2:$F$22,2,FALSE) -> HEAD OFFICE NYASHISHI MWANZA | O45: MGL0012 | P45: =VLOOKUP(O45,'Business Code'!$C$1:$D$19,2,FALSE) -> TRADING OF COMERCIAL EXPLOSIVES | Q45: MGL001 | R45: =VLOOKUP(Q45,'Company Code'!$A$1:$B$7,2,FALSE) -> Mbogo Mining and General Supply Limited | U45: Being payment for purchase of Nails 2 kg @4000 | W45: 8000 | X45: =IF(V45="", W45, V45) -> 8000 | Y45: =IF(V45<>"","DR","CR") -> CR
A46: 02.01.2025 | B46: RV01-02012025 | D46: ONESMO NIBENGO NMB 61810095948 | E46: 62760100 | F46: =VLOOKUP(E46,'Improved Accounting codes'!C127:D2467,2,FALSE) -> Tools | G46: 627601 | H46: =VLOOKUP(G46,'Improved Accounting codes'!A99:B2439,2,FALSE) -> Spare parts, Repair,Acetone and Maintenance | I46: BDD00102 | J46: =VLOOKUP(I46,'Section Code'!$B$1:$C$17,2,FALSE) -> Sales and Marketing Section | K46: BDD001 | L46: =VLOOKUP(K46,'Department Codes'!$A$1:$B$4,2,FALSE) -> Business Development Department | M46: MGL00121 | N46: =VLOOKUP(M46,'Location Code Code'!$E$2:$F$22,2,FALSE) -> HEAD OFFICE NYASHISHI MWANZA | O46: MGL0012 | P46: =VLOOKUP(O46,'Business Code'!$C$1:$D$19,2,FALSE) -> TRADING OF COMERCIAL EXPLOSIVES | Q46: MGL001 | R46: =VLOOKUP(Q46,'Company Code'!$A$1:$B$7,2,FALSE) -> Mbogo Mining and General Supply Limited | U46: Being payment for purchase of roofing timber 3.5m 8 pcs@5000 | V46: 40000 | X46: =IF(V46="", W46, V46) -> 40000 | Y46: =IF(V46<>"","DR","CR") -> DR
A47: 02.01.2025 | B47: RV01-02012025 | D47: ONESMO NIBENGO NMB 61810095948 | E47: 57250100 | F47: =VLOOKUP(E47,'Improved Accounting codes'!C128:D2468,2,FALSE) -> Cash for office use Mbogo Mining and General Supply Limited | G47: 572501 | H47: =VLOOKUP(G47,'Improved Accounting codes'!A100:B2440,2,FALSE) -> Cash for Office Use | I47: BDD00102 | J47: =VLOOKUP(I47,'Section Code'!$B$1:$C$17,2,FALSE) -> Sales and Marketing Section | K47: BDD001 | L47: =VLOOKUP(K47,'Department Codes'!$A$1:$B$4,2,FALSE) -> Business Development Department | M47: MGL00121 | N47: =VLOOKUP(M47,'Location Code Code'!$E$2:$F$22,2,FALSE) -> HEAD OFFICE NYASHISHI MWANZA | O47: MGL0012 | P47: =VLOOKUP(O47,'Business Code'!$C$1:$D$19,2,FALSE) -> TRADING OF COMERCIAL EXPLOSIVES | Q47: MGL001 | R47: =VLOOKUP(Q47,'Company Code'!$A$1:$B$7,2,FALSE) -> Mbogo Mining and General Supply Limited | U47: Being payment for purchase of roofing timber 3.5m 8 pcs@5000 | W47: 40000 | X47: =IF(V47="", W47, V47) -> 40000 | Y47: =IF(V47<>"","DR","CR") -> CR
A48: 03.01.2025 | B48: RV01-03012025 | D48: SALOME KISINZA DAUD 0762013110 M -PESA | E48: 65160105 | F48: =VLOOKUP(E48,'Improved Accounting codes'!C129:D2469,2,FALSE) -> Family benefits | G48: 651601 | H48: =VLOOKUP(G48,'Improved Accounting codes'!A101:B2441,2,FALSE) -> Direct Compensation, Allowance and Benefits | I48: BDD00102 | J48: =VLOOKUP(I48,'Section Code'!$B$1:$C$17,2,FALSE) -> Sales and Marketing Section | K48: BDD001 | L48: =VLOOKUP(K48,'Department Codes'!$A$1:$B$4,2,FALSE) -> Business Development Department | M48: MGL00121 | N48: =VLOOKUP(M48,'Location Code Code'!$E$2:$F$22,2,FALSE) -> HEAD OFFICE NYASHISHI MWANZA | O48: MGL0012 | P48: =VLOOKUP(O48,'Business Code'!$C$1:$D$19,2,FALSE) -> TRADING OF COMERCIAL EXPLOSIVES | Q48: MGL001 | R48: =VLOOKUP(Q48,'Company Code'!$A$1:$B$7,2,FALSE) -> Mbogo Mining and General Supply Limited | U48: Being payment for purchase of Rice for funeral at ihayabuyaga 100 kg@ | V48: 186000 | X48: =IF(V48="", W48, V48) -> 186000 | Y48: =IF(V48<>"","DR","CR") -> DR
A49: 03.01.2025 | B49: RV01-03012025 | D49: SALOME KISINZA DAUD 0762013110 M -PESA | E49: 57250100 | F49: =VLOOKUP(E49,'Improved Accounting codes'!C130:D2470,2,FALSE) -> Cash for office use Mbogo Mining and General Supply Limited | G49: 572501 | H49: =VLOOKUP(G49,'Improved Accounting codes'!A102:B2442,2,FALSE) -> Cash for Office Use | I49: BDD00102 | J49: =VLOOKUP(I49,'Section Code'!$B$1:$C$17,2,FALSE) -> Sales and Marketing Section | K49: BDD001 | L49: =VLOOKUP(K49,'Department Codes'!$A$1:$B$4,2,FALSE) -> Business Development Department | M49: MGL00121 | N49: =VLOOKUP(M49,'Location Code Code'!$E$2:$F$22,2,FALSE) -> HEAD OFFICE NYASHISHI MWANZA | O49: MGL0012 | P49: =VLOOKUP(O49,'Business Code'!$C$1:$D$19,2,FALSE) -> TRADING OF COMERCIAL EXPLOSIVES | Q49: MGL001 | R49: =VLOOKUP(Q49,'Company Code'!$A$1:$B$7,2,FALSE) -> Mbogo Mining and General Supply Limited | U49: Being payment for purchase of Rice for funeral at ihayabuyaga 100 kg@ | W49: 186000 | X49: =IF(V49="", W49, V49) -> 186000 | Y49: =IF(V49<>"","DR","CR") -> CR
A50: 03.01.2025 | B50: RV01-03012025 | D50: CRDB BANK PLC | E50: 63860710 | F50: =VLOOKUP(E50,'Improved Accounting codes'!C131:D2471,2,FALSE) -> CRDB TZS:0150481116500 | G50: 638607 | H50: =VLOOKUP(G50,'Improved Accounting codes'!A103:B2443,2,FALSE) -> Bank Charges | I50: FAD00102 | J50: =VLOOKUP(I50,'Section Code'!$B$1:$C$17,2,FALSE) -> Finance Section | K50: FAD001 | L50: =VLOOKUP(K50,'Department Codes'!$A$1:$B$4,2,FALSE) -> Finance and Administration Department | M50: MGL00121 | N50: =VLOOKUP(M50,'Location Code Code'!$E$2:$F$22,2,FALSE) -> HEAD OFFICE NYASHISHI MWANZA | O50: MGL0012 | P50: =VLOOKUP(O50,'Business Code'!$C$1:$D$19,2,FALSE) -> TRADING OF COMERCIAL EXPLOSIVES | Q50: MGL001 | R50: =VLOOKUP(Q50,'Company Code'!$A$1:$B$7,2,FALSE) -> Mbogo Mining and General Supply Limited | U50: Transaction cost.Tsh 6000/= | V50: 6000 | X50: =IF(V50="", W50, V50) -> 6000 | Y50: =IF(V50<>"","DR","CR") -> DR
A51: 03.01.2025 | B51: RV01-03012025 | D51: CRDB BANK PLC | E51: 56150600 | F51: =VLOOKUP(E51,'Improved Accounting codes'!C132:D2472,2,FALSE) -> CRDB TZS:0150481116500 | G51: 561506 | H51: =VLOOKUP(G51,'Improved Accounting codes'!A104:B2444,2,FALSE) -> CRDB BANK PLC | I51: FAD00102 | J51: =VLOOKUP(I51,'Section Code'!$B$1:$C$17,2,FALSE) -> Finance Section | K51: FAD001 | L51: =VLOOKUP(K51,'Department Codes'!$A$1:$B$4,2,FALSE) -> Finance and Administration Department | M51: MGL00121 | N51: =VLOOKUP(M51,'Location Code Code'!$E$2:$F$22,2,FALSE) -> HEAD OFFICE NYASHISHI MWANZA | O51: MGL0012 | P51: =VLOOKUP(O51,'Business Code'!$C$1:$D$19,2,FALSE) -> TRADING OF COMERCIAL EXPLOSIVES | Q51: MGL001 | R51: =VLOOKUP(Q51,'Company Code'!$A$1:$B$7,2,FALSE) -> Mbogo Mining and General Supply Limited | U51: Transaction cost.Tsh 6000/= | W51: 6000 | X51: =IF(V51="", W51, V51) -> 6000 | Y51: =IF(V51<>"","DR","CR") -> CR
A52: 03.01.2025 | B52: RV01-03012025 | D52: BARNABAS NIBENGO MPESA 0765427622 | E52: 62360104 | F52: =VLOOKUP(E52,'Improved Accounting codes'!C133:D2473,2,FALSE) -> Accomodation, Transport and meals expense | G52: 623601 | H52: =VLOOKUP(G52,'Improved Accounting codes'!A105:B2445,2,FALSE) -> Staff transport | I52: BDD00102 | J52: =VLOOKUP(I52,'Section Code'!$B$1:$C$17,2,FALSE) -> Sales and Marketing Section | K52: BDD001 | L52: =VLOOKUP(K52,'Department Codes'!$A$1:$B$4,2,FALSE) -> Business Development Department | M52: MGL00121 | N52: =VLOOKUP(M52,'Location Code Code'!$E$2:$F$22,2,FALSE) -> HEAD OFFICE NYASHISHI MWANZA | O52: MGL0012 | P52: =VLOOKUP(O52,'Business Code'!$C$1:$D$19,2,FALSE) -> TRADING OF COMERCIAL EXPLOSIVES | Q52: MGL001 | R52: =VLOOKUP(Q52,'Company Code'!$A$1:$B$7,2,FALSE) -> Mbogo Mining and General Supply Limited | U52: Being payment for meals & accommodation allowance | V52: 600000 | X52: =IF(V52="", W52, V52) -> 600000 | Y52: =IF(V52<>"","DR","CR") -> DR
A53: 03.01.2025 | B53: RV01-03012025 | D53: BARNABAS NIBENGO MPESA 0765427622 | E53: 57250100 | F53: =VLOOKUP(E53,'Improved Accounting codes'!C134:D2474,2,FALSE) -> Cash for office use Mbogo Mining and General Supply Limited | G53: 572501 | H53: =VLOOKUP(G53,'Improved Accounting codes'!A106:B2446,2,FALSE) -> Cash for Office Use | I53: BDD00102 | J53: =VLOOKUP(I53,'Section Code'!$B$1:$C$17,2,FALSE) -> Sales and Marketing Section | K53: BDD001 | L53: =VLOOKUP(K53,'Department Codes'!$A$1:$B$4,2,FALSE) -> Business Development Department | M53: MGL00121 | N53: =VLOOKUP(M53,'Location Code Code'!$E$2:$F$22,2,FALSE) -> HEAD OFFICE NYASHISHI MWANZA | O53: MGL0012 | P53: =VLOOKUP(O53,'Business Code'!$C$1:$D$19,2,FALSE) -> TRADING OF COMERCIAL EXPLOSIVES | Q53: MGL001 | R53: =VLOOKUP(Q53,'Company Code'!$A$1:$B$7,2,FALSE) -> Mbogo Mining and General Supply Limited | U53: Being payment for meals & accommodation allowance | W53: 600000 | X53: =IF(V53="", W53, V53) -> 600000 | Y53: =IF(V53<>"","DR","CR") -> CR
A54: 03.01.2025 | B54: RV01-03012025 | D54: BELINDA FREEMAN TIGO PESA 0676302325 | E54: 62360104 | F54: =VLOOKUP(E54,'Improved Accounting codes'!C135:D2475,2,FALSE) -> Accomodation, Transport and meals expense | G54: 623601 | H54: =VLOOKUP(G54,'Improved Accounting codes'!A107:B2447,2,FALSE) -> Staff transport | I54: BDD00102 | J54: =VLOOKUP(I54,'Section Code'!$B$1:$C$17,2,FALSE) -> Sales and Marketing Section | K54: BDD001 | L54: =VLOOKUP(K54,'Department Codes'!$A$1:$B$4,2,FALSE) -> Business Development Department | M54: MGL00121 | N54: =VLOOKUP(M54,'Location Code Code'!$E$2:$F$22,2,FALSE) -> HEAD OFFICE NYASHISHI MWANZA | O54: MGL0012 | P54: =VLOOKUP(O54,'Business Code'!$C$1:$D$19,2,FALSE) -> TRADING OF COMERCIAL EXPLOSIVES | Q54: MGL001 | R54: =VLOOKUP(Q54,'Company Code'!$A$1:$B$7,2,FALSE) -> Mbogo Mining and General Supply Limited | U54: Being payment for transport fare from Nyashishi to Ihayabuyaga for hpysical stock count of December | V54: 20000 | X54: =IF(V54="", W54, V54) -> 20000 | Y54: =IF(V54<>"","DR","CR") -> DR
A55: 03.01.2025 | B55: RV01-03012025 | D55: BELINDA FREEMAN TIGO PESA 0676302325 | E55: 57250100 | F55: =VLOOKUP(E55,'Improved Accounting codes'!C136:D2476,2,FALSE) -> Cash for office use Mbogo Mining and General Supply Limited | G55: 572501 | H55: =VLOOKUP(G55,'Improved Accounting codes'!A108:B2448,2,FALSE) -> Cash for Office Use | I55: BDD00102 | J55: =VLOOKUP(I55,'Section Code'!$B$1:$C$17,2,FALSE) -> Sales and Marketing Section | K55: BDD001 | L55: =VLOOKUP(K55,'Department Codes'!$A$1:$B$4,2,FALSE) -> Business Development Department | M55: MGL00121 | N55: =VLOOKUP(M55,'Location Code Code'!$E$2:$F$22,2,FALSE) -> HEAD OFFICE NYASHISHI MWANZA | O55: MGL0012 | P55: =VLOOKUP(O55,'Business Code'!$C$1:$D$19,2,FALSE) -> TRADING OF COMERCIAL EXPLOSIVES | Q55: MGL001 | R55: =VLOOKUP(Q55,'Company Code'!$A$1:$B$7,2,FALSE) -> Mbogo Mining and General Supply Limited | U55: Being payment for transport fare from Nyashishi to Ihayabuyaga for hpysical stock count of December | W55: 20000 | X55: =IF(V55="", W55, V55) -> 20000 | Y55: =IF(V55<>"","DR","CR") -> CR
A56: 03.01.2025 | B56: RV01-03012025 | D56: JIRIBERI NCHAMU MPESA 0748865433 | E56: 62360104 | F56: =VLOOKUP(E56,'Improved Accounting codes'!C137:D2477,2,FALSE) -> Accomodation, Transport and meals expense | G56: 623601 | H56: =VLOOKUP(G56,'Improved Accounting codes'!A109:B2449,2,FALSE) -> Staff transport | I56: BDD00102 | J56: =VLOOKUP(I56,'Section Code'!$B$1:$C$17,2,FALSE) -> Sales and Marketing Section | K56: BDD001 | L56: =VLOOKUP(K56,'Department Codes'!$A$1:$B$4,2,FALSE) -> Business Development Department | M56: MGL00121 | N56: =VLOOKUP(M56,'Location Code Code'!$E$2:$F$22,2,FALSE) -> HEAD OFFICE NYASHISHI MWANZA | O56: MGL0012 | P56: =VLOOKUP(O56,'Business Code'!$C$1:$D$19,2,FALSE) -> TRADING OF COMERCIAL EXPLOSIVES | Q56: MGL001 | R56: =VLOOKUP(Q56,'Company Code'!$A$1:$B$7,2,FALSE) -> Mbogo Mining and General Supply Limited | U56: Being payment for Mr.Suresh , meals & accommodation allowance at Mwanza site for 10 days@20,000 | V56: 200000 | X56: =IF(V56="", W56, V56) -> 200000 | Y56: =IF(V56<>"","DR","CR") -> DR
A57: 03.01.2025 | B57: RV01-03012025 | D57: JIRIBERI NCHAMU MPESA 0748865433 | E57: 57250100 | F57: =VLOOKUP(E57,'Improved Accounting codes'!C138:D2478,2,FALSE) -> Cash for office use Mbogo Mining and General Supply Limited | G57: 572501 | H57: =VLOOKUP(G57,'Improved Accounting codes'!A110:B2450,2,FALSE) -> Cash for Office Use | I57: BDD00102 | J57: =VLOOKUP(I57,'Section Code'!$B$1:$C$17,2,FALSE) -> Sales and Marketing Section | K57: BDD001 | L57: =VLOOKUP(K57,'Department Codes'!$A$1:$B$4,2,FALSE) -> Business Development Department | M57: MGL00121 | N57: =VLOOKUP(M57,'Location Code Code'!$E$2:$F$22,2,FALSE) -> HEAD OFFICE NYASHISHI MWANZA | O57: MGL0012 | P57: =VLOOKUP(O57,'Business Code'!$C$1:$D$19,2,FALSE) -> TRADING OF COMERCIAL EXPLOSIVES | Q57: MGL001 | R57: =VLOOKUP(Q57,'Company Code'!$A$1:$B$7,2,FALSE) -> Mbogo Mining and General Supply Limited | U57: Being payment for Mr.Suresh , meals & accommodation allowance at Mwanza site for 10 days@20,000 | W57: 200000 | X57: =IF(V57="", W57, V57) -> 200000 | Y57: =IF(V57<>"","DR","CR") -> CR
A58: 04.01.2025 | B58: RV01-04012025 | C58: 141 | D58: EPIFANIA FRANK ODANCE | E58: 57250100 | F58: =VLOOKUP(E58,'Improved Accounting codes'!C91:D2431,2,FALSE) -> Cash for office use Mbogo Mining and General Supply Limited | G58: 572501 | H58: =VLOOKUP(G58,'Improved Accounting codes'!A77:B2417,2,FALSE) -> Cash for Office Use | I58: FAD00102 | J58: =VLOOKUP(I58,'Section Code'!$B$1:$C$17,2,FALSE) -> Finance Section | K58: FAD001 | L58: =VLOOKUP(K58,'Department Codes'!$A$1:$B$4,2,FALSE) -> Finance and Administration Department | M58: MGL00121 | N58: =VLOOKUP(M58,'Location Code Code'!$E$2:$F$22,2,FALSE) -> HEAD OFFICE NYASHISHI MWANZA | O58: MGL0012 | P58: =VLOOKUP(O58,'Business Code'!$C$1:$D$19,2,FALSE) -> TRADING OF COMERCIAL EXPLOSIVES | Q58: MGL001 | R58: =VLOOKUP(Q58,'Company Code'!$A$1:$B$7,2,FALSE) -> Mbogo Mining and General Supply Limited | U58: CHQ.NO. 000141 EPIFANIA FRANK ODANCE | V58: 1380000 | X58: =IF(V58="", W58, V58) -> 1380000 | Y58: =IF(V58<>"","DR","CR") -> DR
A59: 04.01.2025 | B59: RV01-04012025 | C59: 141 | D59: EPIFANIA FRANK ODANCE | E59: 56150600 | F59: =VLOOKUP(E59,'Improved Accounting codes'!C92:D2432,2,FALSE) -> CRDB TZS:0150481116500 | G59: 561506 | H59: =VLOOKUP(G59,'Improved Accounting codes'!A64:B2404,2,FALSE) -> CRDB BANK PLC | I59: FAD00102 | J59: =VLOOKUP(I59,'Section Code'!$B$1:$C$17,2,FALSE) -> Finance Section | K59: FAD001 | L59: =VLOOKUP(K59,'Department Codes'!$A$1:$B$4,2,FALSE) -> Finance and Administration Department | M59: MGL00121 | N59: =VLOOKUP(M59,'Location Code Code'!$E$2:$F$22,2,FALSE) -> HEAD OFFICE NYASHISHI MWANZA | O59: MGL0012 | P59: =VLOOKUP(O59,'Business Code'!$C$1:$D$19,2,FALSE) -> TRADING OF COMERCIAL EXPLOSIVES | Q59: MGL001 | R59: =VLOOKUP(Q59,'Company Code'!$A$1:$B$7,2,FALSE) -> Mbogo Mining and General Supply Limited | U59: CHQ.NO. 000141 EPIFANIA FRANK ODANCE | W59: 1380000 | X59: =IF(V59="", W59, V59) -> 1380000 | Y59: =IF(V59<>"","DR","CR") -> CR
A60: 04.01.2025 | B60: RV01-04012025 | D60: TROPICAL TRAVEL SERVICES CO LTD 015C913091100 CRDB | E60: 41840500 | F60: =VLOOKUP(E60,'Improved Accounting codes'!C93:D2433,2,FALSE) -> Tropical Travel Services Co LTD | G60: 418405 | H60: =VLOOKUP(G60,'Improved Accounting codes'!A65:B2405,2,FALSE) -> Accounts Payable - Service Provider | I60: FAD00102 | J60: =VLOOKUP(I60,'Section Code'!$B$1:$C$17,2,FALSE) -> Finance Section | K60: FAD001 | L60: =VLOOKUP(K60,'Department Codes'!$A$1:$B$4,2,FALSE) -> Finance and Administration Department | M60: MGL00121 | N60: =VLOOKUP(M60,'Location Code Code'!$E$2:$F$22,2,FALSE) -> HEAD OFFICE NYASHISHI MWANZA | O60: MGL0012 | P60: =VLOOKUP(O60,'Business Code'!$C$1:$D$19,2,FALSE) -> TRADING OF COMERCIAL EXPLOSIVES | Q60: MGL001 | R60: =VLOOKUP(Q60,'Company Code'!$A$1:$B$7,2,FALSE) -> Mbogo Mining and General Supply Limited | U60: Being payment for Air ticket for MD from Mwanza to Dar | V60: 1785300 | X60: =IF(V60="", W60, V60) -> 1785300 | Y60: =IF(V60<>"","DR","CR") -> DR
A61: 04.01.205 | B61: RV01-04012025 | D61: TROPICAL TRAVEL SERVICES CO LTD 015C913091100 CRDB | E61: 57250100 | F61: =VLOOKUP(E61,'Improved Accounting codes'!C94:D2434,2,FALSE) -> Cash for office use Mbogo Mining and General Supply Limited | G61: 572501 | H61: =VLOOKUP(G61,'Improved Accounting codes'!A66:B2406,2,FALSE) -> Cash for Office Use | I61: FAD00102 | J61: =VLOOKUP(I61,'Section Code'!$B$1:$C$17,2,FALSE) -> Finance Section | K61: FAD001 | L61: =VLOOKUP(K61,'Department Codes'!$A$1:$B$4,2,FALSE) -> Finance and Administration Department | M61: MGL00121 | N61: =VLOOKUP(M61,'Location Code Code'!$E$2:$F$22,2,FALSE) -> HEAD OFFICE NYASHISHI MWANZA | O61: MGL0012 | P61: =VLOOKUP(O61,'Business Code'!$C$1:$D$19,2,FALSE) -> TRADING OF COMERCIAL EXPLOSIVES | Q61: MGL001 | R61: =VLOOKUP(Q61,'Company Code'!$A$1:$B$7,2,FALSE) -> Mbogo Mining and General Supply Limited | U61: Being payment for Air ticket for MD from Mwanza to Dar | W61: 1785300 | X61: =IF(V61="", W61, V61) -> 1785300 | Y61: =IF(V61<>"","DR","CR") -> CR
A62: 04.01.205 | B62: RV01-04012025 | D62: BARNABAS NIBENGO MPESA 0765427622 | E62: 62360104 | F62: =VLOOKUP(E62,'Improved Accounting codes'!C95:D2435,2,FALSE) -> Accomodation, Transport and meals expense | G62: 623601 | H62: =VLOOKUP(G62,'Improved Accounting codes'!A67:B2407,2,FALSE) -> Staff transport | I62: BDD00102 | J62: =VLOOKUP(I62,'Section Code'!$B$1:$C$17,2,FALSE) -> Sales and Marketing Section | K62: BDD001 | L62: =VLOOKUP(K62,'Department Codes'!$A$1:$B$4,2,FALSE) -> Business Development Department | M62: MGL00121 | N62: =VLOOKUP(M62,'Location Code Code'!$E$2:$F$22,2,FALSE) -> HEAD OFFICE NYASHISHI MWANZA | O62: MGL0012 | P62: =VLOOKUP(O62,'Business Code'!$C$1:$D$19,2,FALSE) -> TRADING OF COMERCIAL EXPLOSIVES | Q62: MGL001 | R62: =VLOOKUP(Q62,'Company Code'!$A$1:$B$7,2,FALSE) -> Mbogo Mining and General Supply Limited | U62: Being payment for meals & accommodation allowance at Songea | V62: 1185000 | X62: =IF(V62="", W62, V62) -> 1185000 | Y62: =IF(V62<>"","DR","CR") -> DR
A63: 04.01.205 | B63: RV01-04012025 | D63: BARNABAS NIBENGO MPESA 0765427622 | E63: 57250100 | F63: =VLOOKUP(E63,'Improved Accounting codes'!C96:D2436,2,FALSE) -> Cash for office use Mbogo Mining and General Supply Limited | G63: 572501 | H63: =VLOOKUP(G63,'Improved Accounting codes'!A68:B2408,2,FALSE) -> Cash for Office Use | I63: BDD00102 | J63: =VLOOKUP(I63,'Section Code'!$B$1:$C$17,2,FALSE) -> Sales and Marketing Section | K63: BDD001 | L63: =VLOOKUP(K63,'Department Codes'!$A$1:$B$4,2,FALSE) -> Business Development Department | M63: MGL00121 | N63: =VLOOKUP(M63,'Location Code Code'!$E$2:$F$22,2,FALSE) -> HEAD OFFICE NYASHISHI MWANZA | O63: MGL0012 | P63: =VLOOKUP(O63,'Business Code'!$C$1:$D$19,2,FALSE) -> TRADING OF COMERCIAL EXPLOSIVES | Q63: MGL001 | R63: =VLOOKUP(Q63,'Company Code'!$A$1:$B$7,2,FALSE) -> Mbogo Mining and General Supply Limited | U63: Being payment for meals & accommodation allowance at Songea | W63: 1185000 | X63: =IF(V63="", W63, V63) -> 1185000 | Y63: =IF(V63<>"","DR","CR") -> CR
A64: 04.01.205 | B64: RV01-04012025 | D64: BELINDA FREEMAN TIGO PESA 0676302325 | E64: 62360104 | F64: =VLOOKUP(E64,'Improved Accounting codes'!C97:D2437,2,FALSE) -> Accomodation, Transport and meals expense | G64: 623601 | H64: =VLOOKUP(G64,'Improved Accounting codes'!A69:B2409,2,FALSE) -> Staff transport | I64: BDD00102 | J64: =VLOOKUP(I64,'Section Code'!$B$1:$C$17,2,FALSE) -> Sales and Marketing Section | K64: BDD001 | L64: =VLOOKUP(K64,'Department Codes'!$A$1:$B$4,2,FALSE) -> Business Development Department | M64: MGL00121 | N64: =VLOOKUP(M64,'Location Code Code'!$E$2:$F$22,2,FALSE) -> HEAD OFFICE NYASHISHI MWANZA | O64: MGL0012 | P64: =VLOOKUP(O64,'Business Code'!$C$1:$D$19,2,FALSE) -> TRADING OF COMERCIAL EXPLOSIVES | Q64: MGL001 | R64: =VLOOKUP(Q64,'Company Code'!$A$1:$B$7,2,FALSE) -> Mbogo Mining and General Supply Limited | U64: 1.Being payment for transport fare from Nyashishi to Ihayabuyaga for hpysical stock count of December .Tzs 20,000/= | V64: 20000 | X64: =IF(V64="", W64, V64) -> 20000 | Y64: =IF(V64<>"","DR","CR") -> DR
A65: 04.01.205 | B65: RV01-04012025 | D65: BELINDA FREEMAN TIGO PESA 0676302325 | E65: 57250100 | F65: =VLOOKUP(E65,'Improved Accounting codes'!C98:D2438,2,FALSE) -> Cash for office use Mbogo Mining and General Supply Limited | G65: 572501 | H65: =VLOOKUP(G65,'Improved Accounting codes'!A70:B2410,2,FALSE) -> Cash for Office Use | I65: BDD00102 | J65: =VLOOKUP(I65,'Section Code'!$B$1:$C$17,2,FALSE) -> Sales and Marketing Section | K65: BDD001 | L65: =VLOOKUP(K65,'Department Codes'!$A$1:$B$4,2,FALSE) -> Business Development Department | M65: MGL00121 | N65: =VLOOKUP(M65,'Location Code Code'!$E$2:$F$22,2,FALSE) -> HEAD OFFICE NYASHISHI MWANZA | O65: MGL0012 | P65: =VLOOKUP(O65,'Business Code'!$C$1:$D$19,2,FALSE) -> TRADING OF COMERCIAL EXPLOSIVES | Q65: MGL001 | R65: =VLOOKUP(Q65,'Company Code'!$A$1:$B$7,2,FALSE) -> Mbogo Mining and General Supply Limited | U65: 1.Being payment for transport fare from Nyashishi to Ihayabuyaga for hpysical stock count of December .Tzs 20,000/= | W65: 20000 | X65: =IF(V65="", W65, V65) -> 20000 | Y65: =IF(V65<>"","DR","CR") -> CR
A66: 04.01.205 | B66: RV01-04012025 | D66: JIRIBERI NCHAMU MPESA 0748865433 | E66: 62360104 | F66: =VLOOKUP(E66,'Improved Accounting codes'!C99:D2439,2,FALSE) -> Accomodation, Transport and meals expense | G66: 623601 | H66: =VLOOKUP(G66,'Improved Accounting codes'!A71:B2411,2,FALSE) -> Staff transport | I66: BDD00102 | J66: =VLOOKUP(I66,'Section Code'!$B$1:$C$17,2,FALSE) -> Sales and Marketing Section | K66: BDD001 | L66: =VLOOKUP(K66,'Department Codes'!$A$1:$B$4,2,FALSE) -> Business Development Department | M66: MGL00121 | N66: =VLOOKUP(M66,'Location Code Code'!$E$2:$F$22,2,FALSE) -> HEAD OFFICE NYASHISHI MWANZA | O66: MGL0012 | P66: =VLOOKUP(O66,'Business Code'!$C$1:$D$19,2,FALSE) -> TRADING OF COMERCIAL EXPLOSIVES | Q66: MGL001 | R66: =VLOOKUP(Q66,'Company Code'!$A$1:$B$7,2,FALSE) -> Mbogo Mining and General Supply Limited | U66: 1. Being payment for Mr.Suresh , meals & accommodation allowance at Mwanza site for 10 days@20,000= 200,000/=. | V66: 200000 | X66: =IF(V66="", W66, V66) -> 200000 | Y66: =IF(V66<>"","DR","CR") -> DR
A67: 04.01.205 | B67: RV01-04012025 | D67: JIRIBERI NCHAMU MPESA 0748865433 | E67: 57250100 | F67: =VLOOKUP(E67,'Improved Accounting codes'!C100:D2440,2,FALSE) -> Cash for office use Mbogo Mining and General Supply Limited | G67: 572501 | H67: =VLOOKUP(G67,'Improved Accounting codes'!A72:B2412,2,FALSE) -> Cash for Office Use | I67: BDD00102 | J67: =VLOOKUP(I67,'Section Code'!$B$1:$C$17,2,FALSE) -> Sales and Marketing Section | K67: BDD001 | L67: =VLOOKUP(K67,'Department Codes'!$A$1:$B$4,2,FALSE) -> Business Development Department | M67: MGL00121 | N67: =VLOOKUP(M67,'Location Code Code'!$E$2:$F$22,2,FALSE) -> HEAD OFFICE NYASHISHI MWANZA | O67: MGL0012 | P67: =VLOOKUP(O67,'Business Code'!$C$1:$D$19,2,FALSE) -> TRADING OF COMERCIAL EXPLOSIVES | Q67: MGL001 | R67: =VLOOKUP(Q67,'Company Code'!$A$1:$B$7,2,FALSE) -> Mbogo Mining and General Supply Limited | U67: 1. Being payment for Mr.Suresh , meals & accommodation allowance at Mwanza site for 10 days@20,000= 200,000/=. | W67: 200000 | X67: =IF(V67="", W67, V67) -> 200000 | Y67: =IF(V67<>"","DR","CR") -> CR
A68: 04.01.205 | B68: RV01-04012025 | D68: NEEMA RAPHAEL 0744979075 M -PESA | E68: 62360104 | F68: =VLOOKUP(E68,'Improved Accounting codes'!C101:D2441,2,FALSE) -> Accomodation, Transport and meals expense | G68: 623601 | H68: =VLOOKUP(G68,'Improved Accounting codes'!A73:B2413,2,FALSE) -> Staff transport | I68: BDD00102 | J68: =VLOOKUP(I68,'Section Code'!$B$1:$C$17,2,FALSE) -> Sales and Marketing Section | K68: BDD001 | L68: =VLOOKUP(K68,'Department Codes'!$A$1:$B$4,2,FALSE) -> Business Development Department | M68: MGL00121 | N68: =VLOOKUP(M68,'Location Code Code'!$E$2:$F$22,2,FALSE) -> HEAD OFFICE NYASHISHI MWANZA | O68: MGL0012 | P68: =VLOOKUP(O68,'Business Code'!$C$1:$D$19,2,FALSE) -> TRADING OF COMERCIAL EXPLOSIVES | Q68: MGL001 | R68: =VLOOKUP(Q68,'Company Code'!$A$1:$B$7,2,FALSE) -> Mbogo Mining and General Supply Limited | U68: Being payment for transportation fare for Filbert Mathias, Benjamin Sabuni, Juma Ramadhani, Kulwa Kusekwaand Neema Raphael (6 days from 04/-10/1/2025).Tsh 180,000 | V68: 355600 | X68: =IF(V68="", W68, V68) -> 355600 | Y68: =IF(V68<>"","DR","CR") -> DR
A69: 04.01.205 | B69: RV01-04012025 | D69: NEEMA RAPHAEL 0744979075 M -PESA | E69: 57250100 | F69: =VLOOKUP(E69,'Improved Accounting codes'!C102:D2442,2,FALSE) -> Cash for office use Mbogo Mining and General Supply Limited | G69: 572501 | H69: =VLOOKUP(G69,'Improved Accounting codes'!A74:B2414,2,FALSE) -> Cash for Office Use | I69: BDD00102 | J69: =VLOOKUP(I69,'Section Code'!$B$1:$C$17,2,FALSE) -> Sales and Marketing Section | K69: BDD001 | L69: =VLOOKUP(K69,'Department Codes'!$A$1:$B$4,2,FALSE) -> Business Development Department | M69: MGL00121 | N69: =VLOOKUP(M69,'Location Code Code'!$E$2:$F$22,2,FALSE) -> HEAD OFFICE NYASHISHI MWANZA | O69: MGL0012 | P69: =VLOOKUP(O69,'Business Code'!$C$1:$D$19,2,FALSE) -> TRADING OF COMERCIAL EXPLOSIVES | Q69: MGL001 | R69: =VLOOKUP(Q69,'Company Code'!$A$1:$B$7,2,FALSE) -> Mbogo Mining and General Supply Limited | U69: Being payment for transportation fare for Filbert Mathias, Benjamin Sabuni, Juma Ramadhani, Kulwa Kusekwaand Neema Raphael (6 days from 04/-10/1/2025).Tsh 180,000 | W69: 355600 | X69: =IF(V69="", W69, V69) -> 355600 | Y69: =IF(V69<>"","DR","CR") -> CR
A70: 04.01.205 | B70: RV01-04012025 | D70: NEEMA RAPHAEL 0744979075 M -PESA | E70: 62360104 | F70: =VLOOKUP(E70,'Improved Accounting codes'!C103:D2443,2,FALSE) -> Accomodation, Transport and meals expense | G70: 623601 | H70: =VLOOKUP(G70,'Improved Accounting codes'!A75:B2415,2,FALSE) -> Staff transport | I70: BDD00102 | J70: =VLOOKUP(I70,'Section Code'!$B$1:$C$17,2,FALSE) -> Sales and Marketing Section | K70: BDD001 | L70: =VLOOKUP(K70,'Department Codes'!$A$1:$B$4,2,FALSE) -> Business Development Department | M70: MGL00121 | N70: =VLOOKUP(M70,'Location Code Code'!$E$2:$F$22,2,FALSE) -> HEAD OFFICE NYASHISHI MWANZA | O70: MGL0012 | P70: =VLOOKUP(O70,'Business Code'!$C$1:$D$19,2,FALSE) -> TRADING OF COMERCIAL EXPLOSIVES | Q70: MGL001 | R70: =VLOOKUP(Q70,'Company Code'!$A$1:$B$7,2,FALSE) -> Mbogo Mining and General Supply Limited | U70: Being payment for Food to staff | V70: 105000 | X70: =IF(V70="", W70, V70) -> 105000 | Y70: =IF(V70<>"","DR","CR") -> DR
A71: 04.01.205 | B71: RV01-04012025 | D71: NEEMA RAPHAEL 0744979075 M -PESA | E71: 57250100 | F71: =VLOOKUP(E71,'Improved Accounting codes'!C104:D2444,2,FALSE) -> Cash for office use Mbogo Mining and General Supply Limited | G71: 572501 | H71: =VLOOKUP(G71,'Improved Accounting codes'!A76:B2416,2,FALSE) -> Cash for Office Use | I71: BDD00102 | J71: =VLOOKUP(I71,'Section Code'!$B$1:$C$17,2,FALSE) -> Sales and Marketing Section | K71: BDD001 | L71: =VLOOKUP(K71,'Department Codes'!$A$1:$B$4,2,FALSE) -> Business Development Department | M71: MGL00121 | N71: =VLOOKUP(M71,'Location Code Code'!$E$2:$F$22,2,FALSE) -> HEAD OFFICE NYASHISHI MWANZA | O71: MGL0012 | P71: =VLOOKUP(O71,'Business Code'!$C$1:$D$19,2,FALSE) -> TRADING OF COMERCIAL EXPLOSIVES | Q71: MGL001 | R71: =VLOOKUP(Q71,'Company Code'!$A$1:$B$7,2,FALSE) -> Mbogo Mining and General Supply Limited | U71: Being payment for Food to staff | W71: 105000 | X71: =IF(V71="", W71, V71) -> 105000 | Y71: =IF(V71<>"","DR","CR") -> CR
A72: 04.01.205 | B72: RV01-04012025 | D72: NEEMA RAPHAEL 0744979075 M -PESA | E72: 62660101 | F72: =VLOOKUP(E72,'Improved Accounting codes'!C105:D2445,2,FALSE) -> Petrol | G72: 626601 | H72: =VLOOKUP(G72,'Improved Accounting codes'!A77:B2417,2,FALSE) -> Fuel Expenses | I72: =VLOOKUP(G72,'Improved Accounting codes'!A77:B2417,2,FALSE) -> Fuel Expenses | J72: BDD00102 | K72: =VLOOKUP(J72,'Section Code'!$B$1:$C$17,2,FALSE) -> Sales and Marketing Section | L72: BDD001 | M72: =VLOOKUP(L72,'Department Codes'!$A$1:$B$4,2,FALSE) -> Business Development Department | N72: MGL00121 | O72: =VLOOKUP(N72,'Location Code Code'!$E$2:$F$22,2,FALSE) -> HEAD OFFICE NYASHISHI MWANZA | P72: MGL0012 | Q72: MGL001 | R72: =VLOOKUP(Q72,'Company Code'!$A$1:$B$7,2,FALSE) -> Mbogo Mining and General Supply Limited | U72: Being payment for Fuel Transportation | V72: 45000 | X72: =IF(V72="", W72, V72) -> 45000 | Y72: =IF(V72<>"","DR","CR") -> DR
A73: 04.01.205 | B73: RV01-04012025 | D73: NEEMA RAPHAEL 0744979075 M -PESA | E73: 57250100 | F73: =VLOOKUP(E73,'Improved Accounting codes'!C106:D2446,2,FALSE) -> Cash for office use Mbogo Mining and General Supply Limited | G73: 572501 | H73: =VLOOKUP(G73,'Improved Accounting codes'!A78:B2418,2,FALSE) -> Cash for Office Use | I73: BDD00102 | J73: =VLOOKUP(I73,'Section Code'!$B$1:$C$17,2,FALSE) -> Sales and Marketing Section | K73: BDD001 | L73: =VLOOKUP(K73,'Department Codes'!$A$1:$B$4,2,FALSE) -> Business Development Department | M73: MGL00121 | N73: =VLOOKUP(M73,'Location Code Code'!$E$2:$F$22,2,FALSE) -> HEAD OFFICE NYASHISHI MWANZA | O73: MGL0012 | P73: =VLOOKUP(O73,'Business Code'!$C$1:$D$19,2,FALSE) -> TRADING OF COMERCIAL EXPLOSIVES | Q73: MGL001 | R73: =VLOOKUP(Q73,'Company Code'!$A$1:$B$7,2,FALSE) -> Mbogo Mining and General Supply Limited | U73: Being payment for Fuel Transportation | W73: 45000 | X73: =IF(V73="", W73, V73) -> 45000 | Y73: =IF(V73<>"","DR","CR") -> CR
A74: 04.01.205 | B74: RV01-04012025 | D74: NEEMA RAPHAEL 0744979075 M -PESA | E74: 60360100 | F74: =VLOOKUP(E74,'Improved Accounting codes'!C107:D2447,2,FALSE) -> Cost of packaging sold | G74: 603601 | H74: =VLOOKUP(G74,'Improved Accounting codes'!A79:B2419,2,FALSE) -> Cost of packaging sold | I74: BDD00102 | J74: =VLOOKUP(I74,'Section Code'!$B$1:$C$17,2,FALSE) -> Sales and Marketing Section | K74: BDD001 | L74: =VLOOKUP(K74,'Department Codes'!$A$1:$B$4,2,FALSE) -> Business Development Department | M74: MGL00121 | N74: =VLOOKUP(M74,'Location Code Code'!$E$2:$F$22,2,FALSE) -> HEAD OFFICE NYASHISHI MWANZA | O74: MGL0012 | P74: =VLOOKUP(O74,'Business Code'!$C$1:$D$19,2,FALSE) -> TRADING OF COMERCIAL EXPLOSIVES | Q74: MGL001 | R74: =VLOOKUP(Q74,'Company Code'!$A$1:$B$7,2,FALSE) -> Mbogo Mining and General Supply Limited | U74: Being payment for purchase of plastik bag 10pcs | V74: 7000 | X74: =IF(V74="", W74, V74) -> 7000 | Y74: =IF(V74<>"","DR","CR") -> DR
A75: 04.01.205 | B75: RV01-04012025 | D75: NEEMA RAPHAEL 0744979075 M -PESA | E75: 57250100 | F75: =VLOOKUP(E75,'Improved Accounting codes'!C108:D2448,2,FALSE) -> Cash for office use Mbogo Mining and General Supply Limited | G75: 572501 | H75: =VLOOKUP(G75,'Improved Accounting codes'!A80:B2420,2,FALSE) -> Cash for Office Use | I75: BDD00102 | J75: =VLOOKUP(I75,'Section Code'!$B$1:$C$17,2,FALSE) -> Sales and Marketing Section | K75: BDD001 | L75: =VLOOKUP(K75,'Department Codes'!$A$1:$B$4,2,FALSE) -> Business Development Department | M75: MGL00121 | N75: =VLOOKUP(M75,'Location Code Code'!$E$2:$F$22,2,FALSE) -> HEAD OFFICE NYASHISHI MWANZA | O75: MGL0012 | P75: =VLOOKUP(O75,'Business Code'!$C$1:$D$19,2,FALSE) -> TRADING OF COMERCIAL EXPLOSIVES | Q75: MGL001 | R75: =VLOOKUP(Q75,'Company Code'!$A$1:$B$7,2,FALSE) -> Mbogo Mining and General Supply Limited | U75: Being payment for purchase of plastik bag 10pcs | W75: 7000 | X75: =IF(V75="", W75, V75) -> 7000 | Y75: =IF(V75<>"","DR","CR") -> CR
A76: 04.01.205 | B76: RV01-04012025 | D76: NEEMA RAPHAEL 0744979075 M -PESA | E76: 61760403 | F76: =VLOOKUP(E76,'Improved Accounting codes'!C109:D2449,2,FALSE) -> Soap | G76: 617604 | H76: =VLOOKUP(G76,'Improved Accounting codes'!A81:B2421,2,FALSE) -> Labaratory product Supplies | I76: BDD00102 | J76: =VLOOKUP(I76,'Section Code'!$B$1:$C$17,2,FALSE) -> Sales and Marketing Section | K76: BDD001 | L76: =VLOOKUP(K76,'Department Codes'!$A$1:$B$4,2,FALSE) -> Business Development Department | M76: MGL00121 | N76: =VLOOKUP(M76,'Location Code Code'!$E$2:$F$22,2,FALSE) -> HEAD OFFICE NYASHISHI MWANZA | O76: MGL0012 | P76: =VLOOKUP(O76,'Business Code'!$C$1:$D$19,2,FALSE) -> TRADING OF COMERCIAL EXPLOSIVES | Q76: MGL001 | R76: =VLOOKUP(Q76,'Company Code'!$A$1:$B$7,2,FALSE) -> Mbogo Mining and General Supply Limited | U76: Being payment for purchase of Soap one caton | V76: 11000 | X76: =IF(V76="", W76, V76) -> 11000 | Y76: =IF(V76<>"","DR","CR") -> DR
A77: 04.01.205 | B77: RV01-04012025 | D77: NEEMA RAPHAEL 0744979075 M -PESA | E77: 57250100 | F77: =VLOOKUP(E77,'Improved Accounting codes'!C110:D2450,2,FALSE) -> Cash for office use Mbogo Mining and General Supply Limited | G77: 572501 | H77: =VLOOKUP(G77,'Improved Accounting codes'!A82:B2422,2,FALSE) -> Cash for Office Use | I77: BDD00102 | J77: =VLOOKUP(I77,'Section Code'!$B$1:$C$17,2,FALSE) -> Sales and Marketing Section | K77: BDD001 | L77: =VLOOKUP(K77,'Department Codes'!$A$1:$B$4,2,FALSE) -> Business Development Department | M77: MGL00121 | N77: =VLOOKUP(M77,'Location Code Code'!$E$2:$F$22,2,FALSE) -> HEAD OFFICE NYASHISHI MWANZA | O77: MGL0012 | P77: =VLOOKUP(O77,'Business Code'!$C$1:$D$19,2,FALSE) -> TRADING OF COMERCIAL EXPLOSIVES | Q77: MGL001 | R77: =VLOOKUP(Q77,'Company Code'!$A$1:$B$7,2,FALSE) -> Mbogo Mining and General Supply Limited | U77: Being payment for purchase of Soap one caton | W77: 11000 | X77: =IF(V77="", W77, V77) -> 11000 | Y77: =IF(V77<>"","DR","CR") -> CR
A78: 04.01.205 | B78: RV01-04012025 | D78: CRDB BANK PLC | E78: 62360104 | F78: =VLOOKUP(E78,'Improved Accounting codes'!C111:D2451,2,FALSE) -> Accomodation, Transport and meals expense | G78: 623601 | H78: =VLOOKUP(G78,'Improved Accounting codes'!A131:B2471,2,FALSE) -> Staff transport | I78: FAD00102 | J78: =VLOOKUP(I78,'Section Code'!$B$1:$C$17,2,FALSE) -> Finance Section | K78: FAD001 | L78: =VLOOKUP(K78,'Department Codes'!$A$1:$B$4,2,FALSE) -> Finance and Administration Department | M78: MGL00121 | N78: =VLOOKUP(M78,'Location Code Code'!$E$2:$F$22,2,FALSE) -> HEAD OFFICE NYASHISHI MWANZA | O78: MGL0012 | P78: =VLOOKUP(O78,'Business Code'!$C$1:$D$19,2,FALSE) -> TRADING OF COMERCIAL EXPLOSIVES | Q78: MGL001 | R78: =VLOOKUP(Q78,'Company Code'!$A$1:$B$7,2,FALSE) -> Mbogo Mining and General Supply Limited | U78: Transaction Cost | V78: 7600 | X78: =IF(V78="", W78, V78) -> 7600 | Y78: =IF(V78<>"","DR","CR") -> DR
A79: 04.01.205 | B79: RV01-04012025 | D79: CRDB BANK PLC | E79: 56150600 | F79: =VLOOKUP(E79,'Improved Accounting codes'!C112:D2452,2,FALSE) -> CRDB TZS:0150481116500 | G79: 561506 | H79: =VLOOKUP(G79,'Improved Accounting codes'!A132:B2472,2,FALSE) -> CRDB BANK PLC | I79: FAD00102 | J79: =VLOOKUP(I79,'Section Code'!$B$1:$C$17,2,FALSE) -> Finance Section | K79: FAD001 | L79: =VLOOKUP(K79,'Department Codes'!$A$1:$B$4,2,FALSE) -> Finance and Administration Department | M79: MGL00121 | N79: =VLOOKUP(M79,'Location Code Code'!$E$2:$F$22,2,FALSE) -> HEAD OFFICE NYASHISHI MWANZA | O79: MGL0012 | P79: =VLOOKUP(O79,'Business Code'!$C$1:$D$19,2,FALSE) -> TRADING OF COMERCIAL EXPLOSIVES | Q79: MGL001 | R79: =VLOOKUP(Q79,'Company Code'!$A$1:$B$7,2,FALSE) -> Mbogo Mining and General Supply Limited | U79: Transaction Cost | W79: 7600 | X79: =IF(V79="", W79, V79) -> 7600 | Y79: =IF(V79<>"","DR","CR") -> CR
A80: 04.01.205 | B80: RV01-04012025 | D80: TROPICAL TRAVEL SERVICES CO LTD 015C913091100 CRDB | E80: 41840500 | F80: =VLOOKUP(E80,'Improved Accounting codes'!C113:D2453,2,FALSE) -> Tropical Travel Services Co LTD | G80: 418405 | H80: =VLOOKUP(G80,'Improved Accounting codes'!A85:B2425,2,FALSE) -> Accounts Payable - Service Provider | I80: FAD00102 | J80: =VLOOKUP(I80,'Section Code'!$B$1:$C$17,2,FALSE) -> Finance Section | K80: FAD001 | L80: =VLOOKUP(K80,'Department Codes'!$A$1:$B$4,2,FALSE) -> Finance and Administration Department | M80: MGL00121 | N80: =VLOOKUP(M80,'Location Code Code'!$E$2:$F$22,2,FALSE) -> HEAD OFFICE NYASHISHI MWANZA | O80: MGL0012 | P80: =VLOOKUP(O80,'Business Code'!$C$1:$D$19,2,FALSE) -> TRADING OF COMERCIAL EXPLOSIVES | Q80: MGL001 | R80: =VLOOKUP(Q80,'Company Code'!$A$1:$B$7,2,FALSE) -> Mbogo Mining and General Supply Limited | U80: Being payment for Air ticket for MD from Mwanza to Dar es salaam | V80: 667000 | X80: =IF(V80="", W80, V80) -> 667000 | Y80: =IF(V80<>"","DR","CR") -> DR
A81: 04.01.205 | B81: RV01-04012025 | D81: TROPICAL TRAVEL SERVICES CO LTD 015C913091100 CRDB | E81: 57250100 | F81: =VLOOKUP(E81,'Improved Accounting codes'!C114:D2454,2,FALSE) -> Cash for office use Mbogo Mining and General Supply Limited | G81: 572501 | H81: =VLOOKUP(G81,'Improved Accounting codes'!A86:B2426,2,FALSE) -> Cash for Office Use | I81: FAD00102 | J81: =VLOOKUP(I81,'Section Code'!$B$1:$C$17,2,FALSE) -> Finance Section | K81: FAD001 | L81: =VLOOKUP(K81,'Department Codes'!$A$1:$B$4,2,FALSE) -> Finance and Administration Department | M81: MGL00121 | N81: =VLOOKUP(M81,'Location Code Code'!$E$2:$F$22,2,FALSE) -> HEAD OFFICE NYASHISHI MWANZA | O81: MGL0012 | P81: =VLOOKUP(O81,'Business Code'!$C$1:$D$19,2,FALSE) -> TRADING OF COMERCIAL EXPLOSIVES | Q81: MGL001 | R81: =VLOOKUP(Q81,'Company Code'!$A$1:$B$7,2,FALSE) -> Mbogo Mining and General Supply Limited | U81: Being payment for Air ticket for MD from Mwanza to Dar es salaam | W81: 667000 | X81: =IF(V81="", W81, V81) -> 667000 | Y81: =IF(V81<>"","DR","CR") -> CR
A82: 04.01.205 | B82: RV01-04012025 | D82: MBOGO MINING & GENERAL SUPPLY LTD | E82: 62760101 | F82: =VLOOKUP(E82,'Improved Accounting codes'!C115:D2455,2,FALSE) -> Spare parts | G82: 627601 | H82: =VLOOKUP(G82,'Improved Accounting codes'!A87:B2427,2,FALSE) -> Spare parts, Repair,Acetone and Maintenance | I82: FAD00102 | J82: =VLOOKUP(I82,'Section Code'!$B$1:$C$17,2,FALSE) -> Finance Section | K82: FAD001 | L82: =VLOOKUP(K82,'Department Codes'!$A$1:$B$4,2,FALSE) -> Finance and Administration Department | M82: MGL00121 | N82: =VLOOKUP(M82,'Location Code Code'!$E$2:$F$22,2,FALSE) -> HEAD OFFICE NYASHISHI MWANZA | O82: MGL0012 | P82: =VLOOKUP(O82,'Business Code'!$C$1:$D$19,2,FALSE) -> TRADING OF COMERCIAL EXPLOSIVES | Q82: MGL001 | R82: =VLOOKUP(Q82,'Company Code'!$A$1:$B$7,2,FALSE) -> Mbogo Mining and General Supply Limited | U82: Being payment for spare parts T-926DMT | V82: 800000 | X82: =IF(V82="", W82, V82) -> 800000 | Y82: =IF(V82<>"","DR","CR") -> DR
A83: 04.01.205 | B83: RV01-04012025 | D83: MBOGO MINING & GENERAL SUPPLY LTD | E83: 56150600 | F83: =VLOOKUP(E83,'Improved Accounting codes'!C116:D2456,2,FALSE) -> CRDB TZS:0150481116500 | G83: 561506 | H83: =VLOOKUP(G83,'Improved Accounting codes'!A136:B2476,2,FALSE) -> CRDB BANK PLC | I83: FAD00102 | J83: =VLOOKUP(I83,'Section Code'!$B$1:$C$17,2,FALSE) -> Finance Section | K83: FAD001 | L83: =VLOOKUP(K83,'Department Codes'!$A$1:$B$4,2,FALSE) -> Finance and Administration Department | M83: MGL00121 | N83: =VLOOKUP(M83,'Location Code Code'!$E$2:$F$22,2,FALSE) -> HEAD OFFICE NYASHISHI MWANZA | O83: MGL0012 | P83: =VLOOKUP(O83,'Business Code'!$C$1:$D$19,2,FALSE) -> TRADING OF COMERCIAL EXPLOSIVES | Q83: MGL001 | R83: =VLOOKUP(Q83,'Company Code'!$A$1:$B$7,2,FALSE) -> Mbogo Mining and General Supply Limited | U83: Being payment for spare parts T-926DMT | W83: 800000 | X83: =IF(V83="", W83, V83) -> 800000 | Y83: =IF(V83<>"","DR","CR") -> CR
A84: 04.01.205 | B84: RV01-04012025 | D84: ZAWADI MWASONGWE 43010002631 NMB | E84: 64160100 | F84: =VLOOKUP(E84,'Improved Accounting codes'!C117:D2457,2,FALSE) -> Royalties for concessions, patents, licenses, trademarks, processes, software, rights and | G84: 641601 | H84: =VLOOKUP(G84,'Improved Accounting codes'!A137:B2477,2,FALSE) -> Royalties for concessions, patents, licenses, trademarks, processes, software, rights and | I84: FAD00102 | J84: =VLOOKUP(I84,'Section Code'!$B$1:$C$17,2,FALSE) -> Finance Section | K84: FAD001 | L84: =VLOOKUP(K84,'Department Codes'!$A$1:$B$4,2,FALSE) -> Finance and Administration Department | M84: MGL00121 | N84: =VLOOKUP(M84,'Location Code Code'!$E$2:$F$22,2,FALSE) -> HEAD OFFICE NYASHISHI MWANZA | O84: MGL0012 | P84: =VLOOKUP(O84,'Business Code'!$C$1:$D$19,2,FALSE) -> TRADING OF COMERCIAL EXPLOSIVES | Q84: MGL001 | R84: =VLOOKUP(Q84,'Company Code'!$A$1:$B$7,2,FALSE) -> Mbogo Mining and General Supply Limited | U84: License to purchase Explosives | V84: 150000 | X84: =IF(V84="", W84, V84) -> 150000 | Y84: =IF(V84<>"","DR","CR") -> DR
A85: 04.01.205 | B85: RV01-04012025 | D85: ZAWADI MWASONGWE 43010002631 NMB | E85: 56150600 | F85: =VLOOKUP(E85,'Improved Accounting codes'!C118:D2458,2,FALSE) -> CRDB TZS:0150481116500 | G85: 561506 | H85: CRDB BANK PLC | I85: FAD00102 | J85: =VLOOKUP(I85,'Section Code'!$B$1:$C$17,2,FALSE) -> Finance Section | K85: FAD001 | L85: =VLOOKUP(K85,'Department Codes'!$A$1:$B$4,2,FALSE) -> Finance and Administration Department | M85: MGL00121 | N85: =VLOOKUP(M85,'Location Code Code'!$E$2:$F$22,2,FALSE) -> HEAD OFFICE NYASHISHI MWANZA | O85: MGL0012 | P85: =VLOOKUP(O85,'Business Code'!$C$1:$D$19,2,FALSE) -> TRADING OF COMERCIAL EXPLOSIVES | Q85: MGL001 | R85: =VLOOKUP(Q85,'Company Code'!$A$1:$B$7,2,FALSE) -> Mbogo Mining and General Supply Limited | U85: License to purchase Explosives | W85: 150000 | X85: =IF(V85="", W85, V85) -> 150000 | Y85: =IF(V85<>"","DR","CR") -> CR
A86: 04.01.205 | B86: RV01-04012025 | D86: CRDB BANK PLC | E86: 63860710 | F86: =VLOOKUP(E86,'Improved Accounting codes'!C119:D2459,2,FALSE) -> CRDB TZS:0150481116500 | G86: 638607 | H86: =VLOOKUP(G86,'Improved Accounting codes'!A139:B2479,2,FALSE) -> Bank Charges | I86: FAD00102 | J86: =VLOOKUP(I86,'Section Code'!$B$1:$C$17,2,FALSE) -> Finance Section | K86: FAD001 | L86: =VLOOKUP(K86,'Department Codes'!$A$1:$B$4,2,FALSE) -> Finance and Administration Department | M86: MGL00121 | N86: =VLOOKUP(M86,'Location Code Code'!$E$2:$F$22,2,FALSE) -> HEAD OFFICE NYASHISHI MWANZA | O86: MGL0012 | P86: =VLOOKUP(O86,'Business Code'!$C$1:$D$19,2,FALSE) -> TRADING OF COMERCIAL EXPLOSIVES | Q86: MGL001 | R86: =VLOOKUP(Q86,'Company Code'!$A$1:$B$7,2,FALSE) -> Mbogo Mining and General Supply Limited | U86: Transaction Cost | V86: 5600 | X86: =IF(V86="", W86, V86) -> 5600 | Y86: =IF(V86<>"","DR","CR") -> DR
A87: 04.01.205 | B87: RV01-04012025 | D87: CRDB BANK PLC | E87: 56150600 | F87: =VLOOKUP(E87,'Improved Accounting codes'!C120:D2460,2,FALSE) -> CRDB TZS:0150481116500 | G87: 561506 | H87: =VLOOKUP(G87,'Improved Accounting codes'!A140:B2480,2,FALSE) -> CRDB BANK PLC | I87: FAD00102 | J87: =VLOOKUP(I87,'Section Code'!$B$1:$C$17,2,FALSE) -> Finance Section | K87: FAD001 | L87: =VLOOKUP(K87,'Department Codes'!$A$1:$B$4,2,FALSE) -> Finance and Administration Department | M87: MGL00121 | N87: =VLOOKUP(M87,'Location Code Code'!$E$2:$F$22,2,FALSE) -> HEAD OFFICE NYASHISHI MWANZA | O87: MGL0012 | P87: =VLOOKUP(O87,'Business Code'!$C$1:$D$19,2,FALSE) -> TRADING OF COMERCIAL EXPLOSIVES | Q87: MGL001 | R87: =VLOOKUP(Q87,'Company Code'!$A$1:$B$7,2,FALSE) -> Mbogo Mining and General Supply Limited | U87: Transaction Cost | W87: 5600 | X87: =IF(V87="", W87, V87) -> 5600 | Y87: =IF(V87<>"","DR","CR") -> CR
A88: 05.01.205 | B88: RV01-05012025 | D88: FINANCIAL HUB NMB 32910019873 | E88: 60160200 | F88: =VLOOKUP(E88,'Improved Accounting codes'!C121:D2461,2,FALSE) -> Service Cost: Fuel | G88: 601602 | H88: =VLOOKUP(G88,'Improved Accounting codes'!A141:B2481,2,FALSE) -> Cost of Services | I88: BDD00103 | J88: =VLOOKUP(I88,'Section Code'!$B$1:$C$17,2,FALSE) -> Logistic and freight Management Section | K88: BDD001 | L88: =VLOOKUP(K88,'Department Codes'!$A$1:$B$4,2,FALSE) -> Business Development Department | M88: MGL00121 | N88: =VLOOKUP(M88,'Location Code Code'!$E$2:$F$22,2,FALSE) -> HEAD OFFICE NYASHISHI MWANZA | O88: MGL0012 | P88: =VLOOKUP(O88,'Business Code'!$C$1:$D$19,2,FALSE) -> TRADING OF COMERCIAL EXPLOSIVES | Q88: MGL001 | R88: =VLOOKUP(Q88,'Company Code'!$A$1:$B$7,2,FALSE) -> Mbogo Mining and General Supply Limited | U88: Being payment for fuel to 221 DGL from songea to Mwanza | V88: 841289 | X88: =IF(V88="", W88, V88) -> 841289 | Y88: =IF(V88<>"","DR","CR") -> DR
A89: 05.01.205 | B89: RV01-05012025 | D89: FINANCIAL HUB NMB 32910019873 | E89: 56150600 | F89: =VLOOKUP(E89,'Improved Accounting codes'!C122:D2462,2,FALSE) -> CRDB TZS:0150481116500 | G89: 561506 | H89: =VLOOKUP(G89,'Improved Accounting codes'!A142:B2482,2,FALSE) -> CRDB BANK PLC | I89: BDD00103 | J89: =VLOOKUP(I89,'Section Code'!$B$1:$C$17,2,FALSE) -> Logistic and freight Management Section | K89: BDD001 | L89: =VLOOKUP(K89,'Department Codes'!$A$1:$B$4,2,FALSE) -> Business Development Department | M89: MGL00121 | N89: =VLOOKUP(M89,'Location Code Code'!$E$2:$F$22,2,FALSE) -> HEAD OFFICE NYASHISHI MWANZA | O89: MGL0012 | P89: =VLOOKUP(O89,'Business Code'!$C$1:$D$19,2,FALSE) -> TRADING OF COMERCIAL EXPLOSIVES | Q89: MGL001 | R89: =VLOOKUP(Q89,'Company Code'!$A$1:$B$7,2,FALSE) -> Mbogo Mining and General Supply Limited | U89: Being payment for fuel to 221 DGL from songea to Mwanza | W89: 841289 | X89: =IF(V89="", W89, V89) -> 841289 | Y89: =IF(V89<>"","DR","CR") -> CR
A90: 05.01.205 | B90: RV01-05012025 | D90: FINANCIAL HUB NMB 32910019873 | E90: 60160200 | F90: =VLOOKUP(E90,'Improved Accounting codes'!C123:D2463,2,FALSE) -> Service Cost: Fuel | G90: 601602 | H90: =VLOOKUP(G90,'Improved Accounting codes'!A143:B2483,2,FALSE) -> Cost of Services | I90: BDD00103 | J90: =VLOOKUP(I90,'Section Code'!$B$1:$C$17,2,FALSE) -> Logistic and freight Management Section | K90: BDD001 | L90: =VLOOKUP(K90,'Department Codes'!$A$1:$B$4,2,FALSE) -> Business Development Department | M90: MGL00121 | N90: =VLOOKUP(M90,'Location Code Code'!$E$2:$F$22,2,FALSE) -> HEAD OFFICE NYASHISHI MWANZA | O90: MGL0012 | P90: =VLOOKUP(O90,'Business Code'!$C$1:$D$19,2,FALSE) -> TRADING OF COMERCIAL EXPLOSIVES | Q90: MGL001 | R90: =VLOOKUP(Q90,'Company Code'!$A$1:$B$7,2,FALSE) -> Mbogo Mining and General Supply Limited | U90: Being payment for fuel from Songea to Mwanza | V90: 1390500 | X90: =IF(V90="", W90, V90) -> 1390500 | Y90: =IF(V90<>"","DR","CR") -> DR
A91: 05.01.205 | B91: RV01-05012025 | D91: FINANCIAL HUB NMB 32910019873 | E91: 56150600 | F91: =VLOOKUP(E91,'Improved Accounting codes'!C124:D2464,2,FALSE) -> CRDB TZS:0150481116500 | G91: 561506 | H91: =VLOOKUP(G91,'Improved Accounting codes'!A144:B2484,2,FALSE) -> CRDB BANK PLC | I91: BDD00103 | J91: =VLOOKUP(I91,'Section Code'!$B$1:$C$17,2,FALSE) -> Logistic and freight Management Section | K91: BDD001 | L91: =VLOOKUP(K91,'Department Codes'!$A$1:$B$4,2,FALSE) -> Business Development Department | M91: MGL00121 | N91: =VLOOKUP(M91,'Location Code Code'!$E$2:$F$22,2,FALSE) -> HEAD OFFICE NYASHISHI MWANZA | O91: MGL0012 | P91: =VLOOKUP(O91,'Business Code'!$C$1:$D$19,2,FALSE) -> TRADING OF COMERCIAL EXPLOSIVES | Q91: MGL001 | R91: =VLOOKUP(Q91,'Company Code'!$A$1:$B$7,2,FALSE) -> Mbogo Mining and General Supply Limited | U91: Being payment for fuel from Songea to Mwanza | W91: 1390500 | X91: =IF(V91="", W91, V91) -> 1390500 | Y91: =IF(V91<>"","DR","CR") -> CR
A92: 06.01.2025 | B92: RV01-06012025 | D92: BAZACK LAZARO CRDB 01J-209133000 | E92: 40240100 | F92: =VLOOKUP(E92,'Improved Accounting codes'!C125:D2465,2,FALSE) -> Fixed Asset Suppliers | G92: 402401 | H92: =VLOOKUP(G92,'Improved Accounting codes'!A145:B2485,2,FALSE) -> Fixed Asset Suppliers | I92: BDD00102 | J92: =VLOOKUP(I92,'Section Code'!$B$1:$C$17,2,FALSE) -> Sales and Marketing Section | K92: BDD001 | L92: =VLOOKUP(K92,'Department Codes'!$A$1:$B$4,2,FALSE) -> Business Development Department | M92: MGL00121 | N92: =VLOOKUP(M92,'Location Code Code'!$E$2:$F$22,2,FALSE) -> HEAD OFFICE NYASHISHI MWANZA | O92: MGL0012 | P92: =VLOOKUP(O92,'Business Code'!$C$1:$D$19,2,FALSE) -> TRADING OF COMERCIAL EXPLOSIVES | Q92: MGL001 | R92: =VLOOKUP(Q92,'Company Code'!$A$1:$B$7,2,FALSE) -> Mbogo Mining and General Supply Limited | U92: Being payment for purchase of self starter | V92: 200000 | X92: =IF(V92="", W92, V92) -> 200000 | Y92: =IF(V92<>"","DR","CR") -> DR
A93: 06.01.2025 | B93: RV01-06012025 | D93: BAZACK LAZARO CRDB 01J-209133000 | E93: 57250100 | F93: =VLOOKUP(E93,'Improved Accounting codes'!C126:D2466,2,FALSE) -> Cash for office use Mbogo Mining and General Supply Limited | G93: 572501 | H93: =VLOOKUP(G93,'Improved Accounting codes'!A146:B2486,2,FALSE) -> Cash for Office Use | I93: BDD00102 | J93: =VLOOKUP(I93,'Section Code'!$B$1:$C$17,2,FALSE) -> Sales and Marketing Section | K93: BDD001 | L93: =VLOOKUP(K93,'Department Codes'!$A$1:$B$4,2,FALSE) -> Business Development Department | M93: MGL00121 | N93: =VLOOKUP(M93,'Location Code Code'!$E$2:$F$22,2,FALSE) -> HEAD OFFICE NYASHISHI MWANZA | O93: MGL0012 | P93: =VLOOKUP(O93,'Business Code'!$C$1:$D$19,2,FALSE) -> TRADING OF COMERCIAL EXPLOSIVES | Q93: MGL001 | R93: =VLOOKUP(Q93,'Company Code'!$A$1:$B$7,2,FALSE) -> Mbogo Mining and General Supply Limited | U93: Being payment for purchase of self starter | W93: 200000 | X93: =IF(V93="", W93, V93) -> 200000 | Y93: =IF(V93<>"","DR","CR") -> CR
A94: 06.01.2025 | B94: RV01-06012025 | D94: YUSTER EDWARD NYIRENDA MPESA 0742077031 | E94: 62360104 | F94: =VLOOKUP(E94,'Improved Accounting codes'!C127:D2467,2,FALSE) -> Accomodation, Transport and meals expense | G94: 623601 | H94: =VLOOKUP(G94,'Improved Accounting codes'!A99:B2439,2,FALSE) -> Staff transport | I94: BDD00102 | J94: =VLOOKUP(I94,'Section Code'!$B$1:$C$17,2,FALSE) -> Sales and Marketing Section | K94: BDD001 | L94: =VLOOKUP(K94,'Department Codes'!$A$1:$B$4,2,FALSE) -> Business Development Department | M94: MGL00121 | N94: =VLOOKUP(M94,'Location Code Code'!$E$2:$F$22,2,FALSE) -> HEAD OFFICE NYASHISHI MWANZA | O94: MGL0012 | P94: =VLOOKUP(O94,'Business Code'!$C$1:$D$19,2,FALSE) -> TRADING OF COMERCIAL EXPLOSIVES | Q94: MGL001 | R94: =VLOOKUP(Q94,'Company Code'!$A$1:$B$7,2,FALSE) -> Mbogo Mining and General Supply Limited | U94: Being payment for MD fish | V94: 361000 | X94: =IF(V94="", W94, V94) -> 361000 | Y94: =IF(V94<>"","DR","CR") -> DR
A95: 06.01.2025 | B95: RV01-06012025 | D95: YUSTER EDWARD NYIRENDA MPESA 0742077031 | E95: 57250100 | F95: =VLOOKUP(E95,'Improved Accounting codes'!C128:D2468,2,FALSE) -> Cash for office use Mbogo Mining and General Supply Limited | G95: 572501 | H95: =VLOOKUP(G95,'Improved Accounting codes'!A100:B2440,2,FALSE) -> Cash for Office Use | I95: BDD00102 | J95: =VLOOKUP(I95,'Section Code'!$B$1:$C$17,2,FALSE) -> Sales and Marketing Section | K95: BDD001 | L95: =VLOOKUP(K95,'Department Codes'!$A$1:$B$4,2,FALSE) -> Business Development Department | M95: MGL00121 | N95: =VLOOKUP(M95,'Location Code Code'!$E$2:$F$22,2,FALSE) -> HEAD OFFICE NYASHISHI MWANZA | O95: MGL0012 | P95: =VLOOKUP(O95,'Business Code'!$C$1:$D$19,2,FALSE) -> TRADING OF COMERCIAL EXPLOSIVES | Q95: MGL001 | R95: =VLOOKUP(Q95,'Company Code'!$A$1:$B$7,2,FALSE) -> Mbogo Mining and General Supply Limited | U95: Being payment for MD fish | W95: 361000 | X95: =IF(V95="", W95, V95) -> 361000 | Y95: =IF(V95<>"","DR","CR") -> CR
A96: 06.01.2025 | B96: RV01-06012025 | D96: MBOGO MINING NMB 32910019873 | P96: =VLOOKUP(O96,'Business Code'!$C$1:$D$19,2,FALSE) -> #N/A | R96: =VLOOKUP(Q96,'Company Code'!$A$1:$B$7,2,FALSE) -> #N/A | U96: Being payment for purcharse of speare parts | V96: 86000 | X96: =IF(V96="", W96, V96) -> 86000 | Y96: =IF(V96<>"","DR","CR") -> DR
A97: 06.01.2025 | B97: RV01-06012025 | D97: MBOGO MINING NMB 32910019873 | R97: =VLOOKUP(Q97,'Company Code'!$A$1:$B$7,2,FALSE) -> #N/A | U97: Being payment for purcharse of speare parts | W97: 86000 | X97: =IF(V97="", W97, V97) -> 86000 | Y97: =IF(V97<>"","DR","CR") -> CR
A98: 06.01.2025 | B98: RV01-06012025 | R98: =VLOOKUP(Q98,'Company Code'!$A$1:$B$7,2,FALSE) -> #N/A | X98: =IF(V98="", W98, V98) -> 0 | Y98: =IF(V98<>"","DR","CR") -> CR
A99: 06.01.2025 | B99: RV01-06012025 | R99: =VLOOKUP(Q99,'Company Code'!$A$1:$B$7,2,FALSE) -> #N/A | X99: =IF(V99="", W99, V99) -> 0 | Y99: =IF(V99<>"","DR","CR") -> CR
A100: 06.01.2025 | B100: RV01-06012025 | X100: =IF(V100="", W100, V100) -> 0 | Y100: =IF(V100<>"","DR","CR") -> CR
A101: 06.01.2025 | B101: RV01-06012025 | X101: =IF(V101="", W101, V101) -> 0 | Y101: =IF(V101<>"","DR","CR") -> CR
A102: 06.01.2025 | B102: RV01-06012025 | X102: =IF(V102="", W102, V102) -> 0 | Y102: =IF(V102<>"","DR","CR") -> CR
A103: 06.01.2025 | B103: RV01-06012025 | X103: =IF(V103="", W103, V103) -> 0 | Y103: =IF(V103<>"","DR","CR") -> CR
...

Sheet JV TO UPLOAD
A1: Posting Date | B1: P.V.NO. | C1: CHQ N0. | D1: PAYEE | E1: Sub Account Code | F1: Section Code | G1: Location code | H1: Busines Code | I1: Currency | J1: EXCHANGE RATE | K1: Details | L1: Amount | M1: condtion | N1: AMOUNT
A2: 45659 | B2: N/A | C2: N/A | D2: CRDB BANK PLC | E2: 56150700 | F2: FAD00102 | G2: MGL00121 | H2: MGL0012 | I2: TZS | J2: 1 | K2: REF:19426ee2ed61dab3 AGENCY FT AB17358199306989206479:Flavian:K N/A | L2: 3000000 | M2: DR | N2: =J2*L2 -> 3000000
A3: 45659 | B3: N/A | C3: N/A | D3: CRDB BANK PLC | E3: 56150600 | F3: FAD00102 | G3: MGL00121 | H3: MGL0012 | I3: TZS | J3: 1 | K3: REF:19426ee2ed61dab3 AGENCY FT AB17358199306989206479:Flavian:K N/A | L3: 3000000 | M3: CR | N3: =J3*L3 -> 3000000
A4: 45659 | B4: RV01-02012025 | C4: N/A | D4: NEEMA RAPHAEL 0744979075 M -PESA | E4: 60160204 | F4: BDD00102 | G4: MGL00121 | H4: MGL0012 | I4: USD | J4: 2560.67 | K4: .Being payment for Casual labour 3 people@8000/= for six days | L4: 140 | M4: DR | N4: =J4*L4 -> 358493.8
A5: 45659 | B5: RV01-02012025 | C5: N/A | D5: NEEMA RAPHAEL 0744979075 M -PESA | E5: 57250100 | F5: BDD00102 | G5: MGL00121 | H5: MGL0012 | I5: USD | J5: 2560.67 | K5: .Being payment for Casual labour 3 people@8000/= for six days | L5: 140 | M5: CR | N5: =J5*L5 -> 358493.8

Sheet Sheet4
A1: 19/12/2024 | D1: BARNABAS ATHANAS NIBENGO | E1: ='Improved Accounting codes'!C1746 -> 67560103 | F1: =VLOOKUP(E1,'Improved Accounting codes'!C5:D2345,2,FALSE) -> Barnabas Athanas Nibengo | G1: ='Improved Accounting codes'!A1743 -> 675601 | H1: =VLOOKUP(G1,'Improved Accounting codes'!A5:B2345,2,FALSE) -> Uncategorised Expenses | I1: FAD00102 | J1: =VLOOKUP(I1,'Section Code'!B1:C17,2,FALSE) -> Finance Section | K1: FAD001 | L1: =VLOOKUP(K1,'Department Codes'!A1:B4,2,FALSE) -> Finance and Administration Department | M1: MGL00121 | N1: =VLOOKUP(M1,'Location Code Code'!E1:F22,2,FALSE) -> HEAD OFFICE NYASHISHI MWANZA | O1: MGL0011 | P1: =VLOOKUP(O1,'Business Code'!C1:D21,2,FALSE) -> MANUFACTUREING OF COMMERCIAL EXPLOSIVES | Q1: MGL001 | R1: =VLOOKUP(Q1,'Company Code'!A1:B7,2,FALSE) -> Mbogo Mining and General Supply Limited | U1: REF:193de55d43cf794d IB FT TO MPESA 0757851332 BARNABAS ATHANAS NIBENGO | V1: 650000
A2: 19/12/2024 | D2: BARNABAS ATHANAS NIBENGO | E2: 56150600 | F2: =VLOOKUP(E2,'Improved Accounting codes'!C6:D2346,2,FALSE) -> CRDB TZS:0150481116500 | G2: 561506 | H2: =VLOOKUP(G2,'Improved Accounting codes'!A6:B2346,2,FALSE) -> CRDB BANK PLC | I2: FAD00102 | J2: =VLOOKUP(I2,'Section Code'!B2:C18,2,FALSE) -> Finance Section | K2: FAD001 | L2: =VLOOKUP(K2,'Department Codes'!A2:B5,2,FALSE) -> Finance and Administration Department | M2: MGL00121 | N2: =VLOOKUP(M2,'Location Code Code'!E2:F23,2,FALSE) -> HEAD OFFICE NYASHISHI MWANZA | O2: MGL0011 | P2: =VLOOKUP(O2,'Business Code'!C2:D22,2,FALSE) -> MANUFACTUREING OF COMMERCIAL EXPLOSIVES | Q2: MGL001 | R2: =VLOOKUP(Q2,'Company Code'!A1:B7,2,FALSE) -> Mbogo Mining and General Supply Limited | U2: REF:193de55d43cf794d IB FT TO MPESA 0757851332 BARNABAS ATHANAS NIBENGO | W2: 650000
A3: 19.12.2024 | D3: CRDB BANK PLC | E3: 63860720 | F3: =VLOOKUP(E3,'Improved Accounting codes'!C7:D2347,2,FALSE) -> #N/A | G3: 638607 | H3: =VLOOKUP(G3,'Improved Accounting codes'!A7:B2347,2,FALSE) -> Bank Charges | I3: FAD00102 | J3: =VLOOKUP(I3,'Section Code'!B3:C19,2,FALSE) -> Finance Section | K3: FAD001 | L3: =VLOOKUP(K3,'Department Codes'!A2:B5,2,FALSE) -> Finance and Administration Department | M3: MGL00121 | N3: =VLOOKUP(M3,'Location Code Code'!E3:F24,2,FALSE) -> HEAD OFFICE NYASHISHI MWANZA | O3: MGL0011 | P3: =VLOOKUP(O3,'Business Code'!C2:D22,2,FALSE) -> MANUFACTUREING OF COMMERCIAL EXPLOSIVES | Q3: MGL001 | R3: =VLOOKUP(Q3,'Company Code'!A2:B8,2,FALSE) -> Mbogo Mining and General Supply Limited | U3: REF:193de55d43cf794d CHARGE: TRANSFER TO MPESA VIA IB | V3: 9067.8
A4: 19.12.2024 | D4: CRDB BANK PLC | E4: 56150600 | F4: =VLOOKUP(E4,'Improved Accounting codes'!C8:D2348,2,FALSE) -> CRDB TZS:0150481116500 | G4: 561506 | H4: =VLOOKUP(G4,'Improved Accounting codes'!A8:B2348,2,FALSE) -> CRDB BANK PLC | I4: FAD00102 | J4: =VLOOKUP(I4,'Section Code'!B3:C19,2,FALSE) -> Finance Section | K4: FAD001 | L4: =VLOOKUP(K4,'Department Codes'!A2:B5,2,FALSE) -> Finance and Administration Department | M4: MGL00121 | N4: =VLOOKUP(M4,'Location Code Code'!E3:F24,2,FALSE) -> HEAD OFFICE NYASHISHI MWANZA | O4: MGL0011 | P4: =VLOOKUP(O4,'Business Code'!C2:D22,2,FALSE) -> MANUFACTUREING OF COMMERCIAL EXPLOSIVES | Q4: MGL001 | R4: =VLOOKUP(Q4,'Company Code'!A2:B8,2,FALSE) -> Mbogo Mining and General Supply Limited | U4: REF:193de55d43cf794d CHARGE: TRANSFER TO MPESA VIA IB | W4: 9067.8
A5: 19.12.2024 | D5: CRDB BANK PLC | E5: 25520102 | F5: =VLOOKUP(E5,'Improved Accounting codes'!C9:D2349,2,FALSE) -> Loans to subsidiaries | G5: 255201 | H5: =VLOOKUP(G5,'Improved Accounting codes'!A9:B2349,2,FALSE) -> Recievables on loans | I5: FAD00102 | J5: =VLOOKUP(I5,'Section Code'!B3:C19,2,FALSE) -> Finance Section | K5: FAD001 | L5: =VLOOKUP(K5,'Department Codes'!A2:B5,2,FALSE) -> Finance and Administration Department | M5: MGL00121 | N5: =VLOOKUP(M5,'Location Code Code'!E3:F24,2,FALSE) -> HEAD OFFICE NYASHISHI MWANZA | O5: MGL0011 | P5: =VLOOKUP(O5,'Business Code'!C2:D22,2,FALSE) -> MANUFACTUREING OF COMMERCIAL EXPLOSIVES | Q5: MGL001 | R5: =VLOOKUP(Q5,'Company Code'!A2:B8,2,FALSE) -> Mbogo Mining and General Supply Limited | U5: VAT (18%) PAYABLE ON COMMISSION AND FEES : FULL | V5: 1632.2
A6: 19.12.2024 | D6: CRDB BANK PLC | E6: 56150600 | F6: =VLOOKUP(E6,'Improved Accounting codes'!C10:D2350,2,FALSE) -> CRDB TZS:0150481116500 | G6: 561506 | H6: =VLOOKUP(G6,'Improved Accounting codes'!A10:B2350,2,FALSE) -> CRDB BANK PLC | I6: FAD00102 | J6: =VLOOKUP(I6,'Section Code'!B3:C19,2,FALSE) -> Finance Section | K6: FAD001 | L6: =VLOOKUP(K6,'Department Codes'!A2:B5,2,FALSE) -> Finance and Administration Department | M6: MGL00121 | N6: =VLOOKUP(M6,'Location Code Code'!E3:F24,2,FALSE) -> HEAD OFFICE NYASHISHI MWANZA | O6: MGL0011 | P6: =VLOOKUP(O6,'Business Code'!C2:D22,2,FALSE) -> MANUFACTUREING OF COMMERCIAL EXPLOSIVES | Q6: MGL001 | R6: =VLOOKUP(Q6,'Company Code'!A2:B8,2,FALSE) -> Mbogo Mining and General Supply Limited | U6: VAT (18%) PAYABLE ON COMMISSION AND FEES : FULL | W6: 1632.2
A7: 19.12.2024 | D7: EPIFANIA FRANK ODANCE | E7: 57250100 | F7: =VLOOKUP(E7,'Improved Accounting codes'!C11:D2351,2,FALSE) -> Cash for office use Mbogo Mining and General Supply Limited | G7: 572501 | H7: =VLOOKUP(G7,'Improved Accounting codes'!A11:B2351,2,FALSE) -> Cash for Office Use | I7: FAD00102 | J7: =VLOOKUP(I7,'Section Code'!B3:C19,2,FALSE) -> Finance Section | K7: FAD001 | L7: =VLOOKUP(K7,'Department Codes'!A2:B5,2,FALSE) -> Finance and Administration Department | M7: MGL00121 | N7: =VLOOKUP(M7,'Location Code Code'!E3:F24,2,FALSE) -> HEAD OFFICE NYASHISHI MWANZA | O7: MGL0011 | P7: =VLOOKUP(O7,'Business Code'!C2:D22,2,FALSE) -> MANUFACTUREING OF COMMERCIAL EXPLOSIVES | Q7: MGL001 | R7: =VLOOKUP(Q7,'Company Code'!A2:B8,2,FALSE) -> Mbogo Mining and General Supply Limited | U7: REF:193decad7dcb2826 IB FT TO MPESA 0765427622 EPIFANIA FRANK ODANCE | V7: 200000
A8: 19.12.2024 | D8: EPIFANIA FRANK ODANCE | E8: 56150600 | F8: =VLOOKUP(E8,'Improved Accounting codes'!C12:D2352,2,FALSE) -> CRDB TZS:0150481116500 | G8: 561506 | H8: =VLOOKUP(G8,'Improved Accounting codes'!A12:B2352,2,FALSE) -> CRDB BANK PLC | I8: FAD00102 | J8: =VLOOKUP(I8,'Section Code'!B3:C19,2,FALSE) -> Finance Section | K8: FAD001 | L8: =VLOOKUP(K8,'Department Codes'!A2:B5,2,FALSE) -> Finance and Administration Department | M8: MGL00121 | N8: =VLOOKUP(M8,'Location Code Code'!E3:F24,2,FALSE) -> HEAD OFFICE NYASHISHI MWANZA | O8: MGL0011 | P8: =VLOOKUP(O8,'Business Code'!C2:D22,2,FALSE) -> MANUFACTUREING OF COMMERCIAL EXPLOSIVES | Q8: MGL001 | R8: =VLOOKUP(Q8,'Company Code'!A2:B8,2,FALSE) -> Mbogo Mining and General Supply Limited | U8: REF:193decad7dcb2826 IB FT TO MPESA 0765427622 EPIFANIA FRANK ODANCE | W8: 200000
A9: 19.12.2024 | D9: CRDB BANK PLC | E9: 63860720 | F9: =VLOOKUP(E9,'Improved Accounting codes'!C13:D2353,2,FALSE) -> #N/A | G9: 638607 | H9: =VLOOKUP(G9,'Improved Accounting codes'!A13:B2353,2,FALSE) -> Bank Charges | I9: FAD00102 | J9: =VLOOKUP(I9,'Section Code'!B3:C19,2,FALSE) -> Finance Section | K9: FAD001 | L9: =VLOOKUP(K9,'Department Codes'!A2:B5,2,FALSE) -> Finance and Administration Department | M9: MGL00121 | N9: =VLOOKUP(M9,'Location Code Code'!E3:F24,2,FALSE) -> HEAD OFFICE NYASHISHI MWANZA | O9: MGL0011 | P9: =VLOOKUP(O9,'Business Code'!C2:D22,2,FALSE) -> MANUFACTUREING OF COMMERCIAL EXPLOSIVES | Q9: MGL001 | R9: =VLOOKUP(Q9,'Company Code'!A2:B8,2,FALSE) -> Mbogo Mining and General Supply Limited | U9: REF:193decad7dcb2826 CHARGE: TRANSFER TO MPESA VIA IB | V9: 6525.42
A10: 19.12.2024 | D10: CRDB BANK PLC | E10: 56150600 | F10: =VLOOKUP(E10,'Improved Accounting codes'!C14:D2354,2,FALSE) -> CRDB TZS:0150481116500 | G10: 561506 | H10: =VLOOKUP(G10,'Improved Accounting codes'!A14:B2354,2,FALSE) -> CRDB BANK PLC | I10: FAD00102 | J10: =VLOOKUP(I10,'Section Code'!B3:C19,2,FALSE) -> Finance Section | K10: FAD001 | L10: =VLOOKUP(K10,'Department Codes'!A2:B5,2,FALSE) -> Finance and Administration Department | M10: MGL00121 | N10: =VLOOKUP(M10,'Location Code Code'!E3:F24,2,FALSE) -> HEAD OFFICE NYASHISHI MWANZA | O10: MGL0011 | P10: =VLOOKUP(O10,'Business Code'!C2:D22,2,FALSE) -> MANUFACTUREING OF COMMERCIAL EXPLOSIVES | Q10: MGL001 | R10: =VLOOKUP(Q10,'Company Code'!A2:B8,2,FALSE) -> Mbogo Mining and General Supply Limited | U10: REF:193decad7dcb2826 CHARGE: TRANSFER TO MPESA VIA IB | W10: 6525.42
A11: 19.12.2024 | D11: CRDB BANK PLC | E11: 25520102 | F11: =VLOOKUP(E11,'Improved Accounting codes'!C15:D2355,2,FALSE) -> Loans to subsidiaries | G11: 255201 | H11: =VLOOKUP(G11,'Improved Accounting codes'!A15:B2355,2,FALSE) -> Recievables on loans | I11: FAD00102 | J11: =VLOOKUP(I11,'Section Code'!B3:C19,2,FALSE) -> Finance Section | K11: FAD001 | L11: =VLOOKUP(K11,'Department Codes'!A2:B5,2,FALSE) -> Finance and Administration Department | M11: MGL00121 | N11: =VLOOKUP(M11,'Location Code Code'!E3:F24,2,FALSE) -> HEAD OFFICE NYASHISHI MWANZA | O11: MGL0011 | P11: =VLOOKUP(O11,'Business Code'!C2:D22,2,FALSE) -> MANUFACTUREING OF COMMERCIAL EXPLOSIVES | Q11: MGL001 | R11: =VLOOKUP(Q11,'Company Code'!A2:B8,2,FALSE) -> Mbogo Mining and General Supply Limited | U11: VAT (18%) PAYABLE ON COMMISSION AND FEES : FULL | V11: 1174.58
D12: CRDB BANK PLC | E12: 56150600 | F12: =VLOOKUP(E12,'Improved Accounting codes'!C16:D2356,2,FALSE) -> CRDB TZS:0150481116500 | G12: 561506 | H12: =VLOOKUP(G12,'Improved Accounting codes'!A16:B2356,2,FALSE) -> CRDB BANK PLC | I12: FAD00102 | J12: =VLOOKUP(I12,'Section Code'!B3:C19,2,FALSE) -> Finance Section | K12: FAD001 | L12: =VLOOKUP(K12,'Department Codes'!A2:B5,2,FALSE) -> Finance and Administration Department | M12: MGL00121 | N12: =VLOOKUP(M12,'Location Code Code'!E3:F24,2,FALSE) -> HEAD OFFICE NYASHISHI MWANZA | O12: MGL0011 | P12: =VLOOKUP(O12,'Business Code'!C2:D22,2,FALSE) -> MANUFACTUREING OF COMMERCIAL EXPLOSIVES | Q12: MGL001 | R12: =VLOOKUP(Q12,'Company Code'!A2:B8,2,FALSE) -> Mbogo Mining and General Supply Limited | U12: VAT (18%) PAYABLE ON COMMISSION AND FEES : FULL | W12: 1174.58
A13: 19.12.2024 | D13: JONATHAN KASHIMIR MUSHI | E13: 56150600 | F13: =VLOOKUP(E13,'Improved Accounting codes'!C17:D2357,2,FALSE) -> CRDB TZS:0150481116500 | G13: 561506 | H13: =VLOOKUP(G13,'Improved Accounting codes'!A17:B2357,2,FALSE) -> CRDB BANK PLC | I13: BDD00101 | J13: =VLOOKUP(I13,'Section Code'!B3:C19,2,FALSE) -> General Supply Section | K13: BDD001 | L13: =VLOOKUP(K13,'Department Codes'!A2:B5,2,FALSE) -> Business Development Department | M13: MGL0014 | N13: =VLOOKUP(M13,'Location Code Code'!C1:D22,2,FALSE) -> GENERAL SUPPLY | O13: MGL00141 | P13: =VLOOKUP(O13,'Location Code Code'!E1:F22,2,FALSE) -> HEAD OFFICE NYASHISHI MWANZA | Q13: MGL001 | R13: =VLOOKUP(Q13,'Company Code'!A2:B8,2,FALSE) -> Mbogo Mining and General Supply Limited | U13: JONATHAN KASHIMIR MUSHI CASH DEPOSITS | V13: 15660920
A14: 21.12.2024 | D14: JONATHAN KASHIMIR MUSHI | E14: 67560105 | F14: =VLOOKUP(E14,'Improved Accounting codes'!C7:D2347,2,FALSE) -> Jonathan Kashimir Mushi | G14: 675601 | H14: =VLOOKUP(G14,'Improved Accounting codes'!A7:B2347,2,FALSE) -> Uncategorised Expenses | I14: BDD00101 | J14: =VLOOKUP(I14,'Section Code'!B3:C19,2,FALSE) -> General Supply Section | K14: BDD001 | L14: =VLOOKUP(K14,'Department Codes'!A2:B5,2,FALSE) -> Business Development Department | M14: MGL0014 | N14: =VLOOKUP(M14,'Location Code Code'!C2:D23,2,FALSE) -> GENERAL SUPPLY | O14: MGL00141 | P14: =VLOOKUP(O14,'Location Code Code'!E2:F23,2,FALSE) -> HEAD OFFICE NYASHISHI MWANZA | Q14: MGL001 | R14: =VLOOKUP(Q14,'Company Code'!A2:B8,2,FALSE) -> Mbogo Mining and General Supply Limited | U14: JONATHAN KASHIMIR MUSHI CASH DEPOSITS | W14: 15660920
A15: 21.12.2024 | D15: CRDB BANK PLC | E15: 63860720 | F15: =VLOOKUP(E15,'Improved Accounting codes'!C9:D2349,2,FALSE) -> #N/A | G15: 638607 | H15: =VLOOKUP(G15,'Improved Accounting codes'!A9:B2349,2,FALSE) -> Bank Charges | I15: FAD00102 | J15: =VLOOKUP(I15,'Section Code'!B3:C19,2,FALSE) -> Finance Section | K15: FAD001 | L15: =VLOOKUP(K15,'Department Codes'!A2:B5,2,FALSE) -> Finance and Administration Department | M15: MGL00121 | N15: =VLOOKUP(M15,'Location Code Code'!E3:F24,2,FALSE) -> HEAD OFFICE NYASHISHI MWANZA | O15: MGL0011 | P15: =VLOOKUP(O15,'Business Code'!C2:D22,2,FALSE) -> MANUFACTUREING OF COMMERCIAL EXPLOSIVES | Q15: MGL001 | R15: =VLOOKUP(Q15,'Company Code'!A2:B8,2,FALSE) -> Mbogo Mining and General Supply Limited | U15: Monthly Maintenance Fee | V15: 13000
A16: 21.12.2024 | D16: CRDB BANK PLC | E16: 56150600 | F16: =VLOOKUP(E16,'Improved Accounting codes'!C10:D2350,2,FALSE) -> CRDB TZS:0150481116500 | G16: 561506 | H16: =VLOOKUP(G16,'Improved Accounting codes'!A10:B2350,2,FALSE) -> CRDB BANK PLC | I16: FAD00102 | J16: =VLOOKUP(I16,'Section Code'!B3:C19,2,FALSE) -> Finance Section | K16: FAD001 | L16: =VLOOKUP(K16,'Department Codes'!A2:B5,2,FALSE) -> Finance and Administration Department | M16: MGL00121 | N16: =VLOOKUP(M16,'Location Code Code'!E3:F24,2,FALSE) -> HEAD OFFICE NYASHISHI MWANZA | O16: MGL0011 | P16: =VLOOKUP(O16,'Business Code'!C2:D22,2,FALSE) -> MANUFACTUREING OF COMMERCIAL EXPLOSIVES | Q16: MGL001 | R16: =VLOOKUP(Q16,'Company Code'!A2:B8,2,FALSE) -> Mbogo Mining and General Supply Limited | U16: Monthly Maintenance Fee | W16: 13000
A17: 22.12.2024 | D17: CRDB BANK PLC | E17: 25520102 | F17: =VLOOKUP(E17,'Improved Accounting codes'!C11:D2351,2,FALSE) -> Loans to subsidiaries | G17: 255201 | H17: =VLOOKUP(G17,'Improved Accounting codes'!A11:B2351,2,FALSE) -> Recievables on loans | I17: FAD00102 | J17: =VLOOKUP(I17,'Section Code'!B3:C19,2,FALSE) -> Finance Section | K17: FAD001 | L17: =VLOOKUP(K17,'Department Codes'!A2:B5,2,FALSE) -> Finance and Administration Department | M17: MGL00121 | N17: =VLOOKUP(M17,'Location Code Code'!E3:F24,2,FALSE) -> HEAD OFFICE NYASHISHI MWANZA | O17: MGL0011 | P17: =VLOOKUP(O17,'Business Code'!C2:D22,2,FALSE) -> MANUFACTUREING OF COMMERCIAL EXPLOSIVES | Q17: MGL001 | R17: =VLOOKUP(Q17,'Company Code'!A2:B8,2,FALSE) -> Mbogo Mining and General Supply Limited | U17: VAT (18%) PAYABLE ON COMMISSION AND FEES : FULL | V17: 2340
A18: 22.12.2024 | D18: CRDB BANK PLC | E18: 56150600 | F18: =VLOOKUP(E18,'Improved Accounting codes'!C12:D2352,2,FALSE) -> CRDB TZS:0150481116500 | G18: 561506 | H18: =VLOOKUP(G18,'Improved Accounting codes'!A12:B2352,2,FALSE) -> CRDB BANK PLC | I18: FAD00102 | J18: =VLOOKUP(I18,'Section Code'!B3:C19,2,FALSE) -> Finance Section | K18: FAD001 | L18: =VLOOKUP(K18,'Department Codes'!A2:B5,2,FALSE) -> Finance and Administration Department | M18: MGL00121 | N18: =VLOOKUP(M18,'Location Code Code'!E3:F24,2,FALSE) -> HEAD OFFICE NYASHISHI MWANZA | O18: MGL0011 | P18: =VLOOKUP(O18,'Business Code'!C2:D22,2,FALSE) -> MANUFACTUREING OF COMMERCIAL EXPLOSIVES | Q18: MGL001 | R18: =VLOOKUP(Q18,'Company Code'!A2:B8,2,FALSE) -> Mbogo Mining and General Supply Limited | U18: VAT (18%) PAYABLE ON COMMISSION AND FEES : FULL | W18: 2340
A19: 23.12.2024 | D19: GePG | E19: 62460227 | F19: =VLOOKUP(E19,'Improved Accounting codes'!C13:D2353,2,FALSE) -> Government Bill | G19: 624602 | H19: =VLOOKUP(G19,'Improved Accounting codes'!A13:B2353,2,FALSE) -> Government Fees and Similar | I19: FAD00102 | J19: =VLOOKUP(I19,'Section Code'!B3:C19,2,FALSE) -> Finance Section | K19: FAD001 | L19: =VLOOKUP(K19,'Department Codes'!A2:B5,2,FALSE) -> Finance and Administration Department | M19: MGL00121 | N19: =VLOOKUP(M19,'Location Code Code'!E3:F24,2,FALSE) -> HEAD OFFICE NYASHISHI MWANZA | O19: MGL0011 | P19: =VLOOKUP(O19,'Business Code'!C2:D22,2,FALSE) -> MANUFACTUREING OF COMMERCIAL EXPLOSIVES | Q19: MGL001 | R19: =VLOOKUP(Q19,'Company Code'!A2:B8,2,FALSE) -> Mbogo Mining and General Supply Limited | U19: REF:193f2e53ba1f28f8 IB GePG BIL 991193051869 REC 924358298939512 MBOGO MINING AND GENERAL | V19: 2047827
A20: 23.12.2024 | D20: GePG | E20: 56150600 | F20: =VLOOKUP(E20,'Improved Accounting codes'!C14:D2354,2,FALSE) -> CRDB TZS:0150481116500 | G20: 561506 | H20: =VLOOKUP(G20,'Improved Accounting codes'!A14:B2354,2,FALSE) -> CRDB BANK PLC | I20: FAD00102 | J20: =VLOOKUP(I20,'Section Code'!B3:C19,2,FALSE) -> Finance Section | K20: FAD001 | L20: =VLOOKUP(K20,'Department Codes'!A2:B5,2,FALSE) -> Finance and Administration Department | M20: MGL00121 | N20: =VLOOKUP(M20,'Location Code Code'!E3:F24,2,FALSE) -> HEAD OFFICE NYASHISHI MWANZA | O20: MGL0011 | P20: =VLOOKUP(O20,'Business Code'!C2:D22,2,FALSE) -> MANUFACTUREING OF COMMERCIAL EXPLOSIVES | Q20: MGL001 | R20: =VLOOKUP(Q20,'Company Code'!A2:B8,2,FALSE) -> Mbogo Mining and General Supply Limited | U20: REF:193f2e53ba1f28f8 IB GePG BIL 991193051869 REC 924358298939512 MBOGO MINING AND GENERAL | W20: 2047827
A21: 23.12.2024 | D21: CRDB BANK PLC | E21: 63860720 | F21: =VLOOKUP(E21,'Improved Accounting codes'!C15:D2355,2,FALSE) -> #N/A | G21: 638607 | H21: =VLOOKUP(G21,'Improved Accounting codes'!A15:B2355,2,FALSE) -> Bank Charges | I21: FAD00102 | J21: =VLOOKUP(I21,'Section Code'!B3:C19,2,FALSE) -> Finance Section | K21: FAD001 | L21: =VLOOKUP(K21,'Department Codes'!A2:B5,2,FALSE) -> Finance and Administration Department | M21: MGL00121 | N21: =VLOOKUP(M21,'Location Code Code'!E3:F24,2,FALSE) -> HEAD OFFICE NYASHISHI MWANZA | O21: MGL0011 | P21: =VLOOKUP(O21,'Business Code'!C2:D22,2,FALSE) -> MANUFACTUREING OF COMMERCIAL EXPLOSIVES | Q21: MGL001 | R21: =VLOOKUP(Q21,'Company Code'!A2:B8,2,FALSE) -> Mbogo Mining and General Supply Limited | U21: REF:193f2e53ba1f28f8 CHARGE: GePG VIA IB | V21: 7000
A22: 23.12.2024 | D22: CRDB BANK PLC | E22: 56150600 | F22: CRDB TZS:0150481116500 | G22: 561506 | H22: =VLOOKUP(G22,'Improved Accounting codes'!A16:B2356,2,FALSE) -> CRDB BANK PLC | I22: FAD00102 | J22: =VLOOKUP(I22,'Section Code'!B3:C19,2,FALSE) -> Finance Section | K22: FAD001 | L22: =VLOOKUP(K22,'Department Codes'!A2:B5,2,FALSE) -> Finance and Administration Department | M22: MGL00121 | N22: =VLOOKUP(M22,'Location Code Code'!E3:F24,2,FALSE) -> HEAD OFFICE NYASHISHI MWANZA | O22: MGL0011 | P22: =VLOOKUP(O22,'Business Code'!C2:D22,2,FALSE) -> MANUFACTUREING OF COMMERCIAL EXPLOSIVES | Q22: MGL001 | R22: =VLOOKUP(Q22,'Company Code'!A1:B7,2,FALSE) -> Mbogo Mining and General Supply Limited | U22: REF:193f2e53ba1f28f8 CHARGE: GePG VIA IB | W22: 7000
A23: 23.12.2024 | D23: NILE COMPLEX PLAZA LTD | E23: 40540101 | F23: CRDB TZS:0150481116500 | G23: 405401 | H23: =VLOOKUP(G23,'Improved Accounting codes'!A17:B2357,2,FALSE) -> Suppliers related companies | I23: BDD00101 | J23: =VLOOKUP(I23,'Section Code'!B3:C19,2,FALSE) -> General Supply Section | K23: BDD001 | L23: =VLOOKUP(K23,'Department Codes'!A2:B5,2,FALSE) -> Business Development Department | M23: NCL00111 | N23: =VLOOKUP(M23,'Location Code Code'!E3:F24,2,FALSE) -> HEAD OFFICE NYASHISHI MWANZA | O23: NCL0011 | P23: =VLOOKUP(O23,'Business Code'!C2:D22,2,FALSE) -> NILE OIL: TRADING OF PETROLEUM PRODUCTS | Q23: NCL001 | R23: =VLOOKUP(Q23,'Company Code'!A2:B8,2,FALSE) -> Nile Complex Plaza Limited | U23: REF:193f2ed867b9fb26 IB TIPS FT FROM MBOGO TO NILE COMPLEX PLAZA LIMITED NILE COMPLEX PLAZ | V23: 2300000
A24: 23.12.2024 | D24: NILE COMPLEX PLAZA LTD | E24: 56150600 | F24: CRDB TZS:0150481116500 | G24: 561506 | H24: =VLOOKUP(G24,'Improved Accounting codes'!A18:B2358,2,FALSE) -> CRDB BANK PLC | I24: BDD00101 | J24: =VLOOKUP(I24,'Section Code'!B3:C19,2,FALSE) -> General Supply Section | K24: BDD001 | L24: =VLOOKUP(K24,'Department Codes'!A2:B5,2,FALSE) -> Business Development Department | M24: NCL00111 | N24: =VLOOKUP(M24,'Location Code Code'!E3:F24,2,FALSE) -> HEAD OFFICE NYASHISHI MWANZA | O24: NCL0011 | P24: =VLOOKUP(O24,'Business Code'!C2:D22,2,FALSE) -> NILE OIL: TRADING OF PETROLEUM PRODUCTS | Q24: NCL001 | R24: =VLOOKUP(Q24,'Company Code'!A2:B8,2,FALSE) -> Nile Complex Plaza Limited | U24: REF:193f2ed867b9fb26 IB TIPS FT FROM MBOGO TO NILE COMPLEX PLAZA LIMITED NILE COMPLEX PLAZ | W24: 2300000
A25: 23.12.2024 | D25: CRDB BANK PLC | E25: 56150600 | F25: CRDB TZS:0150481116500 | G25: 638607 | H25: =VLOOKUP(G25,'Improved Accounting codes'!A19:B2359,2,FALSE) -> Bank Charges | I25: FAD00102 | J25: =VLOOKUP(I25,'Section Code'!B3:C19,2,FALSE) -> Finance Section | K25: FAD001 | L25: =VLOOKUP(K25,'Department Codes'!A2:B5,2,FALSE) -> Finance and Administration Department | M25: MGL00121 | N25: =VLOOKUP(M25,'Location Code Code'!E3:F24,2,FALSE) -> HEAD OFFICE NYASHISHI MWANZA | O25: MGL0011 | P25: =VLOOKUP(O25,'Business Code'!C2:D22,2,FALSE) -> MANUFACTUREING OF COMMERCIAL EXPLOSIVES | Q25: MGL001 | R25: =VLOOKUP(Q25,'Company Code'!A2:B8,2,FALSE) -> Mbogo Mining and General Supply Limited | U25: REF:193f2ed867b9fb26 CHARGE: TIPS TRANSFER VIA IB | V25: 1500
A26: 23.12.2024 | D26: CRDB BANK PLC | E26: 56150600 | F26: =VLOOKUP(E26,'Improved Accounting codes'!C14:D2354,2,FALSE) -> CRDB TZS:0150481116500 | G26: 561506 | H26: =VLOOKUP(G26,'Improved Accounting codes'!A14:B2354,2,FALSE) -> CRDB BANK PLC | I26: FAD00102 | J26: =VLOOKUP(I26,'Section Code'!B3:C19,2,FALSE) -> Finance Section | K26: FAD001 | L26: =VLOOKUP(K26,'Department Codes'!A2:B5,2,FALSE) -> Finance and Administration Department | M26: MGL00121 | N26: =VLOOKUP(M26,'Location Code Code'!E3:F24,2,FALSE) -> HEAD OFFICE NYASHISHI MWANZA | O26: MGL0011 | P26: =VLOOKUP(O26,'Business Code'!C2:D22,2,FALSE) -> MANUFACTUREING OF COMMERCIAL EXPLOSIVES | Q26: MGL001 | R26: =VLOOKUP(Q26,'Company Code'!A2:B8,2,FALSE) -> Mbogo Mining and General Supply Limited | U26: REF:193f2ed867b9fb26 CHARGE: TIPS TRANSFER VIA IB | W26: 1500
A27: 23.12.2024 | D27: NILE COMPLEX PLAZA LTD | E27: 40540101 | F27: =VLOOKUP(E27,'Improved Accounting codes'!C15:D2355,2,FALSE) -> Nile Complex Plaza Limited | G27: 405401 | H27: =VLOOKUP(G27,'Improved Accounting codes'!A15:B2355,2,FALSE) -> Suppliers related companies | I27: BDD00101 | J27: General Supply Section | K27: BDD001 | L27: Business Development Department | M27: NCL00111 | N27: HEAD OFFICE NYASHISHI MWANZA | O27: NCL0011 | P27: NILE OIL: TRADING OF PETROLEUM PRODUCTS | Q27: NCL001 | R27: =VLOOKUP(Q27,'Company Code'!A2:B8,2,FALSE) -> Nile Complex Plaza Limited | U27: REF:193f31b3f627ebb9 IB TIPS FT FROM MBOGO TO NYASHISHI FINANCE LIMITED NYASHISHI FINANCE | V27: 5900000
A28: 23.12.2024 | D28: NILE COMPLEX PLAZA LTD | E28: 56150600 | F28: =VLOOKUP(E28,'Improved Accounting codes'!C16:D2356,2,FALSE) -> CRDB TZS:0150481116500 | G28: 561506 | H28: =VLOOKUP(G28,'Improved Accounting codes'!A16:B2356,2,FALSE) -> CRDB BANK PLC | I28: BDD00101 | J28: General Supply Section | K28: BDD001 | L28: Business Development Department | M28: NCL00111 | N28: HEAD OFFICE NYASHISHI MWANZA | O28: NCL0011 | P28: NILE OIL: TRADING OF PETROLEUM PRODUCTS | Q28: NCL001 | R28: =VLOOKUP(Q28,'Company Code'!A2:B8,2,FALSE) -> Nile Complex Plaza Limited | U28: REF:193f31b3f627ebb9 IB TIPS FT FROM MBOGO TO NYASHISHI FINANCE LIMITED NYASHISHI FINANCE | W28: 5900000
A29: 23.12.2024 | D29: CRDB BANK PLC | E29: 56150600 | F29: =VLOOKUP(E29,'Improved Accounting codes'!C17:D2357,2,FALSE) -> CRDB TZS:0150481116500 | G29: 638607 | H29: =VLOOKUP(G29,'Improved Accounting codes'!A17:B2357,2,FALSE) -> Bank Charges | I29: FAD00102 | J29: =VLOOKUP(I29,'Section Code'!B3:C19,2,FALSE) -> Finance Section | K29: FAD001 | L29: =VLOOKUP(K29,'Department Codes'!A2:B5,2,FALSE) -> Finance and Administration Department | M29: MGL00121 | N29: =VLOOKUP(M29,'Location Code Code'!E3:F24,2,FALSE) -> HEAD OFFICE NYASHISHI MWANZA | O29: MGL0011 | P29: =VLOOKUP(O29,'Business Code'!C2:D22,2,FALSE) -> MANUFACTUREING OF COMMERCIAL EXPLOSIVES | Q29: MGL001 | R29: =VLOOKUP(Q29,'Company Code'!A2:B8,2,FALSE) -> Mbogo Mining and General Supply Limited | U29: REF:193f31b3f627ebb9 CHARGE: TIPS TRANSFER VIA IB | V29: 2000
A30: 23.12.2024 | D30: CRDB BANK PLC | E30: 56150600 | F30: =VLOOKUP(E30,'Improved Accounting codes'!C18:D2358,2,FALSE) -> CRDB TZS:0150481116500 | G30: 561506 | H30: =VLOOKUP(G30,'Improved Accounting codes'!A18:B2358,2,FALSE) -> CRDB BANK PLC | I30: FAD00102 | J30: =VLOOKUP(I30,'Section Code'!B3:C19,2,FALSE) -> Finance Section | K30: FAD001 | L30: =VLOOKUP(K30,'Department Codes'!A2:B5,2,FALSE) -> Finance and Administration Department | M30: MGL00121 | N30: =VLOOKUP(M30,'Location Code Code'!E3:F24,2,FALSE) -> HEAD OFFICE NYASHISHI MWANZA | O30: MGL0011 | P30: =VLOOKUP(O30,'Business Code'!C2:D22,2,FALSE) -> MANUFACTUREING OF COMMERCIAL EXPLOSIVES | Q30: MGL001 | R30: =VLOOKUP(Q30,'Company Code'!A2:B8,2,FALSE) -> Mbogo Mining and General Supply Limited | U30: REF:193f31b3f627ebb9 CHARGE: TIPS TRANSFER VIA IB | W30: 2000
A31: 23.12.2024 | D31: BARNABAS ATHANAS NIBENGO | E31: 67560103 | F31: =VLOOKUP(E31,'Improved Accounting codes'!C35:D2375,2,FALSE) -> Barnabas Athanas Nibengo | G31: 675601 | H31: =VLOOKUP(G31,'Improved Accounting codes'!A19:B2359,2,FALSE) -> Uncategorised Expenses | I31: FAD00102 | J31: =VLOOKUP(I31,'Section Code'!B3:C19,2,FALSE) -> Finance Section | K31: FAD001 | L31: =VLOOKUP(K31,'Department Codes'!A2:B5,2,FALSE) -> Finance and Administration Department | M31: MGL00121 | N31: =VLOOKUP(M31,'Location Code Code'!E3:F24,2,FALSE) -> HEAD OFFICE NYASHISHI MWANZA | O31: MGL0011 | P31: =VLOOKUP(O31,'Business Code'!C2:D22,2,FALSE) -> MANUFACTUREING OF COMMERCIAL EXPLOSIVES | Q31: MGL001 | R31: =VLOOKUP(Q31,'Company Code'!A2:B8,2,FALSE) -> Mbogo Mining and General Supply Limited | U31: REF:193f38dec80f29cb IB FT TO MPESA 0757851332 BARNABAS ATHANAS NIBENGO | V31: 1500000
A32: 23.12.2024 | D32: BARNABAS ATHANAS NIBENGO | E32: 56150600 | F32: =VLOOKUP(E32,'Improved Accounting codes'!C36:D2376,2,FALSE) -> CRDB TZS:0150481116500 | G32: 561506 | H32: =VLOOKUP(G32,'Improved Accounting codes'!A20:B2360,2,FALSE) -> CRDB BANK PLC | I32: FAD00102 | J32: =VLOOKUP(I32,'Section Code'!B3:C19,2,FALSE) -> Finance Section | K32: FAD001 | L32: =VLOOKUP(K32,'Department Codes'!A2:B5,2,FALSE) -> Finance and Administration Department | M32: MGL00121 | N32: =VLOOKUP(M32,'Location Code Code'!E3:F24,2,FALSE) -> HEAD OFFICE NYASHISHI MWANZA | O32: MGL0011 | P32: =VLOOKUP(O32,'Business Code'!C2:D22,2,FALSE) -> MANUFACTUREING OF COMMERCIAL EXPLOSIVES | Q32: MGL001 | R32: =VLOOKUP(Q32,'Company Code'!A2:B8,2,FALSE) -> Mbogo Mining and General Supply Limited | U32: REF:193f38dec80f29cb IB FT TO MPESA 0757851332 BARNABAS ATHANAS NIBENGO | W32: 1500000
A33: 23.12.2024 | D33: CRDB BANK PLC | E33: 63860720 | F33: =VLOOKUP(E33,'Improved Accounting codes'!C37:D2377,2,FALSE) -> #N/A | G33: 638607 | H33: =VLOOKUP(G33,'Improved Accounting codes'!A21:B2361,2,FALSE) -> Bank Charges | I33: FAD00102 | J33: =VLOOKUP(I33,'Section Code'!B3:C19,2,FALSE) -> Finance Section | K33: FAD001 | L33: =VLOOKUP(K33,'Department Codes'!A2:B5,2,FALSE) -> Finance and Administration Department | M33: MGL00121 | N33: =VLOOKUP(M33,'Location Code Code'!E3:F24,2,FALSE) -> HEAD OFFICE NYASHISHI MWANZA | O33: MGL0011 | P33: =VLOOKUP(O33,'Business Code'!C2:D22,2,FALSE) -> MANUFACTUREING OF COMMERCIAL EXPLOSIVES | Q33: MGL001 | R33: =VLOOKUP(Q33,'Company Code'!A2:B8,2,FALSE) -> Mbogo Mining and General Supply Limited | U33: REF:193f38dec80f29cb CHARGE: TRANSFER TO MPESA VIA IB | V33: 10169.49
A34: 23.12.2024 | D34: CRDB BANK PLC | E34: 56150600 | F34: =VLOOKUP(E34,'Improved Accounting codes'!C38:D2378,2,FALSE) -> CRDB TZS:0150481116500 | G34: 561506 | H34: =VLOOKUP(G34,'Improved Accounting codes'!A22:B2362,2,FALSE) -> CRDB BANK PLC | I34: FAD00102 | J34: =VLOOKUP(I34,'Section Code'!B3:C19,2,FALSE) -> Finance Section | K34: FAD001 | L34: =VLOOKUP(K34,'Department Codes'!A2:B5,2,FALSE) -> Finance and Administration Department | M34: MGL00121 | N34: =VLOOKUP(M34,'Location Code Code'!E3:F24,2,FALSE) -> HEAD OFFICE NYASHISHI MWANZA | O34: MGL0011 | P34: =VLOOKUP(O34,'Business Code'!C2:D22,2,FALSE) -> MANUFACTUREING OF COMMERCIAL EXPLOSIVES | Q34: MGL001 | R34: =VLOOKUP(Q34,'Company Code'!A2:B8,2,FALSE) -> Mbogo Mining and General Supply Limited | U34: REF:193f38dec80f29cb CHARGE: TRANSFER TO MPESA VIA IB | W34: 10169.49
A35: 23.12.2024 | D35: CRDB BANK PLC | E35: 25520102 | F35: =VLOOKUP(E35,'Improved Accounting codes'!C39:D2379,2,FALSE) -> Loans to subsidiaries | G35: 255201 | H35: =VLOOKUP(G35,'Improved Accounting codes'!A23:B2363,2,FALSE) -> Recievables on loans | I35: FAD00102 | J35: =VLOOKUP(I35,'Section Code'!B3:C19,2,FALSE) -> Finance Section | K35: FAD001 | L35: =VLOOKUP(K35,'Department Codes'!A2:B5,2,FALSE) -> Finance and Administration Department | M35: MGL00121 | N35: =VLOOKUP(M35,'Location Code Code'!E3:F24,2,FALSE) -> HEAD OFFICE NYASHISHI MWANZA | O35: MGL0011 | P35: =VLOOKUP(O35,'Business Code'!C2:D22,2,FALSE) -> MANUFACTUREING OF COMMERCIAL EXPLOSIVES | Q35: MGL001 | R35: =VLOOKUP(Q35,'Company Code'!A2:B8,2,FALSE) -> Mbogo Mining and General Supply Limited | U35: VAT (18%) PAYABLE ON COMMISSION AND FEES : FULL | V35: 270
A36: 23.12.2024 | D36: CRDB BANK PLC | E36: 56150600 | F36: =VLOOKUP(E36,'Improved Accounting codes'!C40:D2380,2,FALSE) -> CRDB TZS:0150481116500 | G36: 561506 | H36: =VLOOKUP(G36,'Improved Accounting codes'!A24:B2364,2,FALSE) -> CRDB BANK PLC | I36: FAD00102 | J36: =VLOOKUP(I36,'Section Code'!B3:C19,2,FALSE) -> Finance Section | K36: FAD001 | L36: =VLOOKUP(K36,'Department Codes'!A2:B5,2,FALSE) -> Finance and Administration Department | M36: MGL00121 | N36: =VLOOKUP(M36,'Location Code Code'!E3:F24,2,FALSE) -> HEAD OFFICE NYASHISHI MWANZA | O36: MGL0011 | P36: =VLOOKUP(O36,'Business Code'!C2:D22,2,FALSE) -> MANUFACTUREING OF COMMERCIAL EXPLOSIVES | Q36: MGL001 | R36: =VLOOKUP(Q36,'Company Code'!A2:B8,2,FALSE) -> Mbogo Mining and General Supply Limited | U36: VAT (18%) PAYABLE ON COMMISSION AND FEES : FULL | W36: 270
A37: 23.12.2024 | D37: CRDB BANK PLC | E37: 25520102 | F37: =VLOOKUP(E37,'Improved Accounting codes'!C41:D2381,2,FALSE) -> Loans to subsidiaries | G37: 255201 | H37: =VLOOKUP(G37,'Improved Accounting codes'!A25:B2365,2,FALSE) -> Recievables on loans | I37: FAD00102 | J37: =VLOOKUP(I37,'Section Code'!B3:C19,2,FALSE) -> Finance Section | K37: FAD001 | L37: =VLOOKUP(K37,'Department Codes'!A2:B5,2,FALSE) -> Finance and Administration Department | M37: MGL00121 | N37: =VLOOKUP(M37,'Location Code Code'!E3:F24,2,FALSE) -> HEAD OFFICE NYASHISHI MWANZA | O37: MGL0011 | P37: =VLOOKUP(O37,'Business Code'!C2:D22,2,FALSE) -> MANUFACTUREING OF COMMERCIAL EXPLOSIVES | Q37: MGL001 | R37: =VLOOKUP(Q37,'Company Code'!A2:B8,2,FALSE) -> Mbogo Mining and General Supply Limited | U37: VAT (18%) PAYABLE ON COMMISSION AND FEES : FULL | V37: 360
A38: 23.12.2024 | D38: CRDB BANK PLC | E38: 56150600 | F38: =VLOOKUP(E38,'Improved Accounting codes'!C42:D2382,2,FALSE) -> CRDB TZS:0150481116500 | G38: 561506 | H38: =VLOOKUP(G38,'Improved Accounting codes'!A26:B2366,2,FALSE) -> CRDB BANK PLC | I38: FAD00102 | J38: =VLOOKUP(I38,'Section Code'!B3:C19,2,FALSE) -> Finance Section | K38: FAD001 | L38: =VLOOKUP(K38,'Department Codes'!A2:B5,2,FALSE) -> Finance and Administration Department | M38: MGL00121 | N38: =VLOOKUP(M38,'Location Code Code'!E3:F24,2,FALSE) -> HEAD OFFICE NYASHISHI MWANZA | O38: MGL0011 | P38: =VLOOKUP(O38,'Business Code'!C2:D22,2,FALSE) -> MANUFACTUREING OF COMMERCIAL EXPLOSIVES | Q38: MGL001 | R38: =VLOOKUP(Q38,'Company Code'!A2:B8,2,FALSE) -> Mbogo Mining and General Supply Limited | U38: VAT (18%) PAYABLE ON COMMISSION AND FEES : FULL | W38: 360
A39: 23.12.2024 | D39: CRDB BANK PLC | E39: 25520102 | F39: =VLOOKUP(E39,'Improved Accounting codes'!C43:D2383,2,FALSE) -> Loans to subsidiaries | G39: 255201 | H39: =VLOOKUP(G39,'Improved Accounting codes'!A27:B2367,2,FALSE) -> Recievables on loans | I39: FAD00102 | J39: =VLOOKUP(I39,'Section Code'!B3:C19,2,FALSE) -> Finance Section | K39: FAD001 | L39: =VLOOKUP(K39,'Department Codes'!A2:B5,2,FALSE) -> Finance and Administration Department | M39: MGL00121 | N39: =VLOOKUP(M39,'Location Code Code'!E3:F24,2,FALSE) -> HEAD OFFICE NYASHISHI MWANZA | O39: MGL0011 | P39: =VLOOKUP(O39,'Business Code'!C2:D22,2,FALSE) -> MANUFACTUREING OF COMMERCIAL EXPLOSIVES | Q39: MGL001 | R39: =VLOOKUP(Q39,'Company Code'!A2:B8,2,FALSE) -> Mbogo Mining and General Supply Limited | U39: VAT (18%) PAYABLE ON COMMISSION AND FEES : FULL | V39: 1830.51
A40: 23.12.2024 | D40: CRDB BANK PLC | E40: 56150600 | F40: =VLOOKUP(E40,'Improved Accounting codes'!C44:D2384,2,FALSE) -> CRDB TZS:0150481116500 | G40: 561506 | H40: =VLOOKUP(G40,'Improved Accounting codes'!A28:B2368,2,FALSE) -> CRDB BANK PLC | I40: FAD00102 | J40: =VLOOKUP(I40,'Section Code'!B3:C19,2,FALSE) -> Finance Section | K40: FAD001 | L40: =VLOOKUP(K40,'Department Codes'!A2:B5,2,FALSE) -> Finance and Administration Department | M40: MGL00121 | N40: =VLOOKUP(M40,'Location Code Code'!E3:F24,2,FALSE) -> HEAD OFFICE NYASHISHI MWANZA | O40: MGL0011 | P40: =VLOOKUP(O40,'Business Code'!C2:D22,2,FALSE) -> MANUFACTUREING OF COMMERCIAL EXPLOSIVES | Q40: MGL001 | R40: =VLOOKUP(Q40,'Company Code'!A2:B8,2,FALSE) -> Mbogo Mining and General Supply Limited | U40: VAT (18%) PAYABLE ON COMMISSION AND FEES : FULL | W40: 1830.51
A41: 24.12.2024 | D41: BARNABAS ATHANAS NIBENGO | E41: 40540104 | F41: =VLOOKUP(E41,'Improved Accounting codes'!C45:D2385,2,FALSE) -> Barnabas Athanas Nibengo | G41: 405401 | H41: =VLOOKUP(G41,'Improved Accounting codes'!A29:B2369,2,FALSE) -> Suppliers related companies | I41: FAD00102 | J41: =VLOOKUP(I41,'Section Code'!B3:C19,2,FALSE) -> Finance Section | K41: FAD001 | L41: =VLOOKUP(K41,'Department Codes'!A2:B5,2,FALSE) -> Finance and Administration Department | M41: MGL00121 | N41: =VLOOKUP(M41,'Location Code Code'!E3:F24,2,FALSE) -> HEAD OFFICE NYASHISHI MWANZA | O41: MGL0011 | P41: =VLOOKUP(O41,'Business Code'!C2:D22,2,FALSE) -> MANUFACTUREING OF COMMERCIAL EXPLOSIVES | Q41: MGL001 | R41: =VLOOKUP(Q41,'Company Code'!A2:B8,2,FALSE) -> Mbogo Mining and General Supply Limited | U41: REF:193f81d777212b2f IB FT TO MPESA 0757851332 BARNABAS ATHANAS NIBENGO | V41: 3000000
A42: 24.12.2024 | D42: BARNABAS ATHANAS NIBENGO | E42: 56150600 | F42: =VLOOKUP(E42,'Improved Accounting codes'!C46:D2386,2,FALSE) -> CRDB TZS:0150481116500 | G42: 561506 | H42: =VLOOKUP(G42,'Improved Accounting codes'!A30:B2370,2,FALSE) -> CRDB BANK PLC | I42: FAD00102 | J42: =VLOOKUP(I42,'Section Code'!B3:C19,2,FALSE) -> Finance Section | K42: FAD001 | L42: =VLOOKUP(K42,'Department Codes'!A2:B5,2,FALSE) -> Finance and Administration Department | M42: MGL00121 | N42: =VLOOKUP(M42,'Location Code Code'!E3:F24,2,FALSE) -> HEAD OFFICE NYASHISHI MWANZA | O42: MGL0011 | P42: =VLOOKUP(O42,'Business Code'!C2:D22,2,FALSE) -> MANUFACTUREING OF COMMERCIAL EXPLOSIVES | Q42: MGL001 | R42: =VLOOKUP(Q42,'Company Code'!A2:B8,2,FALSE) -> Mbogo Mining and General Supply Limited | U42: REF:193f81d777212b2f IB FT TO MPESA 0757851332 BARNABAS ATHANAS NIBENGO | W42: 3000000
A43: 24.12.2024 | D43: CRDB BANK PLC | E43: 63860720 | F43: =VLOOKUP(E43,'Improved Accounting codes'!C47:D2387,2,FALSE) -> #N/A | G43: 638607 | H43: Bank Charges | I43: FAD00102 | J43: =VLOOKUP(I43,'Section Code'!B3:C19,2,FALSE) -> Finance Section | K43: FAD001 | L43: =VLOOKUP(K43,'Department Codes'!A2:B5,2,FALSE) -> Finance and Administration Department | M43: MGL00121 | N43: =VLOOKUP(M43,'Location Code Code'!E3:F24,2,FALSE) -> HEAD OFFICE NYASHISHI MWANZA | O43: MGL0011 | P43: =VLOOKUP(O43,'Business Code'!C2:D22,2,FALSE) -> MANUFACTUREING OF COMMERCIAL EXPLOSIVES | Q43: MGL001 | R43: =VLOOKUP(Q43,'Company Code'!A2:B8,2,FALSE) -> Mbogo Mining and General Supply Limited | U43: REF:193f81d777212b2f CHARGE: TRANSFER TO MPESA VIA IB | V43: 10169.49
A44: 24.12.2024 | D44: CRDB BANK PLC | E44: 56150600 | F44: =VLOOKUP(E44,'Improved Accounting codes'!C48:D2388,2,FALSE) -> CRDB TZS:0150481116500 | G44: 561506 | H44: CRDB BANK PLC | I44: FAD00102 | J44: =VLOOKUP(I44,'Section Code'!B3:C19,2,FALSE) -> Finance Section | K44: FAD001 | L44: =VLOOKUP(K44,'Department Codes'!A2:B5,2,FALSE) -> Finance and Administration Department | M44: MGL00121 | N44: =VLOOKUP(M44,'Location Code Code'!E3:F24,2,FALSE) -> HEAD OFFICE NYASHISHI MWANZA | O44: MGL0011 | P44: =VLOOKUP(O44,'Business Code'!C2:D22,2,FALSE) -> MANUFACTUREING OF COMMERCIAL EXPLOSIVES | Q44: MGL001 | R44: =VLOOKUP(Q44,'Company Code'!A2:B8,2,FALSE) -> Mbogo Mining and General Supply Limited | U44: REF:193f81d777212b2f CHARGE: TRANSFER TO MPESA VIA IB | W44: 10169.49
A45: 24.12.2024 | D45: CRDB BANK PLC | E45: 25520102 | F45: =VLOOKUP(E45,'Improved Accounting codes'!C49:D2389,2,FALSE) -> Loans to subsidiaries | G45: 255201 | H45: CRDB BANK PLC | I45: FAD00102 | J45: =VLOOKUP(I45,'Section Code'!B3:C19,2,FALSE) -> Finance Section | K45: FAD001 | L45: =VLOOKUP(K45,'Department Codes'!A2:B5,2,FALSE) -> Finance and Administration Department | M45: MGL00121 | N45: =VLOOKUP(M45,'Location Code Code'!E3:F24,2,FALSE) -> HEAD OFFICE NYASHISHI MWANZA | O45: MGL0011 | P45: =VLOOKUP(O45,'Business Code'!C2:D22,2,FALSE) -> MANUFACTUREING OF COMMERCIAL EXPLOSIVES | Q45: MGL001 | R45: =VLOOKUP(Q45,'Company Code'!A2:B8,2,FALSE) -> Mbogo Mining and General Supply Limited | U45: VAT (18%) PAYABLE ON COMMISSION AND FEES : FULL | V45: 1830.51
A46: 24.12.2024 | D46: CRDB BANK PLC | E46: 56150600 | F46: =VLOOKUP(E46,'Improved Accounting codes'!C50:D2390,2,FALSE) -> CRDB TZS:0150481116500 | G46: 561506 | H46: CRDB BANK PLC | I46: FAD00102 | J46: =VLOOKUP(I46,'Section Code'!B3:C19,2,FALSE) -> Finance Section | K46: FAD001 | L46: =VLOOKUP(K46,'Department Codes'!A2:B5,2,FALSE) -> Finance and Administration Department | M46: MGL00121 | N46: =VLOOKUP(M46,'Location Code Code'!E3:F24,2,FALSE) -> HEAD OFFICE NYASHISHI MWANZA | O46: MGL0011 | P46: =VLOOKUP(O46,'Business Code'!C2:D22,2,FALSE) -> MANUFACTUREING OF COMMERCIAL EXPLOSIVES | Q46: MGL001 | R46: =VLOOKUP(Q46,'Company Code'!A2:B8,2,FALSE) -> Mbogo Mining and General Supply Limited | U46: VAT (18%) PAYABLE ON COMMISSION AND FEES : FULL | W46: 1830.51
A47: 27.12.2024 | D47: EDWARD MTANAH | E47: 56150600 | F47: =VLOOKUP(E47,'Improved Accounting codes'!C51:D2391,2,FALSE) -> CRDB TZS:0150481116500 | G47: 561506 | H47: =VLOOKUP(G47,'Improved Accounting codes'!A51:B2391,2,FALSE) -> CRDB BANK PLC | I47: FAD00102 | J47: =VLOOKUP(I47,'Section Code'!B3:C19,2,FALSE) -> Finance Section | K47: FAD001 | L47: =VLOOKUP(K47,'Department Codes'!A2:B5,2,FALSE) -> Finance and Administration Department | M47: MGL00121 | N47: =VLOOKUP(M47,'Location Code Code'!E3:F24,2,FALSE) -> HEAD OFFICE NYASHISHI MWANZA | O47: MGL0011 | P47: =VLOOKUP(O47,'Business Code'!C2:D22,2,FALSE) -> MANUFACTUREING OF COMMERCIAL EXPLOSIVES | Q47: MGL001 | R47: =VLOOKUP(Q47,'Company Code'!A2:B8,2,FALSE) -> Mbogo Mining and General Supply Limited | U47: EDWARD CASH DEPOSITS | V47: 99220000
A48: 27.12.2024 | D48: EDWARD MTANAH | E48: 67560106 | F48: =VLOOKUP(E48,'Improved Accounting codes'!C41:D2381,2,FALSE) -> Edward mtanah | G48: 675601 | H48: =VLOOKUP(G48,'Improved Accounting codes'!A52:B2392,2,FALSE) -> Uncategorised Expenses | I48: FAD00102 | J48: =VLOOKUP(I48,'Section Code'!B3:C19,2,FALSE) -> Finance Section | K48: FAD001 | L48: =VLOOKUP(K48,'Department Codes'!A2:B5,2,FALSE) -> Finance and Administration Department | M48: MGL00121 | N48: =VLOOKUP(M48,'Location Code Code'!E3:F24,2,FALSE) -> HEAD OFFICE NYASHISHI MWANZA | O48: MGL0011 | P48: =VLOOKUP(O48,'Business Code'!C2:D22,2,FALSE) -> MANUFACTUREING OF COMMERCIAL EXPLOSIVES | Q48: MGL001 | R48: =VLOOKUP(Q48,'Company Code'!A2:B8,2,FALSE) -> Mbogo Mining and General Supply Limited | U48: EDWARD CASH DEPOSITS | W48: 99220000
A49: 27.12.2024 | C49: 140 | D49: EDWARD GIDION MTANAH | E49: 56150600 | F49: =VLOOKUP(E49,'Improved Accounting codes'!C42:D2382,2,FALSE) -> CRDB TZS:0150481116500 | G49: 572501 | H49: =VLOOKUP(G49,'Improved Accounting codes'!A53:B2393,2,FALSE) -> Cash for Office Use | I49: FAD00102 | J49: =VLOOKUP(I49,'Section Code'!B3:C19,2,FALSE) -> Finance Section | K49: FAD001 | L49: =VLOOKUP(K49,'Department Codes'!A2:B5,2,FALSE) -> Finance and Administration Department | M49: MGL00121 | N49: =VLOOKUP(M49,'Location Code Code'!E3:F24,2,FALSE) -> HEAD OFFICE NYASHISHI MWANZA | O49: MGL0011 | P49: =VLOOKUP(O49,'Business Code'!C3:D23,2,FALSE) -> #N/A | Q49: MGL001 | R49: =VLOOKUP(Q49,'Company Code'!A2:B8,2,FALSE) -> Mbogo Mining and General Supply Limited | U49: CHQ.NO. 000140 EDWARD MTANAH | V49: 35842500
A50: 27.12.2024 | C50: 140 | D50: EDWARD GIDION MTANAH | E50: 67560106 | F50: =VLOOKUP(E50,'Improved Accounting codes'!C43:D2383,2,FALSE) -> Edward mtanah | G50: 675601 | H50: =VLOOKUP(G50,'Improved Accounting codes'!A54:B2394,2,FALSE) -> Uncategorised Expenses | I50: FAD00102 | J50: =VLOOKUP(I50,'Section Code'!B3:C19,2,FALSE) -> Finance Section | K50: FAD001 | L50: =VLOOKUP(K50,'Department Codes'!A2:B5,2,FALSE) -> Finance and Administration Department | M50: MGL00121 | N50: =VLOOKUP(M50,'Location Code Code'!E3:F24,2,FALSE) -> HEAD OFFICE NYASHISHI MWANZA | O50: MGL0011 | P50: =VLOOKUP(O50,'Business Code'!C2:D22,2,FALSE) -> MANUFACTUREING OF COMMERCIAL EXPLOSIVES | Q50: MGL001 | R50: =VLOOKUP(Q50,'Company Code'!A2:B8,2,FALSE) -> Mbogo Mining and General Supply Limited | U50: CHQ.NO. 000140 EDWARD MTANAH | W50: 35842500
A51: 27.12.2024 | C51: 140 | D51: CURECHEM LTD | E51: 40140101 | F51: =VLOOKUP(E51,'Improved Accounting codes'!C27:D2367,2,FALSE) -> CURECHEM LTD | G51: 401401 | H51: =VLOOKUP(G51,'Improved Accounting codes'!A27:B2367,2,FALSE) -> Ordinary Suppliers- Explosives | I51: FAD00102 | J51: =VLOOKUP(I51,'Section Code'!B3:C19,2,FALSE) -> Finance Section | K51: FAD001 | L51: =VLOOKUP(K51,'Department Codes'!A2:B5,2,FALSE) -> Finance and Administration Department | M51: MGL00121 | N51: =VLOOKUP(M51,'Location Code Code'!E3:F24,2,FALSE) -> HEAD OFFICE NYASHISHI MWANZA | O51: MGL0011 | P51: =VLOOKUP(O51,'Business Code'!C2:D22,2,FALSE) -> MANUFACTUREING OF COMMERCIAL EXPLOSIVES | Q51: MGL001 | R51: =VLOOKUP(Q51,'Company Code'!A2:B8,2,FALSE) -> Mbogo Mining and General Supply Limited | U51: TZ#139 ETG CURECHEM LIMITED UINGIZAJI WA BIDHAA | V51: 20000000
A52: 27.12.2024 | C52: 140 | D52: CURECHEM LTD | E52: 56150600 | F52: =VLOOKUP(E52,'Improved Accounting codes'!C28:D2368,2,FALSE) -> CRDB TZS:0150481116500 | G52: 561506 | H52: =VLOOKUP(G52,'Improved Accounting codes'!A28:B2368,2,FALSE) -> CRDB BANK PLC | I52: FAD00102 | J52: =VLOOKUP(I52,'Section Code'!B3:C19,2,FALSE) -> Finance Section | K52: FAD001 | L52: =VLOOKUP(K52,'Department Codes'!A2:B5,2,FALSE) -> Finance and Administration Department | M52: MGL00121 | N52: =VLOOKUP(M52,'Location Code Code'!E3:F24,2,FALSE) -> HEAD OFFICE NYASHISHI MWANZA | O52: MGL0011 | P52: =VLOOKUP(O52,'Business Code'!C2:D22,2,FALSE) -> MANUFACTUREING OF COMMERCIAL EXPLOSIVES | Q52: MGL001 | R52: =VLOOKUP(Q52,'Company Code'!A2:B8,2,FALSE) -> Mbogo Mining and General Supply Limited | U52: TZ#139 ETG CURECHEM LIMITED UINGIZAJI WA BIDHAA | W52: 20000000
A53: 27.12.2024 | D53: CRDB BANK PLC | E53: 63860720 | F53: =VLOOKUP(E53,'Improved Accounting codes'!C57:D2397,2,FALSE) -> #N/A | G53: 638607 | H53: =VLOOKUP(G53,'Improved Accounting codes'!A29:B2369,2,FALSE) -> Bank Charges | I53: FAD00102 | J53: =VLOOKUP(I53,'Section Code'!B3:C19,2,FALSE) -> Finance Section | K53: FAD001 | L53: =VLOOKUP(K53,'Department Codes'!A2:B5,2,FALSE) -> Finance and Administration Department | M53: MGL00121 | N53: =VLOOKUP(M53,'Location Code Code'!E3:F24,2,FALSE) -> HEAD OFFICE NYASHISHI MWANZA | O53: MGL0011 | P53: =VLOOKUP(O53,'Business Code'!C2:D22,2,FALSE) -> MANUFACTUREING OF COMMERCIAL EXPLOSIVES | Q53: MGL001 | R53: =VLOOKUP(Q53,'Company Code'!A2:B8,2,FALSE) -> Mbogo Mining and General Supply Limited | U53: TZ#COMMISISON: UINGIZAJI WA BIDHAA | V53: 5000
D54: CRDB BANK PLC | E54: 56150600 | F54: =VLOOKUP(E54,'Improved Accounting codes'!C58:D2398,2,FALSE) -> CRDB TZS:0150481116500 | G54: 561506 | H54: =VLOOKUP(G54,'Improved Accounting codes'!A30:B2370,2,FALSE) -> CRDB BANK PLC | I54: FAD00102 | J54: =VLOOKUP(I54,'Section Code'!B3:C19,2,FALSE) -> Finance Section | K54: FAD001 | L54: =VLOOKUP(K54,'Department Codes'!A2:B5,2,FALSE) -> Finance and Administration Department | M54: MGL00121 | N54: =VLOOKUP(M54,'Location Code Code'!E3:F24,2,FALSE) -> HEAD OFFICE NYASHISHI MWANZA | O54: MGL0011 | P54: =VLOOKUP(O54,'Business Code'!C2:D22,2,FALSE) -> MANUFACTUREING OF COMMERCIAL EXPLOSIVES | Q54: MGL001 | R54: =VLOOKUP(Q54,'Company Code'!A2:B8,2,FALSE) -> Mbogo Mining and General Supply Limited | U54: TZ#COMMISISON: UINGIZAJI WA BIDHAA | W54: 5000
A55: 27.12.2024 | C55: 140 | D55: CRDB BANK PLC | E55: 63860720 | F55: =VLOOKUP(E55,'Improved Accounting codes'!C59:D2399,2,FALSE) -> #N/A | G55: 638607 | H55: =VLOOKUP(G55,'Improved Accounting codes'!A31:B2371,2,FALSE) -> Bank Charges | I55: FAD00102 | J55: =VLOOKUP(I55,'Section Code'!B3:C19,2,FALSE) -> Finance Section | K55: FAD001 | L55: =VLOOKUP(K55,'Department Codes'!A2:B5,2,FALSE) -> Finance and Administration Department | M55: MGL00121 | N55: =VLOOKUP(M55,'Location Code Code'!E3:F24,2,FALSE) -> HEAD OFFICE NYASHISHI MWANZA | O55: MGL0011 | P55: =VLOOKUP(O55,'Business Code'!C2:D22,2,FALSE) -> MANUFACTUREING OF COMMERCIAL EXPLOSIVES | Q55: MGL001 | R55: =VLOOKUP(Q55,'Company Code'!A2:B8,2,FALSE) -> Mbogo Mining and General Supply Limited | U55: REF:194086aa8894596b ENCASH CHRG CHQ: 000140 | V55: 35842.5
A56: 27.12.2024 | C56: 140 | D56: CRDB BANK PLC | E56: 56150600 | F56: =VLOOKUP(E56,'Improved Accounting codes'!C60:D2400,2,FALSE) -> CRDB TZS:0150481116500 | G56: 561506 | H56: =VLOOKUP(G56,'Improved Accounting codes'!A32:B2372,2,FALSE) -> CRDB BANK PLC | I56: FAD00102 | J56: =VLOOKUP(I56,'Section Code'!B3:C19,2,FALSE) -> Finance Section | K56: FAD001 | L56: =VLOOKUP(K56,'Department Codes'!A2:B5,2,FALSE) -> Finance and Administration Department | M56: MGL00121 | N56: =VLOOKUP(M56,'Location Code Code'!E3:F24,2,FALSE) -> HEAD OFFICE NYASHISHI MWANZA | O56: MGL0011 | P56: =VLOOKUP(O56,'Business Code'!C2:D22,2,FALSE) -> MANUFACTUREING OF COMMERCIAL EXPLOSIVES | Q56: MGL001 | R56: =VLOOKUP(Q56,'Company Code'!A2:B8,2,FALSE) -> Mbogo Mining and General Supply Limited | U56: REF:194086aa8894596b ENCASH CHRG CHQ: 000140 | W56: 35842.5
A57: 28.12.2024 | D57: CRDB BANK PLC | E57: 25520102 | F57: =VLOOKUP(E57,'Improved Accounting codes'!C61:D2401,2,FALSE) -> Loans to subsidiaries | G57: 255201 | H57: =VLOOKUP(G57,'Improved Accounting codes'!A33:B2373,2,FALSE) -> Recievables on loans | I57: FAD00102 | J57: Finance Section | K57: FAD001 | L57: Finance and Administration Department | M57: MGL00121 | N57: HEAD OFFICE NYASHISHI MWANZA | O57: MGL0011 | P57: MANUFACTUREING OF COMMERCIAL EXPLOSIVES | Q57: MGL001 | R57: Mbogo Mining and General Supply Limited | U57: VAT (18%) PAYABLE ON COMMISSION AND FEES : FULL | V57: 900
A58: 28.12.2024 | D58: CRDB BANK PLC | E58: 56150600 | F58: =VLOOKUP(E58,'Improved Accounting codes'!C62:D2402,2,FALSE) -> CRDB TZS:0150481116500 | G58: 561506 | H58: =VLOOKUP(G58,'Improved Accounting codes'!A34:B2374,2,FALSE) -> CRDB BANK PLC | I58: FAD00102 | J58: Finance Section | K58: FAD001 | L58: Finance and Administration Department | M58: MGL00121 | N58: HEAD OFFICE NYASHISHI MWANZA | O58: MGL0011 | P58: MANUFACTUREING OF COMMERCIAL EXPLOSIVES | Q58: MGL001 | R58: Mbogo Mining and General Supply Limited | U58: VAT (18%) PAYABLE ON COMMISSION AND FEES : FULL | W58: 900
A59: 28.12.2024 | D59: CRDB BANK PLC | E59: 25520102 | F59: =VLOOKUP(E59,'Improved Accounting codes'!C63:D2403,2,FALSE) -> Loans to subsidiaries | G59: 255201 | H59: =VLOOKUP(G59,'Improved Accounting codes'!A35:B2375,2,FALSE) -> Recievables on loans | I59: FAD00102 | J59: Finance Section | K59: FAD001 | L59: Finance and Administration Department | M59: MGL00121 | N59: HEAD OFFICE NYASHISHI MWANZA | O59: MGL0011 | P59: MANUFACTUREING OF COMMERCIAL EXPLOSIVES | Q59: MGL001 | R59: Mbogo Mining and General Supply Limited | U59: VAT (18%) PAYABLE ON COMMISSION AND FEES : FULL | V59: 6451.65
A60: 28.12.2024 | D60: CRDB BANK PLC | E60: 56150600 | F60: =VLOOKUP(E60,'Improved Accounting codes'!C64:D2404,2,FALSE) -> CRDB TZS:0150481116500 | G60: 561506 | H60: =VLOOKUP(G60,'Improved Accounting codes'!A36:B2376,2,FALSE) -> CRDB BANK PLC | I60: FAD00102 | J60: Finance Section | K60: FAD001 | L60: Finance and Administration Department | M60: MGL00121 | N60: HEAD OFFICE NYASHISHI MWANZA | O60: MGL0011 | P60: MANUFACTUREING OF COMMERCIAL EXPLOSIVES | Q60: MGL001 | R60: Mbogo Mining and General Supply Limited | U60: VAT (18%) PAYABLE ON COMMISSION AND FEES : FULL | W60: 6451.65
A61: 28.12.2024 | D61: NILE COMPLEX PLAZA LIMITED | E61: 40540101 | F61: =VLOOKUP(E61,'Improved Accounting codes'!C65:D2405,2,FALSE) -> Nile Complex Plaza Limited | G61: 405401 | H61: =VLOOKUP(G61,'Improved Accounting codes'!A37:B2377,2,FALSE) -> Suppliers related companies | I61: BDD00101 | J61: General Supply Section | K61: BDD001 | L61: Business Development Department | M61: NCL00111 | N61: HEAD OFFICE NYASHISHI MWANZA | O61: NCL0011 | P61: NILE OIL: TRADING OF PETROLEUM PRODUCTS | Q61: NCL001 | R61: =VLOOKUP(Q27,'Company Code'!A2:B8,2,FALSE) -> Nile Complex Plaza Limited | U61: REF:1940cce856cccada IB TIPS FT FROM MBOGO TO NILE COMPLEX PLAZA LIMITED NILE COMPLEX PLAZ | V61: 4835139
A62: 28.12.2024 | D62: NILE COMPLEX PLAZA LIMITED | E62: 56150600 | F62: =VLOOKUP(E62,'Improved Accounting codes'!C66:D2406,2,FALSE) -> CRDB TZS:0150481116500 | G62: 561506 | H62: =VLOOKUP(G62,'Improved Accounting codes'!A38:B2378,2,FALSE) -> CRDB BANK PLC | I62: BDD00101 | J62: General Supply Section | K62: BDD001 | L62: Business Development Department | M62: NCL00111 | N62: HEAD OFFICE NYASHISHI MWANZA | O62: NCL0011 | P62: NILE OIL: TRADING OF PETROLEUM PRODUCTS | Q62: NCL001 | R62: =VLOOKUP(Q27,'Company Code'!A2:B8,2,FALSE) -> Nile Complex Plaza Limited | U62: REF:1940cce856cccada IB TIPS FT FROM MBOGO TO NILE COMPLEX PLAZA LIMITED NILE COMPLEX PLAZ | W62: 4835139
A63: 28.12.2024 | D63: CRDB BANK PLC | E63: 63860720 | F63: =VLOOKUP(E63,'Improved Accounting codes'!C67:D2407,2,FALSE) -> #N/A | G63: 638607 | H63: =VLOOKUP(G63,'Improved Accounting codes'!A39:B2379,2,FALSE) -> Bank Charges | I63: FAD00102 | J63: Finance Section | K63: FAD001 | L63: Finance and Administration Department | M63: MGL00121 | N63: HEAD OFFICE NYASHISHI MWANZA | O63: MGL0011 | P63: MANUFACTUREING OF COMMERCIAL EXPLOSIVES | Q63: MGL001 | R63: =VLOOKUP(Q27,'Company Code'!A2:B8,2,FALSE) -> Nile Complex Plaza Limited | U63: REF:1940cce856cccada CHARGE: TIPS TRANSFER VIA IB | V63: 1500
A64: 28.12.2024 | D64: CRDB BANK PLC | E64: 56150600 | F64: =VLOOKUP(E64,'Improved Accounting codes'!C68:D2408,2,FALSE) -> CRDB TZS:0150481116500 | G64: 561506 | H64: =VLOOKUP(G64,'Improved Accounting codes'!A40:B2380,2,FALSE) -> CRDB BANK PLC | I64: FAD00102 | J64: Finance Section | K64: FAD001 | L64: Finance and Administration Department | M64: MGL00121 | N64: HEAD OFFICE NYASHISHI MWANZA | O64: MGL0011 | P64: MANUFACTUREING OF COMMERCIAL EXPLOSIVES | Q64: MGL001 | R64: Mbogo Mining and General Supply Limited | U64: REF:1940cce856cccada CHARGE: TIPS TRANSFER VIA IB | W64: 1500
A65: 28.12.2024 | D65: CRDB BANK PLC | E65: 25520102 | F65: =VLOOKUP(E65,'Improved Accounting codes'!C69:D2409,2,FALSE) -> Loans to subsidiaries | G65: 255201 | H65: =VLOOKUP(G65,'Improved Accounting codes'!A41:B2381,2,FALSE) -> Recievables on loans | I65: FAD00102 | J65: Finance Section | K65: FAD001 | L65: Finance and Administration Department | M65: MGL00121 | N65: HEAD OFFICE NYASHISHI MWANZA | O65: MGL0011 | P65: MANUFACTUREING OF COMMERCIAL EXPLOSIVES | Q65: MGL001 | R65: Mbogo Mining and General Supply Limited | U65: VAT (18%) PAYABLE ON COMMISSION AND FEES : FULL | V65: 270
A66: 28.12.2024 | D66: CRDB BANK PLC | E66: 56150600 | F66: =VLOOKUP(E66,'Improved Accounting codes'!C70:D2410,2,FALSE) -> CRDB TZS:0150481116500 | G66: 561506 | H66: =VLOOKUP(G66,'Improved Accounting codes'!A42:B2382,2,FALSE) -> CRDB BANK PLC | I66: FAD00102 | J66: Finance Section | K66: FAD001 | L66: Finance and Administration Department | M66: MGL00121 | N66: HEAD OFFICE NYASHISHI MWANZA | O66: MGL0011 | P66: MANUFACTUREING OF COMMERCIAL EXPLOSIVES | Q66: MGL001 | R66: Mbogo Mining and General Supply Limited | U66: VAT (18%) PAYABLE ON COMMISSION AND FEES : FULL | W66: 270
A67: 31.12.2024 | D67: NYASHISHI FINANCE LIMITED | E67: 40540102 | F67: =VLOOKUP(E67,'Improved Accounting codes'!C71:D2411,2,FALSE) -> Nyashishi Finance Limited | G67: 405401 | H67: =VLOOKUP(G67,'Improved Accounting codes'!A43:B2383,2,FALSE) -> Suppliers related companies | I67: FAD00102 | J67: Finance Section | K67: FAD001 | L67: Finance and Administration Department | M67: MGL00121 | N67: HEAD OFFICE NYASHISHI MWANZA | O67: MGL0011 | P67: MANUFACTUREING OF COMMERCIAL EXPLOSIVES | Q67: MGL001 | R67: Mbogo Mining and General Supply Limited | U67: REF:1941cd5d0e4d5851 IB TIPS FT FROM MBOGO TO NYASHISHI FINANCE LIMITED NYASHISHI FINANCE | V67: 4800000
A68: 31.12.2024 | D68: NYASHISHI FINANCE LIMITED | E68: 56150600 | F68: =VLOOKUP(E68,'Improved Accounting codes'!C72:D2412,2,FALSE) -> CRDB TZS:0150481116500 | G68: 561506 | H68: =VLOOKUP(G68,'Improved Accounting codes'!A44:B2384,2,FALSE) -> CRDB BANK PLC | I68: FAD00102 | J68: Finance Section | K68: FAD001 | L68: Finance and Administration Department | M68: MGL00121 | N68: HEAD OFFICE NYASHISHI MWANZA | O68: MGL0011 | P68: MANUFACTUREING OF COMMERCIAL EXPLOSIVES | Q68: MGL001 | R68: Mbogo Mining and General Supply Limited | U68: REF:1941cd5d0e4d5851 IB TIPS FT FROM MBOGO TO NYASHISHI FINANCE LIMITED NYASHISHI FINANCE | W68: 4800000
A69: 31.12.2024 | D69: CRDB BANK PLC | E69: 63860720 | F69: =VLOOKUP(E69,'Improved Accounting codes'!C73:D2413,2,FALSE) -> #N/A | G69: 638607 | H69: =VLOOKUP(G69,'Improved Accounting codes'!A45:B2385,2,FALSE) -> Bank Charges | I69: FAD00102 | J69: Finance Section | K69: FAD001 | L69: Finance and Administration Department | M69: MGL00121 | N69: HEAD OFFICE NYASHISHI MWANZA | O69: MGL0011 | P69: MANUFACTUREING OF COMMERCIAL EXPLOSIVES | Q69: MGL001 | R69: Mbogo Mining and General Supply Limited | U69: REF:1941cd5d0e4d5851 CHARGE: TIPS TRANSFER VIA IB | V69: 1500
A70: 31.12.2024 | D70: CRDB BANK PLC | E70: 56150600 | F70: =VLOOKUP(E70,'Improved Accounting codes'!C74:D2414,2,FALSE) -> CRDB TZS:0150481116500 | G70: 561506 | H70: =VLOOKUP(G70,'Improved Accounting codes'!A46:B2386,2,FALSE) -> CRDB BANK PLC | I70: FAD00102 | J70: Finance Section | K70: FAD001 | L70: Finance and Administration Department | M70: MGL00121 | N70: HEAD OFFICE NYASHISHI MWANZA | O70: MGL0011 | P70: MANUFACTUREING OF COMMERCIAL EXPLOSIVES | Q70: MGL001 | R70: Mbogo Mining and General Supply Limited | U70: REF:1941cd5d0e4d5851 CHARGE: TIPS TRANSFER VIA IB | W70: 1500
A71: 31.12.2024 | D71: GePG | E71: 62460227 | F71: =VLOOKUP(E71,'Improved Accounting codes'!C75:D2415,2,FALSE) -> Government Bill | G71: 624602 | H71: =VLOOKUP(G71,'Improved Accounting codes'!A47:B2387,2,FALSE) -> Government Fees and Similar | I71: FAD00102 | J71: Finance Section | K71: FAD001 | L71: Finance and Administration Department | M71: MGL00121 | N71: HEAD OFFICE NYASHISHI MWANZA | O71: MGL0011 | P71: MANUFACTUREING OF COMMERCIAL EXPLOSIVES | Q71: MGL001 | R71: Mbogo Mining and General Supply Limited | U71: TZ HZ1IGEDFJL9F0A6E IB GePG TIS BIL /ROC/998421433978 REC 925366300707393 MBOGO MINING AND | V71: 8000000
A72: 31.12.2024 | D72: GePG | E72: 56150600 | F72: =VLOOKUP(E72,'Improved Accounting codes'!C76:D2416,2,FALSE) -> CRDB TZS:0150481116500 | G72: 561506 | H72: =VLOOKUP(G72,'Improved Accounting codes'!A48:B2388,2,FALSE) -> CRDB BANK PLC | I72: FAD00102 | J72: Finance Section | K72: FAD001 | L72: Finance and Administration Department | M72: MGL00121 | N72: HEAD OFFICE NYASHISHI MWANZA | O72: MGL0011 | P72: MANUFACTUREING OF COMMERCIAL EXPLOSIVES | Q72: MGL001 | R72: Mbogo Mining and General Supply Limited | U72: TZ HZ1IGEDFJL9F0A6E IB GePG TIS BIL /ROC/998421433978 REC 925366300707393 MBOGO MINING AND | W72: 8000000
A73: 31.12.2024 | D73: CRDB BANK PLC | E73: 63860720 | F73: =VLOOKUP(E73,'Improved Accounting codes'!C77:D2417,2,FALSE) -> #N/A | G73: 638607 | H73: =VLOOKUP(G73,'Improved Accounting codes'!A49:B2389,2,FALSE) -> Bank Charges | I73: FAD00102 | J73: Finance Section | K73: FAD001 | L73: Finance and Administration Department | M73: MGL00121 | N73: HEAD OFFICE NYASHISHI MWANZA | O73: MGL0011 | P73: MANUFACTUREING OF COMMERCIAL EXPLOSIVES | Q73: MGL001 | R73: Mbogo Mining and General Supply Limited | U73: GePG TISS Commission | V73: 2000
A74: 31.12.2024 | D74: CRDB BANK PLC | E74: 56150600 | F74: =VLOOKUP(E74,'Improved Accounting codes'!C78:D2418,2,FALSE) -> CRDB TZS:0150481116500 | G74: 561506 | H74: =VLOOKUP(G74,'Improved Accounting codes'!A50:B2390,2,FALSE) -> CRDB BANK PLC | I74: FAD00102 | J74: Finance Section | K74: FAD001 | L74: Finance and Administration Department | M74: MGL00121 | N74: HEAD OFFICE NYASHISHI MWANZA | O74: MGL0011 | P74: MANUFACTUREING OF COMMERCIAL EXPLOSIVES | Q74: MGL001 | R74: Mbogo Mining and General Supply Limited | U74: GePG TISS Commission | W74: 2000
A75: 31.12.2024 | D75: BARNABAS ATHANAS NIBENGO | E75: 67560103 | F75: =VLOOKUP(E75,'Improved Accounting codes'!C79:D2419,2,FALSE) -> Barnabas Athanas Nibengo | G75: 675601 | H75: =VLOOKUP(G75,'Improved Accounting codes'!A51:B2391,2,FALSE) -> Uncategorised Expenses | I75: FAD00102 | J75: Finance Section | K75: FAD001 | L75: Finance and Administration Department | M75: MGL00121 | N75: HEAD OFFICE NYASHISHI MWANZA | O75: MGL0011 | P75: MANUFACTUREING OF COMMERCIAL EXPLOSIVES | Q75: MGL001 | R75: Mbogo Mining and General Supply Limited | U75: REF:1941cfbaf56919ca IB FT TO MPESA 0757851332 BARNABAS ATHANAS NIBENGO | V75: 1700000
A76: 31.12.2024 | D76: BARNABAS ATHANAS NIBENGO | E76: 56150600 | F76: =VLOOKUP(E76,'Improved Accounting codes'!C80:D2420,2,FALSE) -> CRDB TZS:0150481116500 | G76: 561506 | H76: =VLOOKUP(G76,'Improved Accounting codes'!A52:B2392,2,FALSE) -> CRDB BANK PLC | I76: FAD00102 | J76: Finance Section | K76: FAD001 | L76: Finance and Administration Department | M76: MGL00121 | N76: HEAD OFFICE NYASHISHI MWANZA | O76: MGL0011 | P76: MANUFACTUREING OF COMMERCIAL EXPLOSIVES | Q76: MGL001 | R76: Mbogo Mining and General Supply Limited | U76: REF:1941cfbaf56919ca IB FT TO MPESA 0757851332 BARNABAS ATHANAS NIBENGO | W76: 1700000
A77: 31.12.2024 | D77: CRDB BANK PLC | E77: 63860720 | F77: =VLOOKUP(E77,'Improved Accounting codes'!C81:D2421,2,FALSE) -> #N/A | G77: 638607 | H77: =VLOOKUP(G77,'Improved Accounting codes'!A53:B2393,2,FALSE) -> Bank Charges | I77: FAD00102 | J77: Finance Section | K77: FAD001 | L77: Finance and Administration Department | M77: MGL00121 | N77: HEAD OFFICE NYASHISHI MWANZA | O77: MGL0011 | P77: MANUFACTUREING OF COMMERCIAL EXPLOSIVES | Q77: MGL001 | R77: Mbogo Mining and General Supply Limited | U77: REF:1941cfbaf56919ca CHARGE: TRANSFER TO MPESA VIA IB | V77: 10169.49
A78: 31.12.2024 | D78: CRDB BANK PLC | E78: 56150600 | F78: =VLOOKUP(E78,'Improved Accounting codes'!C82:D2422,2,FALSE) -> CRDB TZS:0150481116500 | G78: 561506 | H78: =VLOOKUP(G78,'Improved Accounting codes'!A54:B2394,2,FALSE) -> CRDB BANK PLC | I78: FAD00102 | J78: Finance Section | K78: FAD001 | L78: Finance and Administration Department | M78: MGL00121 | N78: HEAD OFFICE NYASHISHI MWANZA | O78: MGL0011 | P78: MANUFACTUREING OF COMMERCIAL EXPLOSIVES | Q78: MGL001 | R78: Mbogo Mining and General Supply Limited | U78: REF:1941cfbaf56919ca CHARGE: TRANSFER TO MPESA VIA IB | W78: 10169.49
A79: 31.12.2024 | D79: CRDB BANK PLC | E79: 25520102 | F79: =VLOOKUP(E79,'Improved Accounting codes'!C83:D2423,2,FALSE) -> Loans to subsidiaries | G79: 255201 | H79: =VLOOKUP(G79,'Improved Accounting codes'!A55:B2395,2,FALSE) -> Recievables on loans | I79: FAD00102 | J79: Finance Section | K79: FAD001 | L79: Finance and Administration Department | M79: MGL00121 | N79: HEAD OFFICE NYASHISHI MWANZA | O79: MGL0011 | P79: MANUFACTUREING OF COMMERCIAL EXPLOSIVES | Q79: MGL001 | R79: Mbogo Mining and General Supply Limited | U79: VAT (18%) PAYABLE ON COMMISSION AND FEES : FULL | V79: 270
A80: 31.12.2024 | D80: CRDB BANK PLC | E80: 56150600 | F80: =VLOOKUP(E80,'Improved Accounting codes'!C84:D2424,2,FALSE) -> CRDB TZS:0150481116500 | G80: 561506 | H80: =VLOOKUP(G80,'Improved Accounting codes'!A56:B2396,2,FALSE) -> CRDB BANK PLC | I80: FAD00102 | J80: Finance Section | K80: FAD001 | L80: Finance and Administration Department | M80: MGL00121 | N80: HEAD OFFICE NYASHISHI MWANZA | O80: MGL0011 | P80: MANUFACTUREING OF COMMERCIAL EXPLOSIVES | Q80: MGL001 | R80: Mbogo Mining and General Supply Limited | U80: VAT (18%) PAYABLE ON COMMISSION AND FEES : FULL | W80: 270
A81: 31.12.2024 | D81: CRDB BANK PLC | E81: 25520102 | F81: =VLOOKUP(E81,'Improved Accounting codes'!C85:D2425,2,FALSE) -> Loans to subsidiaries | G81: 255201 | H81: =VLOOKUP(G81,'Improved Accounting codes'!A57:B2397,2,FALSE) -> Recievables on loans | I81: FAD00102 | J81: Finance Section | K81: FAD001 | L81: Finance and Administration Department | M81: MGL00121 | N81: HEAD OFFICE NYASHISHI MWANZA | O81: MGL0011 | P81: MANUFACTUREING OF COMMERCIAL EXPLOSIVES | Q81: MGL001 | R81: Mbogo Mining and General Supply Limited | U81: VAT (18%) PAYABLE ON COMMISSION AND FEES : FULL | V81: 360
A82: 31.12.2024 | D82: CRDB BANK PLC | E82: 56150600 | F82: =VLOOKUP(E82,'Improved Accounting codes'!C86:D2426,2,FALSE) -> CRDB TZS:0150481116500 | G82: 561506 | H82: =VLOOKUP(G82,'Improved Accounting codes'!A58:B2398,2,FALSE) -> CRDB BANK PLC | I82: FAD00102 | J82: Finance Section | K82: FAD001 | L82: Finance and Administration Department | M82: MGL00121 | N82: HEAD OFFICE NYASHISHI MWANZA | O82: MGL0011 | P82: MANUFACTUREING OF COMMERCIAL EXPLOSIVES | Q82: MGL001 | R82: Mbogo Mining and General Supply Limited | U82: VAT (18%) PAYABLE ON COMMISSION AND FEES : FULL | W82: 360
A83: 31.12.2024 | D83: CRDB BANK PLC | E83: 25520102 | F83: =VLOOKUP(E83,'Improved Accounting codes'!C87:D2427,2,FALSE) -> Loans to subsidiaries | G83: 255201 | H83: =VLOOKUP(G83,'Improved Accounting codes'!A59:B2399,2,FALSE) -> Recievables on loans | I83: FAD00102 | J83: Finance Section | K83: FAD001 | L83: Finance and Administration Department | M83: MGL00121 | N83: HEAD OFFICE NYASHISHI MWANZA | O83: MGL0011 | P83: MANUFACTUREING OF COMMERCIAL EXPLOSIVES | Q83: MGL001 | R83: Mbogo Mining and General Supply Limited | U83: VAT (18%) PAYABLE ON COMMISSION AND FEES : FULL | V83: 1830.51
A84: 31.12.2024 | D84: CRDB BANK PLC | E84: 56150600 | F84: =VLOOKUP(E84,'Improved Accounting codes'!C88:D2428,2,FALSE) -> CRDB TZS:0150481116500 | G84: 561506 | H84: =VLOOKUP(G84,'Improved Accounting codes'!A60:B2400,2,FALSE) -> CRDB BANK PLC | I84: FAD00102 | J84: Finance Section | K84: FAD001 | L84: Finance and Administration Department | M84: MGL00121 | N84: HEAD OFFICE NYASHISHI MWANZA | O84: MGL0011 | P84: MANUFACTUREING OF COMMERCIAL EXPLOSIVES | Q84: MGL001 | R84: Mbogo Mining and General Supply Limited | U84: VAT (18%) PAYABLE ON COMMISSION AND FEES : FULL | W84: 1830.51
